Workbook

Sheet Project type mapping - TEMPLATE
A1: Project Type | B1: Section | C1: Room Type | D1: Unit Type | E1: Category | F1: Brand | G1: Material Type | H1: Default? | I1: Customisable?
A2: Economy | B2: Modular | C2: Wet / Exposed Area | D2: Base Storage | E2: Core Material | F2: GreenPly | G2: BWP | H2: Yes | I2: Yes
A3: Economy | B3: Modular | C3: Dry / Inexposed area | D3: Wall Storage | E3: Core Material | F3: GreenPly | G3: MR | H3: Yes | I3: Yes
A4: Economy | B4: Modular | C4: Dry / Inexposed area | D4: Wardrobe | E4: Core Material | F4: GreenPly | G4: MR | H4: Yes | I4: Yes
A5: Economy | B5: Modular | C5: Dry / Inexposed area | D5: Tall Storage | E5: Core Material | F5: GreenPly | G5: MR | H5: Yes | I5: Yes
A6: Economy | B6: Modular | C6: Wet / Exposed Area | D6: Base Storage | E6: Finish Material | F6: Merino | G6: Smooth Finish | H6: Yes | I6: Yes
A7: Economy | B7: Modular | C7: Dry / Inexposed area | D7: Wall Storage | E7: Finish Material | F7: Merino | G7: Smooth Finish | H7: Yes | I7: Yes
A8: Economy | B8: Modular | C8: Dry / Inexposed area | D8: Tall Storage | E8: Finish Material | F8: Merino | G8: Smooth Finish | H8: Yes | I8: Yes
A9: Economy | B9: Modular | C9: Wet / Exposed Area | D9: Base Storage | E9: Hinges | F9: Hettich | G9: Onsys | H9: Yes | I9: No
A10: Economy | B10: Modular | C10: Dry / Inexposed area | D10: Wall Storage | E10: Hinges | F10: Hettich | G10: Onsys | H10: Yes | I10: No
A11: Economy | B11: Modular | C11: Dry / Inexposed area | D11: Tall Storage | E11: Hinges | F11: Hettich | G11: Onsys | H11: Yes | I11: No
A12: Economy | B12: Modular | C12: Dry / Inexposed area | D12: Wardrobe | E12: Hinges | F12: Hettich | G12: Onsys | H12: Yes | I12: No
... A45: Luxury | B45: Modular | C45: Dry / Inexposed area | D45: Wardrobe | E45: Hinges | F45: Hettich | G45: Onsys | H45: Yes | I45: No

Sheet Economy
A1: Project Type | B1: Section | C1: Room Type | D1: Unit Type | E1: Panel type | F1: Category | G1: Material Type | H1: Brand | I1: DESCRIPTION | J1: Rate | K1: Mark up | L1: Margin | M1: Selling Price
A2: SMOOTH FINISH | I2: Description format : Supply and installation of **Unit Type** with **Core material** **Finish Material****Hinges**
A3: Economy | B3: Modular | C3: Wet / Exposed Area | D3: Base Storage, Wall Storage, Tall Storage, Wardrobe | E3: Carcass/shutter | F3: Core Material, Finish Material, Hinges | G3: Carcass - BWP / Shutter - HDF, Smooth Finish, Soft Close | H3: Carcass - Kit ply Vista Marine / Shutter - Green Panel, Ebco , Sleek , Abhiyam , Catch Plus , Virgo | I3: Supply and installation of Base storage unit with BWP Carcass, HDF Shutter, Smooth finish laminate and soft close hinges | J3: 1475 | K3: 0.25 | L3: =J3*K3 -> 368.75 | M3: =J3+L3 -> 1843.75
I4: Supply and installation of Wall storage unit with BWP Carcass, HDF Shutter, Smooth finish laminate and soft close hinges
I5: Supply and installation of Tall storage unit with BWP Carcass, HDF Shutter, Smooth finish laminate and soft close hinges
I6: Supply and installation of Wardobe unit with BWP Carcass, HDF Shutter, Smooth finish laminate and soft close hinges
C7: Wet / Exposed Area | D7: Base Storage - Inner 1mm, Wall Storage - inner 1mm, Tall Storage - Inner 1mm | E7: Carcass, Shutter | F7: Core Material, Finish Material, Hinges | G7: Carcass - BWP / Shutter - HDF, Smooth Finish , Soft Close | I7: Supply and installation of Base storage - Inner 1mm unit with BWP Carcass, HDF Shutter, Smooth finish laminate and soft close hinges | J7: 1625 | K7: 0.25 | L7: =J7*K7 -> 406.25 | M7: =J7+L7 -> 2031.25
I8: Supply and installation of Wall storage - Inner 1mm unit with BWP Carcass, HDF Shutter, Smooth finish laminate and soft close hinges
I9: Supply and installation of Tall storage - Inner 1mm unit with BWP Carcass, HDF Shutter, Smooth finish laminate and soft close hinges
A10: Economy | B10: Modular | C10: Wet / Exposed Area | D10: Base Storage, Wall Storage, Tall Storage, Wardrobe | E10: Carcass/shutter | F10: Core Material, Finish Material, Hinges | G10: Carcass - BWP / Shutter - Plywood Border with Clear / Tinted Glass , Soft Close, Smooth Finish | H10: Ebco , Sleek , Abhiyam , Catch Plus , Virgo, Carcass / Shutter - Kitply Vist Marine with Glass | I10: Supply and installation of Base storage unit with BWP Carcass, Plywood Border with Clear/Tinted Glass Shutter, Smooth finish laminate and soft close hinges | J10: 1880 | K10: 0.25 | L10: =J10*K10 -> 470 | M10: =J10+L10 -> 2350
I11: Supply and installation of Wall storage unit with BWP Carcass, Plywood Border with Clear/Tinted Glass Shutter, Smooth finish laminate and soft close hinges
I12: Supply and installation of Tall storage unit with BWP Carcass, Plywood Border with Clear/Tinted Glass Shutter, Smooth finish laminate and soft close hinges
I13: Supply and installation of Wardrobe with BWP Carcass, Plywood Border with Clear/Tinted Glass Shutter, Smooth finish laminate and soft close hinges
A14: Economy | B14: Modular | C14: Wet / Exposed Area | D14: Base Storage, Wall Storage, Tall Storage, Wardrobe | E14: Carcass/shutter | F14: Core Material, Finish Material, Hinges | G14: Carcass - BWP / Shutter - Plywood Border with Fluted Glass , Smooth Finish , Soft Close | H14: Ebco , Sleek , Abhiyam , Catch Plus , Virgo, Carcass / Shutter - Kitply Vist Marine with Glass | I14: Supply and installation of Base storage unit with BWP Carcass, Plywood Border with Fluted Glass Shutter, Smooth finish laminate and soft close hinges | J14: 2000 | K14: 0.25 | L14: =J14*K14 -> 500 | M14: =J14+L14 -> 2500
I15: Supply and installation of Wall storage unit with BWP Carcass, Plywood Border with Fluted Glass Shutter, Smooth finish laminate and soft close hinges
I16: Supply and installation of Tall storage unit with BWP Carcass, Plywood Border with Fluted Glass Shutter, Smooth finish laminate and soft close hinges
I17: Supply and installation of Wardrobe with BWP Carcass, Plywood Border with Fluted Glass Shutter, Smooth finish laminate and soft close hinges
A18: Economy | B18: Modular | C18: Wet / Exposed Area | D18: Base Storage, Wall Storage, Tall Storage, Wardrobe | E18: Carcass/shutter | F18: Core Material, Finish Material, Hinges | G18: Carcass - BWP / Shutter - Black / Silver colour Aluminium Profile with Clear or Tinted Glass, Smooth Finish , Soft Close | H18: Sleek , Ebco, Abhiyam , Catch Plus , Virgo, Carcass -Kitply Vista Marine / Shutter - Imported Aluminium Profile Shutters | I18: Supply and installation of Base storage unit with BWP Carcass, Aluminium Profile with Clear/Tinted Glass Shutter, Smooth finish laminate and soft close hinges | J18: 2325 | K18: 0.25 | L18: =J18*K18 -> 581.25 | M18: =J18+L18 -> 2906.25
I19: Supply and installation of Wall storage unit with BWP Carcass, Aluminium Profile with Clear/Tinted Glass Shutter, Smooth finish laminate and soft close hinges
I20: Supply and installation of Tall storage unit with BWP Carcass, Aluminium Profile with Clear/Tinted Glass Shutter, Smooth finish laminate and soft close hinges
I21: Supply and installation of Wardrobe with BWP Carcass, Aluminium Profile with Clear/Tinted Glass Shutter, Smooth finish laminate and soft close hinges
A22: Economy | B22: Modular | C22: Wet / Exposed Area | D22: Base Storage, Wall Storage, Tall Storage, Wardrobe | E22: Carcass/shutter | F22: Core Material, Finish Material, Hinges | G22: Carcass - BWP / Shutter - Black / Silver colour Aluminium Profile with Fluted Glass, Smooth Finish , Soft Close | H22: Sleek , Ebco, Abhiyam , Catch Plus , Virgo, Carcass -Kitply Vista Marine / Shutter - Imported Aluminium Profile Shutters | J22: 2425 | K22: 0.25 | L22: =J22*K22 -> 606.25 | M22: =J22+L22 -> 3031.25
A23: Economy | B23: Modular | C23: Wet / Exposed Area | D23: Base Storage, Wall Storage, Tall Storage, Wardrobe | E23: Carcass/shutter | F23: Core Material, Finish Material, Hinges | G23: Carcass - BWP / Shutter - Gold / Rose Gold colour Aluminium Profile with Clear or Tinted Glass, Soft Close, Smooth Finish | H23: Sleek , Ebco, Abhiyam , Catch Plus , Virgo, Carcass -Kitply Vista Marine / Shutter - Imported Aluminium Profile Shutters | J23: 2425 | K23: 0.25 | L23: =J23*K23 -> 606.25 | M23: =J23+L23 -> 3031.25
A24: Economy | B24: Modular | C24: Wet / Exposed Area | D24: Base Storage, Wall Storage, Tall Storage, Wardrobe | E24: Carcass/shutter | F24: Core Material, Finish Material, Hinges | G24: Carcass - BWP / Shutter - Gold / Rose Gold colour Aluminium Profile with Fluted Glass, Smooth Finish , Soft Close | H24: Sleek , Ebco, Abhiyam , Catch Plus , Virgo, Carcass -Kitply Vista Marine / Shutter - Imported Aluminium Profile Shutters | J24: 2525 | K24: 0.25 | L24: =J24*K24 -> 631.25 | M24: =J24+L24 -> 3156.25
A25: Economy | B25: Modular | C25: Wet / Exposed Area | D25: Base Storage, Wall Storage, Tall Storage, Wardrobe | E25: Carcass/shutter | F25: Core Material, Finish Material, Hinges | G25: Carcass Inner 1mm- BWP / Shutter - Plywood Border with Clear / Tinted Glass , Smooth Finish , Soft Close | H25: Ebco , Sleek , Abhiyam , Catch Plus , Virgo, Carcass / Shutter - Kitply Vist Marine with Glass | J25: 2130 | K25: 0.25 | L25: =J25*K25 -> 532.5 | M25: =J25+L25 -> 2662.5
A26: Economy | B26: Modular | C26: Wet / Exposed Area | D26: Base Storage, Wall Storage, Tall Storage, Wardrobe | E26: Carcass/shutter | F26: Core Material, Finish Material, Hinges | G26: Carcass inner 1mm - BWP / Shutter - Plywood Border with Fluted Glass , Smooth Finish , Soft Close | H26: Ebco , Sleek , Abhiyam , Catch Plus , Virgo, Carcass / Shutter - Kitply Vist Marine with Glass | J26: 2230 | K26: 0.25 | L26: =J26*K26 -> 557.5 | M26: =J26+L26 -> 2787.5
A27: Economy | B27: Modular | C27: Wet / Exposed Area | D27: Base Storage, Wall Storage, Tall Storage, Wardrobe | E27: Carcass/shutter | F27: Core Material, Finish Material, Hinges | G27: Carcass Inner 1mm- BWP / Shutter - Black / Silver colour Aluminium Profile with Clear or Tinted Glass , Smooth Finish , Soft Close | H27: Sleek , Ebco, Abhiyam , Catch Plus , Virgo, Carcass -Kitply Vista Marine / Shutter - Imported Aluminium Profile Shutters | J27: 2475 | K27: 0.25 | L27: =J27*K27 -> 618.75 | M27: =J27+L27 -> 3093.75
A28: Economy | B28: Modular | C28: Wet / Exposed Area | D28: Base Storage, Wall Storage, Tall Storage, Wardrobe | E28: Carcass/shutter | F28: Core Material, Finish Material, Hinges | G28: Carcass Inner 1mm - BWP / Shutter - Black / Silver colour Aluminium Profile with Fluted Glass, Smooth Finish , Soft Close | H28: Sleek , Ebco, Abhiyam , Catch Plus , Virgo, Carcass -Kitply Vista Marine / Shutter - Imported Aluminium Profile Shutters | J28: 2575 | K28: 0.25 | L28: =J28*K28 -> 643.75 | M28: =J28+L28 -> 3218.75
A29: Economy | B29: Modular | C29: Wet / Exposed Area | D29: Base Storage, Wall Storage, Tall Storage, Wardrobe | E29: Carcass/shutter | F29: Core Material, Finish Material, Hinges | G29: Carcass Inner 1mm - BWP / Shutter - Gold / Rose Gold colour Aluminium Profile with Fluted Glass, Smooth Finish , Soft Close | H29: Sleek , Ebco, Abhiyam , Catch Plus , Virgo, Carcass -Kitply Vista Marine / Shutter - Imported Aluminium Profile Shutters | J29: 2575 | K29: 0.25 | L29: =J29*K29 -> 643.75 | M29: =J29+L29 -> 3218.75
A30: Economy | B30: Modular | C30: Wet / Exposed Area | D30: Base Storage, Wall Storage, Tall Storage, Wardrobe | E30: Carcass/shutter | F30: Core Material, Finish Material, Hinges | G30: Carcass Inner 1mm- BWP / Shutter - Gold / Rose Gold colour Aluminium Profile with Clear or Tinted Glass, Smooth Finish , Soft Close | H30: Sleek , Ebco, Abhiyam , Catch Plus , Virgo, Carcass -Kitply Vista Marine / Shutter - Imported Aluminium Profile Shutters | J30: 2675 | K30: 0.25 | L30: =J30*K30 -> 668.75 | M30: =J30+L30 -> 3343.75
A31: Economy | B31: Modular | C31: Wet / Exposed Area | D31: Curved Shape Base Storage unit | E31: Carcass/shutter | F31: Core Material, Finish Material, Hinges | G31: Carcass - BWP / Shutter - HDF, Smooth Finish , Soft Close | H31: Carcass - Kit ply Vista Marine / Shutter - Green Panel, Ebco , Sleek , Abhiyam , Catch Plus , Virgo | J31: 1850 | K31: 0.25 | L31: =J31*K31 -> 462.5 | M31: =J31+L31 -> 2312.5
A32: Economy | B32: Modular | C32: Wet / Exposed Area | D32: Curved Shape Drawer Storage unit | E32: Carcass/shutter | F32: Core Material, Finish Material | G32: Carcass - BWP / Shutter - HDF, Smooth Finish | H32: Carcass - Kit ply Vista Marine / Shutter - Green Panel, Catch Plus , Virgo , Abhiyam | J32: 1850 | K32: 0.25 | L32: =J32*K32 -> 462.5 | M32: =J32+L32 -> 2312.5
A33: Economy | B33: Modular | C33: Wet / Exposed Area | D33: Open Unit - Inner 0.8mm | E33: Carcass | F33: Core Material, Finish Material | G33: CARCASS - BWP, Smooth Finish | H33: Carcass - Kit ply Vista Marine, Abhiyam, Catch Plus , Virgo | I33: Supply and installation of Open unit - Inner 0.8mm with BWP Carcass and Smooth finish laminate | J33: 1250 | K33: 0.25 | L33: =J33*K33 -> 312.5 | M33: =J33+L33 -> 1562.5
A34: Economy | B34: Modular | C34: Wet / Exposed Area | D34: Open Unit - Inner 1mm | E34: Carcass | F34: Core Material, Finish Material | G34: CARCASS - BWP, Smooth Finish | H34: Carcass - Kit ply Vista Marine, Abhiyam, Catch Plus , Virgo | I34: Supply and installation of Open unit - Inner 1mm with BWP Carcass and Smooth finish laminate | J34: 1475 | K34: 0.25 | L34: =J34*K34 -> 368.75 | M34: =J34+L34 -> 1843.75
A35: Economy | B35: Modular | C35: Wet / Exposed Area | D35: Loft | E35: Frame and Shutter | F35: Core Material, Finish Material, Hinges | G35: Smooth Finish, Soft Close, Frame - BWP / Shutter - HDF | H35: Ebco , Sleek , Abhiyam , Catch Plus , Virgo, Frame- Kit ply Vista Marine / Shutter - Green Panel, Fortune gold | J35: 872 | K35: 0.25 | L35: =J35*K35 -> 218 | M35: =J35+L35 -> 1090
A36: Economy | B36: Modular | C36: Wet / Exposed Area | D36: Ledge | E36: Ledge -25mm | F36: Finish Material, Core Material | G36: Smooth Finish , CARCASS - BWP | H36: Ledge - Kit Ply Vista Marine, Abhiyam , Catch Plus , Virgo | J36: 758 | K36: 0.25 | L36: =J36*K36 -> 189.5 | M36: =J36+L36 -> 947.5
A37: Economy | B37: Modular | C37: Wet / Exposed Area | D37: Ledge | E37: Ledge -36mm | F37: Finish Material, Core Material | G37: Smooth Finish , CARCASS - BWP | H37: Ledge - Kit Ply Vista Marine, Abhiyam , Catch Plus , Virgo | J37: 758 | K37: 0.25 | L37: =J37*K37 -> 189.5 | M37: =J37+L37 -> 947.5
A38: Economy | B38: Modular | C38: Wet / Exposed Area | D38: Ledge | E38: Ledge -50mm | F38: Finish Material, Core Material | G38: Smooth Finish , CARCASS - BWP | H38: Ledge - Kit Ply Vista Marine, Abhiyam , Catch Plus , Virgo | J38: 958 | K38: 0.25 | L38: =J38*K38 -> 239.5 | M38: =J38+L38 -> 1197.5
A39: Economy | B39: Modular | C39: Wet / Exposed Area | D39: Partition | E39: Partition -75mm | F39: Finish Material, Core Material | G39: Smooth Finish , CARCASS - BWP | H39: Kit Ply Vista Marine , Abhiyam , Catch Plus , Virgo | J39: 1575 | K39: 0.25 | L39: =J39*K39 -> 393.75 | M39: =J39+L39 -> 1968.75
A40: Economy | B40: Modular | C40: Wet / Exposed Area | D40: Panel | E40: Curved Shape Panel | F40: Finish Material, Core Material | G40: Smooth Finish , CARCASS - BWP | H40: Kit Ply Vista Marine, Catch Plus , Abhiyam , Virgo | J40: 1025 | K40: 0.25 | L40: =J40*K40 -> 256.25 | M40: =J40+L40 -> 1281.25
A41: Economy | B41: Modular | C41: Wet / Exposed Area | D41: Panel | E41: Wallpanel , pelmet , Ceiling Panel , Base panel / Side panel, Jam Panel, Chimney Panel | F41: Finish Material, Core Material | G41: Smooth Finish , CARCASS - BWP | H41: Kit Ply Vista Marine, Catch Plus , Abhiyam , Virgo | I41: Supply and installation of Chimney Panel with BWP Carcass and Smooth finish laminate | J41: 875 | K41: 0.25 | L41: =J41*K41 -> 218.75 | M41: =J41+L41 -> 1093.75
A46: Economy | B46: Modular | C46: Dry / Inexposed area | D46: Base Storage, Wall Storage, Tall Storage, Wardrobe, Drawer Storage | E46: Carcass/shutter | F46: Core Material, Finish Material, Hinges | G46: Smooth Finish, Soft Close, Carcass - MR Premium / Shutter - HDF | H46: Carcass - Kitply Plus / Shutter - Green Panel, Ebco , Sleek , Catch Plus , Abhiyam , Virgo | I46: Supply and installation of Base storage unit with MR Premium Carcass, HDF Shutter, Smooth finish laminate and soft close hinges | J46: 1375 | K46: 0.25 | L46: =J46*K46 -> 343.75 | M46: =J46+L46 -> 1718.75
I47: Supply and installation of Wall storage unit with MR Premium Carcass, HDF Shutter, Smooth finish laminate and soft close hinges | P47: Providing a base storage unit with a smooth finish laminate.- Handle | Q47: 1500 | R47: =Q47-125 -> 1375
I48: Supply and installation of Tall storage unit with MR Premium Carcass, HDF Shutter, Smooth finish laminate and soft close hinges | P48: Providing a base storage unit with a smooth finish laminate - Profile Handle – G / Gola Profile | Q48: =Q47+150 -> 1650 | R48: =Q48-125 -> 1525
I49: Supply and installation of Wardrobe with MR Premium Carcass, HDF Shutter, Smooth finish laminate and soft close hinges | P49: Providing a base storage unit with a smooth finish laminate - Handless - Finger groove | Q49: =Q47 -> 1500 | R49: =Q49-125 -> 1375
I50: Supply and installation of Drawer Storage with MR Premium Carcass, HDF Shutter, Smooth finish laminate and soft close hinges | P50: Providing a Curved Shape base storage unit with a smooth finish laminate. | Q50: =Q47+350 -> 1850 | R50: =Q50-125 -> 1725
C51: Dry / Inexposed area | D51: Base Storage - Inner 1mm, Wall Storage - inner 1mm, Tall Storage - Inner 1mm | E51: Carcass, Shutter | F51: Core Material, Finish Material, Hinges | G51: Carcass - MR Premium / Shutter - HDF, Smooth Finish , Soft Close | I51: Supply and installation of Base storage - Inner 1mm unit with MR Premium Carcass, HDF Shutter, Smooth finish laminate and soft close hinges | J51: =J46+150 -> 1525 | K51: 0.25 | L51: =J51*K51 -> 381.25 | M51: =J51+L51 -> 1906.25 | P51: Providing a Curved Shape base storage unit with a smooth finish laminate - Finger groove | Q51: =Q47+350 -> 1850 | R51: =Q51-125 -> 1725
I52: Supply and installation of Wall storage - Inner 1mm unit with MR Premium Carcass, HDF Shutter, Smooth finish laminate and soft close hinges | P52: Providing a storage unit featuring an HDHMR sandwiched glass shutter with a rattan finish and a smooth laminate surface. | Q52: =Q47+350 -> 1850 | R52: =Q52-125 -> 1725
I53: Supply and installation of Tall storage - Inner 1mm unit with MR Premium Carcass, HDF Shutter, Smooth finish laminate and soft close hinges | P53: Providing a storage unit featuring an HDHMR sandwiched glass shutter with a rattan finish and a smooth laminate surface. - Gola profile Handle | Q53: =Q47+500 -> 2000 | R53: =Q53-125 -> 1875
A54: Economy | B54: Modular | C54: Dry / Inexposed area | D54: Base Storage, Wall Storage, Tall Storage, Wardrobe | E54: Carcass/shutter | F54: Core Material, Finish Material, Hinges | G54: Carcass - MR - Premium/ Shutter - Plywood Border with Clear / Tinted Glass , Smooth Finish , Soft Close | H54: Carcass - Kitply Plus / Shutter - Green Panel, Ebco , Sleek , Catch Plus , Abhiyam , Virgo | J54: 1780 | K54: 0.25 | L54: =J54*K54 -> 445 | M54: =J54+L54 -> 2225 | P54: Providing a storage unit with a smooth finish laminate featuring a mix laminate design. | Q54: =175+Q47 -> 1675 | R54: =Q54-125 -> 1550
A55: Economy | B55: Modular | C55: Dry / Inexposed area | D55: Base Storage, Wall Storage, Tall Storage, Wardrobe | E55: Carcass/shutter | F55: Core Material, Finish Material, Hinges | G55: Carcass - MR - Premium / Shutter - Ply wood border with Fluted Glass , Smooth Finish , Soft Close | H55: Ebco , Sleek , Abhiyam , Catch Plus , Virgo, Carcass - Kit ply Vista Marine / Shutter - Green Panel with Glass | I55: Supply and installation of Base storage unit with MR Premium Carcass, Plywood Border with Fluted Glass Shutter, Smooth finish laminate and soft close hinges | J55: 1900 | K55: 0.25 | L55: =J55*K55 -> 475 | M55: =J55+L55 -> 2375 | P55: Providing a storage unit with a smooth finish laminate featuring a mix laminate design - Finger Froove | Q55: =175+Q47 -> 1675 | R55: =Q55-125 -> 1550
I56: Supply and installation of Wall storage unit with MR Premium Carcass, Plywood Border with Fluted Glass Shutter, Smooth finish laminate and soft close hinges | P56: Providing a Smooth Finish laminate storage unit featuring a plywood border with Clear or Tinted glass. | Q56: =Q47+380 -> 1880 | R56: =Q56-125 -> 1755
A57: Economy | B57: Modular | C57: Dry / Inexposed area | D57: Base Storage, Wall Storage, Tall Storage, Wardrobe | E57: Carcass/shutter | F57: Core Material, Finish Material, Hinges | G57: Carcass - MR - Premium / Shutter - Black / Silver colour Aluminium Profile with Clear or Tinted Glass , Smooth Finish , Soft Close | H57: Carcass - Kit Ply Plus / Shutter - Imported Aluminium Profile shutter, Sleek , Ebco, Abhiyam , Catch Plus , Virgo | I57: Supply and installation of Base storage unit with MR Premium Carcass, Aluminium profile shutter with Tinted glass, Smooth finish laminate and soft close hinges | J57: 2125 | K57: 0.25 | L57: =J57*K57 -> 531.25 | M57: =J57+L57 -> 2656.25 | P57: Providing a Smooth Finish laminate storage unit featuring a plywood border with Fluted glass. | Q57: =Q47+500 -> 2000 | R57: =Q57-125 -> 1875
I58: Supply and installation of Wall storage unit with MR Premium Carcass, Aluminium profile shutter with Tinted glass, Smooth finish laminate and soft close hinges | P58: Providing a Open storage unit with a inner 0.8mm Laminate and Outer 1mm smooth finish laminate. | Q58: =Q47-250 -> 1250 | R58: =Q58-125 -> 1125
A59: Economy | B59: Modular | C59: Dry / Inexposed area | D59: Base Storage, Wall Storage, Tall Storage, Wardrobe | E59: Carcass/shutter | F59: Core Material, Finish Material, Hinges | G59: Carcass - MR - Premium / Shutter - Black / Silver colour Aluminium Profile with Fluted Glass, Soft Close, Smooth Finish | H59: Carcass - Kit Ply Plus / Shutter - Imported Aluminium Profile shutter, Sleek , Ebco, Abhiyam , Catch Plus , Virgo | J59: 2225 | K59: 0.25 | L59: =J59*K59 -> 556.25 | M59: =J59+L59 -> 2781.25 | P59: Providing a Open storage unit with Inner and Outer 1mm smooth finish laminate. | Q59: =Q47 -> 1500 | R59: =Q59-125 -> 1375
P60: Providing a storage unit with Inner and Outer 1mm smooth finish laminate - Handle | Q60: =Q47+150 -> 1650 | R60: =Q60-125 -> 1525
P61: Providing a storage unit with Inner and Outer 1mm smooth finish laminate - Finger groove | Q61: =Q47+150 -> 1650 | R61: =Q61-125 -> 1525
P62: Providing loft frame and shutters (excluding base ply) - Smooth Finish Laminate | Q62: 740 | R62: =Q62-125 -> 615
A63: Economy | B63: Modular | C63: Dry / Inexposed area | D63: Base Storage, Wall Storage, Tall Storage, Wardrobe | E63: Carcass/shutter | F63: Core Material, Finish Material, Hinges | G63: Carcass - MR - Premium / Shutter - Gold Colour Aluminium profile with Clear Glass , Smooth Finish , Soft Close | H63: Carcass - Kit Ply Plus / Shutter - Imported Aluminium Profile shutter, Sleek , Ebco, Abhiyam , Catch Plus , Virgo | J63: 2225 | K63: 0.25 | L63: =J63*K63 -> 556.25 | M63: =J63+L63 -> 2781.25 | P63: Providing loft frame and shutters (excluding base ply) - Handless Finger groove - Smooth Finish Laminate | Q63: 740 | R63: =Q63-125 -> 615
A64: Economy | B64: Modular | C64: Dry / Inexposed area | D64: Base Storage, Wall Storage, Tall Storage, Wardrobe | E64: Carcass/shutter | F64: Core Material, Finish Material, Hinges | G64: Carcass - MR - Premium / Shutter - Gold Colour Aluminium profile with Fluted Glass , Smooth Finish , Soft Close | H64: Carcass - Kit Ply Plus / Shutter - Imported Aluminium Profile shutter, Sleek , Ebco, Abhiyam , Catch Plus , Virgo | J64: 2325 | K64: 0.25 | L64: =J64*K64 -> 581.25 | M64: =J64+L64 -> 2906.25 | P64: Providing exposed or base panels - (chimney panels, loft bottom panels, or loft side panels.)- Smooth Finish Laminate | Q64: 900 | R64: =Q64-125 -> 775
A65: Economy | B65: Modular | C65: Dry / Inexposed area | D65: Base Storage, Wall Storage, Tall Storage, Wardrobe | E65: Carcass/shutter | F65: Core Material, Finish Material, Hinges | G65: Carcass Inner 1mm - MR - Premium/ Shutter - Plywood Border with Clear / Tinted Glass , Smooth Finish , Soft Close | H65: Carcass - Kit Ply Plus / Shutter - Imported Aluminium Profile shutter, Sleek , Ebco, Abhiyam , Catch Plus , Virgo | J65: 2030 | K65: 0.25 | L65: =J65*K65 -> 507.5 | M65: =J65+L65 -> 2537.5 | P65: Providing ledges 25mm / 36mm thickness with a smooth finish laminate. | Q65: 700 | R65: =Q65-125 -> 575
A66: Economy | B66: Modular | C66: Dry / Inexposed area | D66: Base Storage, Wall Storage, Tall Storage, Wardrobe | E66: Carcass/shutter | F66: Core Material, Finish Material, Hinges | G66: Carcass Inner 1mm- MR - Premium / Shutter - Ply wood border with Fluted Glass , Smooth Finish , Soft Close | H66: Carcass - Kit Ply Plus / Shutter - Imported Aluminium Profile shutter, Sleek , Ebco, Abhiyam , Catch Plus , Virgo | J66: 2130 | K66: 0.25 | L66: =J66*K66 -> 532.5 | M66: =J66+L66 -> 2662.5 | P66: Providing ledges 50mm thickness with a smooth finish laminate. | Q66: 850 | R66: =Q66-125 -> 725
A67: Economy | B67: Modular | C67: Dry / Inexposed area | D67: Base Storage, Wall Storage, Tall Storage, Wardrobe | E67: Carcass/shutter | F67: Core Material, Finish Material, Hinges | G67: Carcass inner 1mm- MR - Premium / Shutter - Black / Silver colour Aluminium Profile with Clear or Tinted Glass , Smooth Finish , Soft Close | H67: Carcass - Kit Ply Plus / Shutter - Imported Aluminium Profile shutter, Sleek , Ebco, Abhiyam , Catch Plus , Virgo | J67: 2375 | K67: 0.25 | L67: =J67*K67 -> 593.75 | M67: =J67+L67 -> 2968.75 | P67: Providing wall Panel with Smooth Laminate Finish | Q67: 600 | R67: =Q67-125 -> 475
A68: Economy | B68: Modular | C68: Dry / Inexposed area | D68: Base Storage, Wall Storage, Tall Storage, Wardrobe | E68: Carcass/shutter | F68: Core Material, Finish Material, Hinges | G68: Carcass Inner 1mm - MR - Premium / Shutter - Black / Silver colour Aluminium Profile with Fluted Glass , Smooth Finish , Soft Close | H68: Carcass - Kit Ply Plus / Shutter - Imported Aluminium Profile shutter, Sleek , Ebco, Abhiyam , Catch Plus , Virgo | J68: 2475 | K68: 0.25 | L68: =J68*K68 -> 618.75 | M68: =J68+L68 -> 3093.75 | P68: Providing Panel work in Ceiling with Smooth Laminate Finish | Q68: 1050 | R68: =Q68-125 -> 925
A69: Economy | B69: Modular | C69: Dry / Inexposed area | D69: Base Storage, Wall Storage, Tall Storage, Wardrobe | E69: Carcass/shutter | F69: Core Material, Finish Material, Hinges | G69: Carcass Inner 1mm - MR - Premium / Shutter - Gold Colour Aluminium profile with Clear Glass , Smooth Finish , Soft Close | H69: Carcass - Kit Ply Plus / Shutter - Imported Aluminium Profile shutter, Sleek , Ebco, Abhiyam , Catch Plus , Virgo | J69: 2475 | K69: 0.25 | L69: =J69*K69 -> 618.75 | M69: =J69+L69 -> 3093.75 | P69: Providing Curved wall Panel with Smooth Laminate Finish | Q69: 800 | R69: =Q69-125 -> 675
A70: Economy | B70: Modular | C70: Dry / Inexposed area | D70: Base Storage, Wall Storage, Tall Storage, Wardrobe | E70: Carcass/shutter | F70: Core Material, Finish Material, Hinges | G70: Carcass Inner 1mm - MR - Premium / Shutter - Gold Colour Aluminium profile with Fluted Glass , Smooth Finish , Soft Close | H70: Carcass - Kit Ply Plus / Shutter - Imported Aluminium Profile shutter, Sleek , Ebco, Abhiyam , Catch Plus , Virgo | J70: 2575 | K70: 0.25 | L70: =J70*K70 -> 643.75 | M70: =J70+L70 -> 3218.75 | P70: Providing Arch Shape wall Panel with Smooth Laminate Finish | Q70: 900 | R70: =Q70-125 -> 775
A71: Economy | B71: Modular | C71: Dry / Inexposed area | D71: Curved Shape Base Storage unit | E71: Carcass/shutter | F71: Core Material, Finish Material, Hinges | G71: Carcass - MR Premium / Shutter - HDF, Smooth Finish , Soft Close | H71: Ebco , Sleek , Abhiyam , Catch Plus , Virgo, Carcass - Kitply Plus / Shutter - Green Panel | J71: 1750 | K71: 0.25 | L71: =J71*K71 -> 437.5 | M71: =J71+L71 -> 2187.5 | P71: Providing 75mm thick Plywood partition with the Minimal CNC pattern - Smooth Finish Laminate | Q71: 1600 | R71: =Q71-125 -> 1475
A72: Economy | B72: Modular | C72: Dry / Inexposed area | D72: Curved Shape Drawer Storage unit | E72: Carcass/shutter | F72: Core Material, Finish Material | G72: Carcass - MR Premium / Shutter - HDF, Smooth Finish | H72: Catch Plus , Virgo , Abhiyam, Carcass - Kitply Plus / Shutter - Green Panel | J72: 1750 | K72: 0.25 | L72: =J72*K72 -> 437.5 | M72: =J72+L72 -> 2187.5
A73: Economy | B73: Modular | C73: Dry / Inexposed area | D73: Tambour Storage | E73: Carcass | F73: Core Material, Finish Material | G73: Smooth Finish, Carcass - MR - Premium | H73: Carcass - Kitply plus | J73: 1125 | K73: 0.25 | L73: =J73*K73 -> 281.25 | M73: =J73+L73 -> 1406.25
A74: Economy | B74: Modular | C74: Dry / Inexposed area | D74: Open Unit - Inner 1mm | E74: Carcass | F74: Core Material, Finish Material | G74: Smooth Finish, Carcass - MR - Premium | H74: Abhiyam, Catch Plus , Virgo, Carcass - Kitply plus | J74: 1375 | K74: 0.25 | L74: =J74*K74 -> 343.75 | M74: =J74+L74 -> 1718.75
A75: Economy | B75: Modular | C75: Dry / Inexposed area | D75: Loft | E75: Frame and Shutter | F75: Core Material, Finish Material, Hinges | G75: Smooth Finish , Soft Close, Frame - MR Premium / Shutter - HDF | H75: Ebco , Sleek , Abhiyam , Catch Plus , Virgo, Frame - Kit ply Plus / Shutter - Green Panel | I75: Supply and installation of Loft Frame and Shutter unit with MR Premium Frame, HDF Shutter, Smooth finish laminate and Soft Close hinges | J75: 772 | K75: 0.25 | L75: =J75*K75 -> 193 | M75: =J75+L75 -> 965
A76: Economy | B76: Modular | C76: Dry / Inexposed area | D76: Ledge | E76: Ledge -25mm | F76: Finish Material, Core Material | G76: Smooth Finish, Carcass - MR - Premium | H76: Abhiyam , Catch Plus , Virgo, Kitply plus | I76: Supply and installation of Ledge with 25mm Ledge MR Premium and Smooth finish laminate | J76: 658 | K76: 0.25 | L76: =J76*K76 -> 164.5 | M76: =J76+L76 -> 822.5
A77: Economy | B77: Modular | C77: Dry / Inexposed area | D77: Ledge | E77: Ledge -36mm | F77: Finish Material, Core Material | G77: Smooth Finish, Carcass - MR - Premium | H77: Abhiyam , Catch Plus , Virgo, Kitply plus | J77: 658 | K77: 0.25 | L77: =J77*K77 -> 164.5 | M77: =J77+L77 -> 822.5
A78: Economy | B78: Modular | C78: Dry / Inexposed area | D78: Ledge | E78: Ledge -50mm | F78: Finish Material, Core Material | G78: Smooth Finish, Carcass - MR - Premium | H78: Abhiyam , Catch Plus , Virgo, Kitply plus | J78: 858 | K78: 0.25 | L78: =J78*K78 -> 214.5 | M78: =J78+L78 -> 1072.5
A79: Economy | B79: Modular | C79: Dry / Inexposed area | D79: Partition | E79: Partition -75mm | F79: Finish Material, Core Material | G79: Smooth Finish, Carcass - MR - Premium | H79: Abhiyam , Catch Plus , Virgo, Kitply plus | J79: 1475 | K79: 0.25 | L79: =J79*K79 -> 368.75 | M79: =J79+L79 -> 1843.75
A80: Economy | B80: Modular | C80: Dry / Inexposed area | D80: Panel | E80: Curved Shape Panel | F80: Finish Material, Core Material | G80: Smooth Finish, Carcass - MR - Premium | H80: Abhiyam , Catch Plus , Virgo, Kitply plus | I80: Supply and installation of Chamfered Wall Panel with MR Premium Carcass, Smooth finish laminate | J80: 925 | K80: 0.25 | L80: =J80*K80 -> 231.25 | M80: =J80+L80 -> 1156.25
A81: Economy | B81: Modular | C81: Dry / Inexposed area | D81: Panel | E81: Wallpanel , pelmet , Ceiling Panel , Base panel / Side panel, Jam Panel, Chimney Panel | F81: Finish Material, Core Material | G81: Smooth Finish, Carcass - MR - Premium | H81: Abhiyam , Catch Plus , Virgo, Kitply plus | I81: Supply and installation of Wall Panel with MR Premium Carcass, Smooth finish laminate | J81: 775 | K81: 0.25 | L81: =J81*K81 -> 193.75 | M81: =J81+L81 -> 968.75
I82: Supply and installation of Pelmet Panel with MR Premium Carcass, Smooth finish laminate
I83: Supply and installation of Jam Panel with MR Premium Carcass, Smooth finish laminate
I84: Supply and installation of Ceiling Panel with MR Premium Carcass, Smooth finish laminate
I85: Supply and installation of Base Panel with MR Premium Carcass, Smooth finish laminate
A87: GLOSSY FINISH
A88: Project Type | B88: Section | C88: Room Type | D88: Unit Type | E88: Panel type | F88: Category | G88: Material Type | H88: Brand
A89: Economy | B89: Modular | C89: Wet / Exposed Area | D89: Base Storage, Wall Storage, Tall Storage, Wardrobe | E89: Carcass/shutter | F89: Core Material, Finish Material, Hinges | G89: Carcass - BWP / Shutter - HDF, Glossy Finish, Soft Close | H89: Carcass - Kit ply Vista Marine / Shutter - Green Panel, Ebco , Sleek , Abhiyam , Catch Plus , Virgo | J89: 1525 | K89: 0.25 | L89: =J89*K89 -> 381.25 | M89: =J89+L89 -> 1906.25
A90: Economy | B90: Modular | C90: Wet / Exposed Area | D90: Base Storage, Wall Storage, Tall Storage, Wardrobe | E90: Carcass/shutter | F90: Core Material, Finish Material, Hinges | G90: Carcass - BWP / Shutter - Plywood Border with Clear / Tinted Glass , Soft Close, Glossy Finish | H90: Ebco , Sleek , Abhiyam , Catch Plus , Virgo, Carcass / Shutter - Kitply Vist Marine with Glass | J90: 1930 | K90: 0.25 | L90: =J90*K90 -> 482.5 | M90: =J90+L90 -> 2412.5
A91: Economy | B91: Modular | C91: Wet / Exposed Area | D91: Base Storage, Wall Storage, Tall Storage, Wardrobe | E91: Carcass/shutter | F91: Core Material, Finish Material, Hinges | G91: Carcass - BWP / Shutter - Plywood Border with Fluted Glass , Glossy Finish , Soft Close | H91: Ebco , Sleek , Abhiyam , Catch Plus , Virgo, Carcass / Shutter - Kitply Vist Marine with Glass | J91: 2050 | K91: 0.25 | L91: =J91*K91 -> 512.5 | M91: =J91+L91 -> 2562.5
A92: Economy | B92: Modular | C92: Wet / Exposed Area | D92: Base Storage, Wall Storage, Tall Storage, Wardrobe | E92: Carcass/shutter | F92: Core Material, Finish Material, Hinges | G92: Carcass - BWP / Shutter - Black / Silver colour Aluminium Profile with Clear or Tinted Glass, Glossy Finish , Soft Close | H92: Sleek , Ebco, Abhiyam , Catch Plus , Virgo, Carcass -Kitply Vista Marine / Shutter - Imported Aluminium Profile Shutters | J92: 2375 | K92: 0.25 | L92: =J92*K92 -> 593.75 | M92: =J92+L92 -> 2968.75
A93: Economy | B93: Modular | C93: Wet / Exposed Area | D93: Base Storage, Wall Storage, Tall Storage, Wardrobe | E93: Carcass/shutter | F93: Core Material, Finish Material, Hinges | G93: Carcass - BWP / Shutter - Black / Silver colour Aluminium Profile with Fluted Glass, Glossy Finish , Soft Close | H93: Sleek , Ebco, Abhiyam , Catch Plus , Virgo, Carcass -Kitply Vista Marine / Shutter - Imported Aluminium Profile Shutters | J93: 2475 | K93: 0.25 | L93: =J93*K93 -> 618.75 | M93: =J93+L93 -> 3093.75
A94: Economy | B94: Modular | C94: Wet / Exposed Area | D94: Base Storage, Wall Storage, Tall Storage, Wardrobe | E94: Carcass/shutter | F94: Core Material, Finish Material, Hinges | G94: Carcass - BWP / Shutter - Gold / Rose Gold colour Aluminium Profile with Clear or Tinted Glass, Soft Close, Glossy Finish | H94: Sleek , Ebco, Abhiyam , Catch Plus , Virgo, Carcass -Kitply Vista Marine / Shutter - Imported Aluminium Profile Shutters | J94: 2475 | K94: 0.25 | L94: =J94*K94 -> 618.75 | M94: =J94+L94 -> 3093.75
A95: Economy | B95: Modular | C95: Wet / Exposed Area | D95: Base Storage, Wall Storage, Tall Storage, Wardrobe | E95: Carcass/shutter | F95: Core Material, Finish Material, Hinges | G95: Carcass - BWP / Shutter - Gold / Rose Gold colour Aluminium Profile with Fluted Glass, Glossy Finish , Soft Close | H95: Sleek , Ebco, Abhiyam , Catch Plus , Virgo, Carcass -Kitply Vista Marine / Shutter - Imported Aluminium Profile Shutters | J95: 2575 | K95: 0.25 | L95: =J95*K95 -> 643.75 | M95: =J95+L95 -> 3218.75
A96: Economy | B96: Modular | C96: Wet / Exposed Area | D96: Base Storage, Wall Storage, Tall Storage, Wardrobe | E96: Carcass/shutter | F96: Core Material, Finish Material, Hinges | G96: Carcass Inner 1mm- BWP / Shutter - Plywood Border with Clear / Tinted Glass , Glossy Finish , Soft Close | H96: Ebco , Sleek , Abhiyam , Catch Plus , Virgo, Carcass / Shutter - Kitply Vist Marine with Glass | J96: 2180 | K96: 0.25 | L96: =J96*K96 -> 545 | M96: =J96+L96 -> 2725
A97: Economy | B97: Modular | C97: Wet / Exposed Area | D97: Base Storage, Wall Storage, Tall Storage, Wardrobe | E97: Carcass/shutter | F97: Core Material, Finish Material, Hinges | G97: Carcass inner 1mm - BWP / Shutter - Plywood Border with Fluted Glass , Glossy Finish , Soft Close | H97: Ebco , Sleek , Abhiyam , Catch Plus , Virgo, Carcass / Shutter - Kitply Vist Marine with Glass | J97: 2280 | K97: 0.25 | L97: =J97*K97 -> 570 | M97: =J97+L97 -> 2850
A98: Economy | B98: Modular | C98: Wet / Exposed Area | D98: Base Storage, Wall Storage, Tall Storage, Wardrobe | E98: Carcass/shutter | F98: Core Material, Finish Material, Hinges | G98: Carcass Inner 1mm- BWP / Shutter - Black / Silver colour Aluminium Profile with Clear or Tinted Glass , Glossy Finish , Soft Close | H98: Sleek , Ebco, Abhiyam , Catch Plus , Virgo, Carcass -Kitply Vista Marine / Shutter - Imported Aluminium Profile Shutters | J98: 2525 | K98: 0.25 | L98: =J98*K98 -> 631.25 | M98: =J98+L98 -> 3156.25
A99: Economy | B99: Modular | C99: Wet / Exposed Area | D99: Base Storage, Wall Storage, Tall Storage, Wardrobe | E99: Carcass/shutter | F99: Core Material, Finish Material, Hinges | G99: Carcass Inner 1mm - BWP / Shutter - Black / Silver colour Aluminium Profile with Fluted Glass, Glossy Finish , Soft Close | H99: Sleek , Ebco, Abhiyam , Catch Plus , Virgo, Carcass -Kitply Vista Marine / Shutter - Imported Aluminium Profile Shutters | J99: 2625 | K99: 0.25 | L99: =J99*K99 -> 656.25 | M99: =J99+L99 -> 3281.25
A100: Economy | B100: Modular | C100: Wet / Exposed Area | D100: Base Storage, Wall Storage, Tall Storage, Wardrobe | E100: Carcass/shutter | F100: Core Material, Finish Material, Hinges | G100: Carcass Inner 1mm - BWP / Shutter - Gold / Rose Gold colour Aluminium Profile with Fluted Glass, Glossy Finish , Soft Close | H100: Sleek , Ebco, Abhiyam , Catch Plus , Virgo, Carcass -Kitply Vista Marine / Shutter - Imported Aluminium Profile Shutters | J100: 2625 | K100: 0.25 | L100: =J100*K100 -> 656.25 | M100: =J100+L100 -> 3281.25
... A111: Economy | B111: Modular | C111: Wet / Exposed Area | D111: Panel | E111: Curved Shape Panel | F111: Finish Material, Core Material | G111: Glossy Finish , CARCASS - BWP | H111: Kit Ply Vista Marine, Catch Plus , Abhiyam , Virgo | J111: 1075 | K111: 0.25 | L111: =J111*K111 -> 268.75 | M111: =J111+L111 -> 1343.75
A112: Economy | B112: Modular | C112: Wet / Exposed Area | D112: Panel | E112: Wallpanel , pelmet , Ceiling Panel , Base panel / Side panel | F112: Finish Material, Core Material | G112: Glossy Finish , CARCASS - BWP | H112: Kit Ply Vista Marine, Catch Plus , Abhiyam , Virgo
A114: Economy | B114: Modular | C114: Dry / Inexposed area | D114: Base Storage, Wall Storage, Tall Storage, Wardrobe | E114: Carcass/shutter | F114: Core Material, Finish Material, Hinges | G114: Glossy Finish, Soft Close, Carcass - MR Premium / Shutter - HDF | H114: Carcass - Kitply Plus / Shutter - Green Panel, Ebco , Sleek , Catch Plus , Abhiyam , Virgo | J114: 1425 | K114: 0.25 | L114: =J114*K114 -> 356.25 | M114: =J114+L114 -> 1781.25
A115: Economy | B115: Modular | C115: Dry / Inexposed area | D115: Base Storage, Wall Storage, Tall Storage, Wardrobe | E115: Carcass/shutter | F115: Core Material, Finish Material, Hinges | G115: Carcass - MR - Premium/ Shutter - Plywood Border with Clear / Tinted Glass , Glossy Finish , Soft Close | H115: Carcass - Kitply Plus / Shutter - Green Panel, Ebco , Sleek , Catch Plus , Abhiyam , Virgo | J115: 1830 | K115: 0.25 | L115: =J115*K115 -> 457.5 | M115: =J115+L115 -> 2287.5
A116: Economy | B116: Modular | C116: Dry / Inexposed area | D116: Base Storage, Wall Storage, Tall Storage, Wardrobe | E116: Carcass/shutter | F116: Core Material, Finish Material, Hinges | G116: Carcass - MR - Premium / Shutter - Ply wood border with Fluted Glass , Glossy Finish , Soft Close | H116: Ebco , Sleek , Abhiyam , Catch Plus , Virgo, Carcass - Kit ply Vista Marine / Shutter - Green Panel with Glass | J116: 1950 | K116: 0.25 | L116: =J116*K116 -> 487.5 | M116: =J116+L116 -> 2437.5
...

Sheet Lite Premium
A1: Project Type | B1: Section | C1: Room Type | D1: Unit Type | E1: Panel type | F1: Category | G1: Material Type | H1: Brand | I1: Description | J1: Rate | K1: Mark up | L1: Margin | M1: Selling Price
A2: SMOOTH FINISH
A3: Mid Premium | B3: Modular | C3: Wet / Exposed Area | D3: Base Storage, Wall Storage, Tall Storage, Wardrobe | E3: Carcass/shutter | F3: Core Material, Finish Material, Hinges | G3: Carcass - BWP / Shutter - HDHMR, Smooth Finish, Soft Close | H3: Carcass - Century Sainik or Green Absolute / Shutter - Green Panel, Hettich Onsys , , Advance , New Mika , Rotolam | J3: =J32+100 -> 1600 | K3: 0.25 | L3: =J3*K3 -> 400 | M3: =J3+L3 -> 2000
A4: Mid Premium | B4: Modular | C4: Wet / Exposed Area | D4: Base Storage - Inner 1mm, Wall Storage - inner 1mm, Tall Storage - Inner 1mm | E4: Carcass, Shutter | F4: Core Material, Finish Material, Hinges | G4: Carcass - BWP / Shutter - HDHMR, Smooth Finish, Soft Close | H4: Carcass - Century Sainik or Green Absolute / Shutter - Green Panel, Hettich Onsys , , Advance , New Mika , Rotolam | I4: Supply and installation of Base storage - Inner 1mm unit with BWP Carcass, HDHMR Shutter, Smooth finish laminate and soft close hinges | J4: =J36+100 -> 1750 | K4: 0.25 | L4: =J4*K4 -> 437.5 | M4: =J4+L4 -> 2187.5
H5: Carcass - Century Sainik or Green Absolute / Shutter - Green Panel, Hettich Onsys , , Advance , New Mika , Rotolam | I5: Supply and installation of Wall storage - Inner 1mm unit with BWP Carcass, HDHMR Shutter, Smooth finish laminate and soft close hinges
H6: Carcass - Century Sainik or Green Absolute / Shutter - Green Panel, Hettich Onsys , , Advance , New Mika , Rotolam | I6: Supply and installation of Tall storage - Inner 1mm unit with BWP Carcass, HDHMR Shutter, Smooth finish laminate and soft close hinges
A7: Mid Premium | B7: Modular | C7: Wet / Exposed Area | D7: Base Storage, Wall Storage, Tall Storage, Wardrobe | E7: Carcass/shutter | F7: Core Material, Finish Material, Hinges | G7: Carcass - BWP / Shutter - Plywood Border with Clear / Tinted Glass , Soft Close, Smooth Finish | H7: Hettich Onsys , , Advance , New Mika , Rotolam, Carcass / Shutter - Century Sainik or Green Absolute with Glass | J7: =J39+100 -> 2005 | K7: 0.25 | L7: =J7*K7 -> 501.25 | M7: =J7+L7 -> 2506.25
A8: Mid Premium | B8: Modular | C8: Wet / Exposed Area | D8: Base Storage, Wall Storage, Tall Storage, Wardrobe | E8: Carcass/shutter | F8: Core Material, Finish Material, Hinges | G8: Carcass - BWP / Shutter - Plywood Border with Fluted Glass , Smooth Finish , Soft Close | H8: Hettich Onsys , , Advance , New Mika , Rotolam, Carcass / Shutter - Century Sainik or Green Absolute with Glass | J8: =J40+100 -> 2125 | K8: 0.25 | L8: =J8*K8 -> 531.25 | M8: =J8+L8 -> 2656.25
A9: Mid Premium | B9: Modular | C9: Wet / Exposed Area | D9: Base Storage, Wall Storage, Tall Storage, Wardrobe | E9: Carcass/shutter | F9: Core Material, Finish Material, Hinges | G9: Carcass - BWP / Shutter - Black / Silver colour Aluminium Profile with Clear or Tinted Glass, Smooth Finish , Soft Close | H9: , Hettich Onsys, Advance , New Mika , Rotolam, Carcass -Century Sainik or Green Absolute / Shutter - CNR Aluminium Profile Shutters | J9: =J41+100 -> 2450 | K9: 0.25 | L9: =J9*K9 -> 612.5 | M9: =J9+L9 -> 3062.5
A10: Mid Premium | B10: Modular | C10: Wet / Exposed Area | D10: Base Storage, Wall Storage, Tall Storage, Wardrobe | E10: Carcass/shutter | F10: Core Material, Finish Material, Hinges | G10: Carcass - BWP / Shutter - Black / Silver colour Aluminium Profile with Fluted Glass, Smooth Finish , Soft Close | H10: , Hettich Onsys, Advance , New Mika , Rotolam, Carcass -Century Sainik or Green Absolute / Shutter - CNR Aluminium Profile Shutters | J10: =J42+100 -> 2550 | K10: 0.25 | L10: =J10*K10 -> 637.5 | M10: =J10+L10 -> 3187.5
A11: Mid Premium | B11: Modular | C11: Wet / Exposed Area | D11: Base Storage, Wall Storage, Tall Storage, Wardrobe | E11: Carcass/shutter | F11: Core Material, Finish Material, Hinges | G11: Carcass - BWP / Shutter - Gold / Rose Gold colour Aluminium Profile with Clear or Tinted Glass, Soft Close, Smooth Finish | H11: , Hettich Onsys, Advance , New Mika , Rotolam, Carcass -Century Sainik or Green Absolute / Shutter - CNR Aluminium Profile Shutters | J11: =J43+100 -> 2550 | K11: 0.25 | L11: =J11*K11 -> 637.5 | M11: =J11+L11 -> 3187.5
A12: Mid Premium | B12: Modular | C12: Wet / Exposed Area | D12: Base Storage, Wall Storage, Tall Storage, Wardrobe | E12: Carcass/shutter | F12: Core Material, Finish Material, Hinges | G12: Carcass - BWP / Shutter - Gold/ Rose Gold Aluminium Profile with Clear or Tinted Glass | H12: , Hettich Onsys, Advance , New Mika , Rotolam, Carcass -Century Sainik or Green Absolute / Shutter - CNR Aluminium Profile Shutters | J12: =J44+100 -> 2650 | K12: 0.25 | L12: =J12*K12 -> 662.5 | M12: =J12+L12 -> 3312.5
A13: Mid Premium | B13: Modular | C13: Wet / Exposed Area | D13: Base Storage, Wall Storage, Tall Storage, Wardrobe | E13: Carcass/shutter | F13: Core Material, Finish Material, Hinges | G13: Carcass Inner 1mm- BWP / Shutter - Plywood Border with Clear / Tinted Glass , Smooth Finish , Soft Close | H13: Hettich Onsys , , Advance , New Mika , Rotolam, Carcass / Shutter - Century Sainik or Green Absolute with Glass | J13: =J45+100 -> 2130 | K13: 0.25 | L13: =J13*K13 -> 532.5 | M13: =J13+L13 -> 2662.5
A14: Mid Premium | B14: Modular | C14: Wet / Exposed Area | D14: Base Storage, Wall Storage, Tall Storage, Wardrobe | E14: Carcass/shutter | F14: Core Material, Finish Material, Hinges | G14: Carcass inner 1mm - BWP / Shutter - Plywood Border with Fluted Glass , Smooth Finish , Soft Close | H14: Hettich Onsys , , Advance , New Mika , Rotolam, Carcass / Shutter - Century Sainik or Green Absolute with Glass | J14: =J46+100 -> 2250 | K14: 0.25 | L14: =J14*K14 -> 562.5 | M14: =J14+L14 -> 2812.5
A15: Mid Premium | B15: Modular | C15: Wet / Exposed Area | D15: Base Storage, Wall Storage, Tall Storage, Wardrobe | E15: Carcass/shutter | F15: Core Material, Finish Material, Hinges | G15: Carcass Inner 1mm- BWP / Shutter - Black / Silver colour Aluminium Profile with Clear or Tinted Glass , Smooth Finish , Soft Close | H15: , Hettich Onsys, Advance , New Mika , Rotolam, Carcass -Century Sainik or Green Absolute / Shutter - CNR Aluminium Profile Shutters | J15: =J47+100 -> 2600 | K15: 0.25 | L15: =J15*K15 -> 650 | M15: =J15+L15 -> 3250
A16: Mid Premium | B16: Modular | C16: Wet / Exposed Area | D16: Base Storage, Wall Storage, Tall Storage, Wardrobe | E16: Carcass/shutter | F16: Core Material, Finish Material, Hinges | G16: Carcass Inner 1mm - BWP / Shutter - Black / Silver colour Aluminium Profile with Fluted Glass, Smooth Finish , Soft Close | H16: , Hettich Onsys, Advance , New Mika , Rotolam, Carcass -Century Sainik or Green Absolute / Shutter - CNR Aluminium Profile Shutters | J16: =J48+100 -> 2700 | K16: 0.25 | L16: =J16*K16 -> 675 | M16: =J16+L16 -> 3375
A17: Mid Premium | B17: Modular | C17: Wet / Exposed Area | D17: Base Storage, Wall Storage, Tall Storage, Wardrobe | E17: Carcass/shutter | F17: Core Material, Finish Material, Hinges | G17: Carcass Inner 1mm- BWP / Shutter - Gold / Rose Gold colour Aluminium Profile with Clear or Tinted Glass, Smooth Finish , Soft Close | H17: , Hettich Onsys, Advance , New Mika , Rotolam, Carcass -Century Sainik or Green Absolute / Shutter - CNR Aluminium Profile Shutters | J17: =J52+100 -> 2700 | K17: 0.25 | L17: =J17*K17 -> 675 | M17: =J17+L17 -> 3375
A18: Mid Premium | B18: Modular | C18: Wet / Exposed Area | D18: Base Storage, Wall Storage, Tall Storage, Wardrobe | E18: Carcass/shutter | F18: Core Material, Finish Material, Hinges | G18: Carcass Inner 1mm - BWP / Shutter - Gold / Rose Gold colour Aluminium Profile with Fluted Glass, Smooth Finish , Soft Close | H18: , Hettich Onsys, Advance , New Mika , Rotolam, Carcass -Century Sainik or Green Absolute / Shutter - CNR Aluminium Profile Shutters | J18: =J53+100 -> 2800 | K18: 0.25 | L18: =J18*K18 -> 700 | M18: =J18+L18 -> 3500
A19: Mid Premium | B19: Modular | C19: Wet / Exposed Area | D19: Curved Shape Base Storage unit | E19: Carcass/shutter | F19: Core Material, Finish Material, Hinges | G19: Carcass - BWP / Shutter - HDHMR, Smooth Finish , Soft Close | H19: Carcass - Century Sainik or Green Absolute / Shutter - Green Panel, Hettich Onsys , , Advance , New Mika , Rotolam | J19: =J54+100 -> 1975 | K19: 0.25 | L19: =J19*K19 -> 493.75 | M19: =J19+L19 -> 2468.75
A20: Mid Premium | B20: Modular | C20: Wet / Exposed Area | D20: Curved Shape Drawer Storage unit | E20: Carcass/shutter | F20: Core Material, Finish Material | G20: Carcass - BWP / Shutter - HDHMR, Smooth Finish | H20: Carcass - Century Sainik or Green Absolute / Shutter - Green Panel, New Mika , Rotolam , Advance | J20: =J55+100 -> 1975 | K20: 0.25 | L20: =J20*K20 -> 493.75 | M20: =J20+L20 -> 2468.75
A21: Mid Premium | B21: Modular | C21: Wet / Exposed Area | D21: Tambour Storage | E21: Carcass | F21: Core Material, Finish Material | G21: CARCASS - BWP, Smooth Finish | H21: Carcass - Century Sainik or Green Absolute, Advance, New Mika , Rotolam | J21: =J56+100 -> 1375 | K21: 0.25 | L21: =J21*K21 -> 343.75 | M21: =J21+L21 -> 1718.75
A22: Mid Premium | B22: Modular | C22: Wet / Exposed Area | D22: Open Unit - Inner 1mm | E22: Carcass | F22: Core Material, Finish Material | G22: CARCASS - BWP, Smooth Finish | H22: Carcass - Century Sainik or Green Absolute, Advance, New Mika , Rotolam | J22: =J57+100 -> 1600 | K22: 0.25 | L22: =J22*K22 -> 400 | M22: =J22+L22 -> 2000
A23: Mid Premium | B23: Modular | C23: Wet / Exposed Area | D23: Loft | E23: Frame and Shutter | F23: Core Material, Finish Material, Hinges | G23: Smooth Finish, Soft Close, Frame - BWP / Shutter - HDHMR | H23: Hettich Onsys , , Advance , New Mika , Rotolam, Frame- Century Sainik or Green Absolute / Shutter - Green Panel, | J23: =J58+100 -> 997 | K23: 0.25 | L23: =J23*K23 -> 249.25 | M23: =J23+L23 -> 1246.25
A24: Mid Premium | B24: Modular | C24: Wet / Exposed Area | D24: Ledge | E24: Ledge -25mm | F24: Finish Material, Core Material | G24: Smooth Finish , CARCASS - BWP | H24: Ledge - Century Sainik or Green Absolute, Advance , New Mika , Rotolam | J24: =J59+100 -> 883 | K24: 0.25 | L24: =J24*K24 -> 220.75 | M24: =J24+L24 -> 1103.75
A25: Mid Premium | B25: Modular | C25: Wet / Exposed Area | D25: Ledge | E25: Ledge -36mm | F25: Finish Material, Core Material | G25: Smooth Finish , CARCASS - BWP | H25: Ledge - Century Sainik or Green Absolute, Advance , New Mika , Rotolam | J25: =J60+100 -> 883 | K25: 0.25 | L25: =J25*K25 -> 220.75 | M25: =J25+L25 -> 1103.75
A26: Mid Premium | B26: Modular | C26: Wet / Exposed Area | D26: Ledge | E26: Ledge -50mm | F26: Finish Material, Core Material | G26: Smooth Finish , CARCASS - BWP | H26: Ledge - Century Sainik or Green Absolute, Advance , New Mika , Rotolam | J26: =J61+100 -> 1083 | K26: 0.25 | L26: =J26*K26 -> 270.75 | M26: =J26+L26 -> 1353.75
A27: Mid Premium | B27: Modular | C27: Wet / Exposed Area | D27: Partition | E27: Partition -75mm | F27: Finish Material, Core Material | G27: Smooth Finish , CARCASS - BWP | H27: Century Sainik or Green Absolute , Advance , New Mika , Rotolam | J27: =J62+100 -> 1700 | K27: 0.25 | L27: =J27*K27 -> 425 | M27: =J27+L27 -> 2125
A28: Mid Premium | B28: Modular | C28: Wet / Exposed Area | D28: Panel | E28: Curved Shape Panel | F28: Finish Material, Core Material | G28: Smooth Finish , CARCASS - BWP | H28: Century Sainik or Green Absolute, New Mika , Advance , Rotolam | J28: =J63+100 -> 1150 | K28: 0.25 | L28: =J28*K28 -> 287.5 | M28: =J28+L28 -> 1437.5
A29: Mid Premium | B29: Modular | C29: Wet / Exposed Area | D29: Panel | E29: Wallpanel , pelmet , Base panel / Side panel , Jam Panel, Chimney Panel | F29: Finish Material, Core Material | G29: Smooth Finish , CARCASS - BWP | H29: Century Sainik or Green Absolute, New Mika , Advance , Rotolam | J29: =J64+100 -> 1000 | K29: 0.25 | L29: =J29*K29 -> 250 | M29: =J29+L29 -> 1250
A30: Mid Premium | B30: Modular | C30: Wet / Exposed Area | D30: Panel | E30: Ceiling Panel | F30: Finish Material, Core Material | G30: Smooth Finish , CARCASS - BWP | H30: Century Sainik or Green Absolute, New Mika , Advance , Rotolam | J30: =J69+100 -> 1167 | K30: 0.25 | L30: =J30*K30 -> 291.75 | M30: =J30+L30 -> 1458.75
K31: 0.25 | L31: =J31*K31 -> 0
A32: Mid Premium | B32: Modular | C32: Dry / Inexposed area | D32: Base Storage, Wall Storage, Tall Storage, Wardrobe | E32: Carcass/shutter | F32: Core Material, Finish Material, Hinges | G32: Smooth Finish, Soft Close, Carcass - MR / Shutter - HDHMR | H32: Carcass - Century Sainik or Greenply Absolute / Shutter - Green Panel, Hettich Onsys , , New Mika , Advance , Rotolam | I32: Supply and installation of Base storage with MR Carcass, HDHMR Shutter, Smooth finish laminate and soft close hinges | J32: 1500 | K32: 0.25 | L32: =J32*K32 -> 375 | M32: =J32+L32 -> 1875
I33: Supply and installation of Wall storage with MR Carcass, HDHMR Shutter, Smooth finish laminate and soft close hinges
I34: Supply and installation of Tall storage with MR Carcass, HDHMR Shutter, Smooth finish laminate and soft close hinges
I35: Supply and installation of Wardrobe with MR Carcass, HDHMR Shutter, Smooth finish laminate and soft close hinges
A36: Mid Premium | B36: Modular | C36: Dry / Inexposed area | D36: Base Storage - Inner 1mm, Wall Storage - inner 1mm, Tall Storage - Inner 1mm | E36: Carcass, Shutter | F36: Core Material, Finish Material, Hinges | G36: Carcass - BWP / Shutter - HDHMR, Smooth Finish, Soft Close | H36: Carcass - Century Sainik or Green Absolute / Shutter - Green Panel, Hettich Onsys , , Advance , New Mika , Rotolam | I36: Supply and installation of Base storage - Inner 1mm unit with BWP Carcass, HDHMR Shutter, Smooth finish laminate and soft close hinges | J36: 1650 | K36: 0.25 | L36: =J36*K36 -> 412.5 | M36: =J36+L36 -> 2062.5
H37: Carcass - Century Sainik or Green Absolute / Shutter - Green Panel, Hettich Onsys , , Advance , New Mika , Rotolam | I37: Supply and installation of Wall storage - Inner 1mm unit with BWP Carcass, HDHMR Shutter, Smooth finish laminate and soft close hinges
H38: Carcass - Century Sainik or Green Absolute / Shutter - Green Panel, Hettich Onsys , , Advance , New Mika , Rotolam | I38: Supply and installation of Tall storage - Inner 1mm unit with BWP Carcass, HDHMR Shutter, Smooth finish laminate and soft close hinges
A39: Mid Premium | B39: Modular | C39: Dry / Inexposed area | D39: Base Storage, Wall Storage, Tall Storage, Wardrobe | E39: Carcass/shutter | F39: Core Material, Finish Material, Hinges | G39: Carcass - MR/ Shutter - Plywood Border with Clear / Tinted Glass , Smooth Finish , Soft Close | H39: Carcass - Century Sainik or Greenply Absolute / Shutter - Green Panel, Hettich Onsys , , New Mika , Advance , Rotolam | J39: 1905 | K39: 0.25 | L39: =J39*K39 -> 476.25 | M39: =J39+L39 -> 2381.25
A40: Mid Premium | B40: Modular | C40: Dry / Inexposed area | D40: Base Storage, Wall Storage, Tall Storage, Wardrobe | E40: Carcass/shutter | F40: Core Material, Finish Material, Hinges | G40: Carcass - MR / Shutter - Ply wood border with Fluted Glass , Smooth Finish , Soft Close | H40: Hettich Onsys , , Advance , New Mika , Rotolam, Carcass - Century Sainik or Green Absolute / Shutter - Green Panel with Glass | J40: 2025 | K40: 0.25 | L40: =J40*K40 -> 506.25 | M40: =J40+L40 -> 2531.25
A41: Mid Premium | B41: Modular | C41: Dry / Inexposed area | D41: Base Storage, Wall Storage, Tall Storage, Wardrobe | E41: Carcass/shutter | F41: Core Material, Finish Material, Hinges | G41: Carcass - MR / Shutter - Black / Silver colour Aluminium Profile with Clear or Tinted Glass , Smooth Finish , Soft Close | H41: Cracass - Century Sainik or Greenply Absolute / Shutter - Imported Aluminium Profile shutter, , Hettich Onsys, Advance , New Mika , Rotolam | J41: =2250+100 -> 2350 | K41: 0.25 | L41: =J41*K41 -> 587.5 | M41: =J41+L41 -> 2937.5
A42: Mid Premium | B42: Modular | C42: Dry / Inexposed area | D42: Base Storage, Wall Storage, Tall Storage, Wardrobe | E42: Carcass/shutter | F42: Core Material, Finish Material, Hinges | G42: Carcass - MR / Shutter - Black / Silver colour Aluminium Profile with Fluted Glass, Soft Close, Smooth Finish | H42: Cracass - Century Sainik or Greenply Absolute / Shutter - Imported Aluminium Profile shutter, , Hettich Onsys, Advance , New Mika , Rotolam | J42: =2350+100 -> 2450 | K42: 0.25 | L42: =J42*K42 -> 612.5 | M42: =J42+L42 -> 3062.5
A43: Mid Premium | B43: Modular | C43: Dry / Inexposed area | D43: Base Storage, Wall Storage, Tall Storage, Wardrobe | E43: Carcass/shutter | F43: Core Material, Finish Material, Hinges | G43: Carcass - MR / Shutter - Gold / Rose Gold Aluminium Profile with Clear Glass , Smooth Finish , Soft Close | H43: Cracass - Century Sainik or Greenply Absolute / Shutter - Imported Aluminium Profile shutter, , Hettich Onsys, Advance , New Mika , Rotolam | J43: =2350+100 -> 2450 | K43: 0.25 | L43: =J43*K43 -> 612.5 | M43: =J43+L43 -> 3062.5
A44: Mid Premium | B44: Modular | C44: Dry / Inexposed area | D44: Base Storage, Wall Storage, Tall Storage, Wardrobe | E44: Carcass/shutter | F44: Core Material, Finish Material, Hinges | G44: Smooth Finish , Soft Close, Carcass - MR / Shutter - Gold Colour Aluminium profile with Fluted Glass | H44: Cracass - Century Sainik or Greenply Absolute / Shutter - Imported Aluminium Profile shutter, , Hettich Onsys, Advance , New Mika , Rotolam | J44: =2450+100 -> 2550 | K44: 0.25 | L44: =J44*K44 -> 637.5 | M44: =J44+L44 -> 3187.5
A45: Mid Premium | B45: Modular | C45: Dry / Inexposed area | D45: Base Storage, Wall Storage, Tall Storage, Wardrobe | E45: Carcass/shutter | F45: Core Material, Finish Material, Hinges | G45: Carcass Inner 1mm - MR/ Shutter - Plywood Border with Clear / Tinted Glass , Smooth Finish , Soft Close | H45: Cracass - Century Sainik or Greenply Absolute / Shutter - Imported Aluminium Profile shutter, , Hettich Onsys, Advance , New Mika , Rotolam | J45: 2030 | K45: 0.25 | L45: =J45*K45 -> 507.5 | M45: =J45+L45 -> 2537.5
A46: Mid Premium | B46: Modular | C46: Dry / Inexposed area | D46: Base Storage, Wall Storage, Tall Storage, Wardrobe | E46: Carcass/shutter | F46: Core Material, Finish Material, Hinges | G46: Carcass Inner 1mm- MR / Shutter - Ply wood border with Fluted Glass , Smooth Finish , Soft Close | H46: Cracass - Century Sainik or Greenply Absolute / Shutter - Imported Aluminium Profile shutter, , Hettich Onsys, Advance , New Mika , Rotolam | J46: 2150 | K46: 0.25 | L46: =J46*K46 -> 537.5 | M46: =J46+L46 -> 2687.5
A47: Mid Premium | B47: Modular | C47: Dry / Inexposed area | D47: Base Storage, Wall Storage, Tall Storage, Wardrobe | E47: Carcass/shutter | F47: Core Material, Finish Material, Hinges | G47: Carcass inner 1mm- MR / Shutter - Black / Silver colour Aluminium Profile with Clear or Tinted Glass , Smooth Finish , Soft Close | H47: Cracass - Century Sainik or Greenply Absolute / Shutter - Imported Aluminium Profile shutter, , Hettich Onsys, Advance , New Mika , Rotolam | J47: 2500 | K47: 0.25 | L47: =J47*K47 -> 625 | M47: =J47+L47 -> 3125
A48: Mid Premium | B48: Modular | C48: Dry / Inexposed area | D48: Base Storage, Wall Storage, Tall Storage, Wardrobe | E48: Carcass/shutter | F48: Core Material, Finish Material, Hinges | G48: Carcass Inner 1mm - MR / Shutter - Black / Silver colour Aluminium Profile with Fluted Glass , Smooth Finish , Soft Close | H48: Cracass - Century Sainik or Greenply Absolute / Shutter - Imported Aluminium Profile shutter, , Hettich Onsys, Advance , New Mika , Rotolam | I48: Supply and installation of Base storage unit with MR ply frame - Inner 1mm, Black/Silver Aluminium Profile with Fluted Glass Shutter, Smooth finish laminate and soft close hinges | J48: 2600 | K48: 0.25 | L48: =J48*K48 -> 650 | M48: =J48+L48 -> 3250
I49: Supply and installation of Wall storage unit with MR ply frame - Inner 1mm, Black/Silver Aluminium Profile with Fluted Glass Shutter, Smooth finish laminate and soft close hinges
I50: Supply and installation of Tall storage unit with MR ply frame - Inner 1mm, Black/Silver Aluminium Profile with Fluted Glass Shutter, Smooth finish laminate and soft close hinges
I51: Supply and installation of Wardrobe with MR ply frame - Inner 1mm, Black/Silver Aluminium Profile with Fluted Glass Shutter, Smooth finish laminate and soft close hinges
A52: Mid Premium | B52: Modular | C52: Dry / Inexposed area | D52: Base Storage, Wall Storage, Tall Storage, Wardrobe | E52: Carcass/shutter | F52: Core Material, Finish Material, Hinges | G52: Carcass Inner 1mm - MR / Shutter - Gold / Rose Gold Aluminium Profile with Clear Glass , Smooth Finish , Soft Close | H52: Cracass - Century Sainik or Greenply Absolute / Shutter - Imported Aluminium Profile shutter, , Hettich Onsys, Advance , New Mika , Rotolam | J52: 2600 | K52: 0.25 | L52: =J52*K52 -> 650 | M52: =J52+L52 -> 3250
A53: Mid Premium | B53: Modular | C53: Dry / Inexposed area | D53: Base Storage, Wall Storage, Tall Storage, Wardrobe | E53: Carcass/shutter | F53: Core Material, Finish Material, Hinges | G53: Carcass Inner 1mm - MR / Shutter - Colour Aluminium profile with Fluted Glass , Smooth Finish , Soft Close | H53: Cracass - Century Sainik or Greenply Absolute / Shutter - Imported Aluminium Profile shutter, , Hettich Onsys, Advance , New Mika , Rotolam | J53: 2700 | K53: 0.25 | L53: =J53*K53 -> 675 | M53: =J53+L53 -> 3375
A54: Mid Premium | B54: Modular | C54: Dry / Inexposed area | D54: Curved Shape Base Storage unit | E54: Carcass/shutter | F54: Core Material, Finish Material, Hinges | G54: Carcass - MR / Shutter - HDHMR, Smooth Finish , Soft Close | H54: Hettich Onsys , , Advance , New Mika , Rotolam, Carcass - Century Sainik or Greenply Absolute / Shutter - Green Panel | J54: 1875 | K54: 0.25 | L54: =J54*K54 -> 468.75 | M54: =J54+L54 -> 2343.75
A55: Mid Premium | B55: Modular | C55: Dry / Inexposed area | D55: Curved Shape Drawer Storage unit | E55: Carcass/shutter | F55: Core Material, Finish Material | G55: Carcass - MR / Shutter - HDHMR, Smooth Finish | H55: New Mika , Rotolam , Advance, Carcass - Century Sainik or Greenply Absolute / Shutter - Green Panel | J55: 1875 | K55: 0.25 | L55: =J55*K55 -> 468.75 | M55: =J55+L55 -> 2343.75
A56: Mid Premium | B56: Modular | C56: Dry / Inexposed area | D56: Tambour Storage | E56: Carcass | F56: Core Material, Finish Material | G56: Smooth Finish, Carcass - MR | H56: Carcass - Century Sainik or Greenply Absolute | J56: 1275 | K56: 0.25 | L56: =J56*K56 -> 318.75 | M56: =J56+L56 -> 1593.75
A57: Mid Premium | B57: Modular | C57: Dry / Inexposed area | D57: Open Unit - Inner 1mm | E57: Carcass | F57: Core Material, Finish Material | G57: Smooth Finish, Carcass - MR | H57: Advance, New Mika , Rotolam, Carcass - Century Sainik or Greenply Absolute | I57: Supply and installation of Open unit - Inner 1mm with MR ply frame and Smooth finish laminate | J57: 1500 | K57: 0.25 | L57: =J57*K57 -> 375 | M57: =J57+L57 -> 1875
A58: Mid Premium | B58: Modular | C58: Dry / Inexposed area | D58: Loft | E58: Frame and Shutter | F58: Core Material, Finish Material, Hinges | G58: Smooth Finish , Soft Close, Frame - MR / Shutter - HDHMR | H58: Hettich Onsys , , Advance , New Mika , Rotolam, Frame - Century Sainik or Greenply Absolute / Shutter - Green Panel | I58: Supply and installation of Loft Frame and Shutter unit with MR Frame, HDHMR Shutter, Smooth finish laminate and Soft Close hinges | J58: 897 | K58: 0.25 | L58: =J58*K58 -> 224.25 | M58: =J58+L58 -> 1121.25
A59: Mid Premium | B59: Modular | C59: Dry / Inexposed area | D59: Ledge | E59: Ledge -25mm | F59: Finish Material, Core Material | G59: Smooth Finish, Carcass - MR | H59: Advance , New Mika , Rotolam, Century Sainik or Greenply Absolute | I59: Supply and installation of Ledge with 25mm Ledge MR Frame and Smooth Finish laminate | J59: 783 | K59: 0.25 | L59: =J59*K59 -> 195.75 | M59: =J59+L59 -> 978.75
A60: Mid Premium | B60: Modular | C60: Dry / Inexposed area | D60: Ledge | E60: Ledge -36mm | F60: Finish Material, Core Material | G60: Smooth Finish, Carcass - MR | H60: Advance , New Mika , Rotolam, Century Sainik or Greenply Absolute | J60: 783 | K60: 0.25 | L60: =J60*K60 -> 195.75 | M60: =J60+L60 -> 978.75
A61: Mid Premium | B61: Modular | C61: Dry / Inexposed area | D61: Ledge | E61: Ledge -50mm | F61: Finish Material, Core Material | G61: Smooth Finish, Carcass - MR | H61: Advance , New Mika , Rotolam, Century Sainik or Greenply Absolute | J61: 983 | K61: 0.25 | L61: =J61*K61 -> 245.75 | M61: =J61+L61 -> 1228.75
A62: Mid Premium | B62: Modular | C62: Dry / Inexposed area | D62: Partition | E62: Partition -75mm | F62: Finish Material, Core Material | G62: Smooth Finish, Carcass - MR | H62: Advance , New Mika , Rotolam, Century Sainik or Greenply Absolute | J62: 1600 | K62: 0.25 | L62: =J62*K62 -> 400 | M62: =J62+L62 -> 2000
A63: Mid Premium | B63: Modular | C63: Dry / Inexposed area | D63: Panel | E63: Curved Shape Panel | F63: Finish Material, Core Material | G63: Smooth Finish, Carcass - MR | H63: Advance , New Mika , Rotolam, Century Sainik or Greenply Absolute | J63: 1050 | K63: 0.25 | L63: =J63*K63 -> 262.5 | M63: =J63+L63 -> 1312.5
A64: Mid Premium | B64: Modular | C64: Dry / Inexposed area | D64: Panel | E64: Wallpanel , pelmet , Base panel / Side panel , Chimney Panel, Jam Panel | F64: Finish Material, Core Material | G64: Smooth Finish, Carcass - MR | H64: Advance , New Mika , Rotolam, Century Sainik or Greenply Absolute | I64: Supply and installation of Wall Panel with MR Ply Frame, Smooth Finish laminate | J64: 900 | K64: 0.25 | L64: =J64*K64 -> 225 | M64: =J64+L64 -> 1125
I65: Supply and installation of Pelmet Panel with MR Ply Frame, Smooth Finish laminate
I66: Supply and installation of Jam Panel with MR Ply Frame, Smooth Finish laminate
I67: Supply and installation of Ceiling Panel with MR Ply Frame, Smooth Finish laminate
I68: Supply and installation of Base Panel with MR Ply Frame, Smooth Finish laminate
D69: Panel | E69: Ceiling Panel | G69: CARCASS - MR, Smooth Finish | J69: 1067 | K69: 0.25 | L69: =J69*K69 -> 266.75 | M69: =L69+J69 -> 1333.75
A70: GLOSSY FINISH
B71: Section | C71: Room Type | D71: Unit Type | E71: Panel type | F71: Category | G71: Material Type | H71: Brand | J71: Rate | K71: 0.25 | L71: =J71*K71 -> #VALUE! | M71: =J71+L71 -> #VALUE!
A72: Mid Premium | B72: Modular | C72: Wet / Exposed Area | D72: Base Storage, Wall Storage, Tall Storage, Wardrobe | E72: Carcass/shutter | F72: Core Material, Finish Material, Hinges | G72: Carcass - BWP / Shutter - HDHMR, Glossy Finish, Soft Close | H72: Carcass - Century Sainik or Green Absolute / Shutter - Green Panel, Hettich Onsys , , Advance , New Mika , Rotolam | J72: =J3+50 -> 1650 | K72: 0.25 | L72: =J72*K72 -> 412.5 | M72: =J72+L72 -> 2062.5 | O72: Inner 1mm to be added
D73: Base Storage - Inner 1mm, Wall Storage - inner 1mm, Tall Storage - Inner 1mm | E73: Carcass, Shutter | F73: Core Material, Finish Material, Hinges | G73: Carcass - BWP / Shutter - HDHMR, Glossy Finish, Soft Close | H73: Carcass - Century Sainik or Green Absolute / Shutter - Green Panel, Hettich Onsys , , Advance , New Mika , Rotolam | I73: Supply and installation of Base storage - Inner 1mm unit with BWP Carcass, HDHMR Shutter, Smooth finish laminate and soft close hinges | J73: =J4+50 -> 1800 | K73: 0.25 | L73: =J73*K73 -> 450 | M73: =J73+L73 -> 2250
H74: Carcass - Century Sainik or Green Absolute / Shutter - Green Panel, Hettich Onsys , , Advance , New Mika , Rotolam | I74: Supply and installation of Wall storage - Inner 1mm unit with BWP Carcass, HDHMR Shutter, Smooth finish laminate and soft close hinges
H75: Carcass - Century Sainik or Green Absolute / Shutter - Green Panel, Hettich Onsys , , Advance , New Mika , Rotolam | I75: Supply and installation of Tall storage - Inner 1mm unit with BWP Carcass, HDHMR Shutter, Smooth finish laminate and soft close hinges
A76: Mid Premium | B76: Modular | C76: Wet / Exposed Area | D76: Base Storage, Wall Storage, Tall Storage, Wardrobe | E76: Carcass/shutter | F76: Core Material, Finish Material, Hinges | G76: Carcass - BWP / Shutter - Plywood Border with Clear / Tinted Glass , Soft Close, Glossy Finish | H76: Hettich Onsys , , Advance , New Mika , Rotolam, Carcass / Shutter - Century Sainik or Green Absolute with Glass | J76: =J7+50 -> 2055 | K76: 0.25 | L76: =J76*K76 -> 513.75 | M76: =J76+L76 -> 2568.75
A77: Mid Premium | B77: Modular | C77: Wet / Exposed Area | D77: Base Storage, Wall Storage, Tall Storage, Wardrobe | E77: Carcass/shutter | F77: Core Material, Finish Material, Hinges | G77: Carcass - BWP / Shutter - Plywood Border with Fluted Glass , Glossy Finish , Soft Close | H77: Hettich Onsys , , Advance , New Mika , Rotolam, Carcass / Shutter - Century Sainik or Green Absolute with Glass | J77: =J8+50 -> 2175 | K77: 0.25 | L77: =J77*K77 -> 543.75 | M77: =J77+L77 -> 2718.75
A78: Mid Premium | B78: Modular | C78: Wet / Exposed Area | D78: Base Storage, Wall Storage, Tall Storage, Wardrobe | E78: Carcass/shutter | F78: Core Material, Finish Material, Hinges | G78: Carcass - BWP / Shutter - Black / Silver colour Aluminium Profile with Clear or Tinted Glass, Glossy Finish , Soft Close | H78: , Hettich Onsys, Advance , New Mika , Rotolam, Carcass -Century Sainik or Green Absolute / Shutter - CNR Aluminium Profile Shutters | J78: =J9+50 -> 2500 | K78: 0.25 | L78: =J78*K78 -> 625 | M78: =J78+L78 -> 3125
A79: Mid Premium | B79: Modular | C79: Wet / Exposed Area | D79: Base Storage, Wall Storage, Tall Storage, Wardrobe | E79: Carcass/shutter | F79: Core Material, Finish Material, Hinges | G79: Carcass - BWP / Shutter - Black / Silver colour Aluminium Profile with Fluted Glass, Glossy Finish , Soft Close | H79: , Hettich Onsys, Advance , New Mika , Rotolam, Carcass -Century Sainik or Green Absolute / Shutter - CNR Aluminium Profile Shutters | J79: =J10+50 -> 2600 | K79: 0.25 | L79: =J79*K79 -> 650 | M79: =J79+L79 -> 3250
A80: Mid Premium | B80: Modular | C80: Wet / Exposed Area | D80: Base Storage, Wall Storage, Tall Storage, Wardrobe | E80: Carcass/shutter | F80: Core Material, Finish Material, Hinges | G80: Carcass - BWP / Shutter - Gold / Rose Gold colour Aluminium Profile with Clear or Tinted Glass, Soft Close, Glossy Finish | H80: , Hettich Onsys, Advance , New Mika , Rotolam, Carcass -Century Sainik or Green Absolute / Shutter - CNR Aluminium Profile Shutters | J80: =J11+50 -> 2600 | K80: 0.25 | L80: =J80*K80 -> 650 | M80: =J80+L80 -> 3250
A81: Mid Premium | B81: Modular | C81: Wet / Exposed Area | D81: Base Storage, Wall Storage, Tall Storage, Wardrobe | E81: Carcass/shutter | F81: Core Material, Finish Material, Hinges | G81: Carcass - BWP / Shutter - Gold / Rose Gold colour Aluminium Profile with Fluted Glass, Glossy Finish , Soft Close | H81: , Hettich Onsys, Advance , New Mika , Rotolam, Carcass -Century Sainik or Green Absolute / Shutter - CNR Aluminium Profile Shutters | J81: =J12+50 -> 2700 | K81: 0.25 | L81: =J81*K81 -> 675 | M81: =J81+L81 -> 3375
A82: Mid Premium | B82: Modular | C82: Wet / Exposed Area | D82: Base Storage, Wall Storage, Tall Storage, Wardrobe | E82: Carcass/shutter | F82: Core Material, Finish Material, Hinges | G82: Carcass Inner 1mm- BWP / Shutter - Plywood Border with Clear / Tinted Glass , Glossy Finish , Soft Close | H82: Hettich Onsys , , Advance , New Mika , Rotolam, Carcass / Shutter - Century Sainik or Green Absolute with Glass | J82: =J13+50 -> 2180 | K82: 0.25 | L82: =J82*K82 -> 545 | M82: =J82+L82 -> 2725
A83: Mid Premium | B83: Modular | C83: Wet / Exposed Area | D83: Base Storage, Wall Storage, Tall Storage, Wardrobe | E83: Carcass/shutter | F83: Core Material, Finish Material, Hinges | G83: Carcass inner 1mm - BWP / Shutter - Plywood Border with Fluted Glass , Glossy Finish , Soft Close | H83: Hettich Onsys , , Advance , New Mika , Rotolam, Carcass / Shutter - Century Sainik or Green Absolute with Glass | J83: =J14+50 -> 2300 | K83: 0.25 | L83: =J83*K83 -> 575 | M83: =J83+L83 -> 2875
A84: Mid Premium | B84: Modular | C84: Wet / Exposed Area | D84: Base Storage, Wall Storage, Tall Storage, Wardrobe | E84: Carcass/shutter | F84: Core Material, Finish Material, Hinges | G84: Carcass Inner 1mm- BWP / Shutter - Black / Silver colour Aluminium Profile with Clear or Tinted Glass , Glossy Finish , Soft Close | H84: , Hettich Onsys, Advance , New Mika , Rotolam, Carcass -Century Sainik or Green Absolute / Shutter - CNR Aluminium Profile Shutters | J84: =J15+50 -> 2650 | K84: 0.25 | L84: =J84*K84 -> 662.5 | M84: =J84+L84 -> 3312.5
A85: Mid Premium | B85: Modular | C85: Wet / Exposed Area | D85: Base Storage, Wall Storage, Tall Storage, Wardrobe | E85: Carcass/shutter | F85: Core Material, Finish Material, Hinges | G85: Carcass Inner 1mm - BWP / Shutter - Black / Silver colour Aluminium Profile with Fluted Glass, Glossy Finish , Soft Close | H85: , Hettich Onsys, Advance , New Mika , Rotolam, Carcass -Century Sainik or Green Absolute / Shutter - CNR Aluminium Profile Shutters | J85: =J16+50 -> 2750 | K85: 0.25 | L85: =J85*K85 -> 687.5 | M85: =J85+L85 -> 3437.5
A86: Mid Premium | B86: Modular | C86: Wet / Exposed Area | D86: Base Storage, Wall Storage, Tall Storage, Wardrobe | E86: Carcass/shutter | F86: Core Material, Finish Material, Hinges | G86: Carcass Inner 1mm- BWP / Shutter - Gold / Rose Gold colour Aluminium Profile with Clear or Tinted Glass, Glossy Finish , Soft Close | H86: , Hettich Onsys, Advance , New Mika , Rotolam, Carcass -Century Sainik or Green Absolute / Shutter - CNR Aluminium Profile Shutters | J86: =J17+50 -> 2750 | K86: 0.25 | L86: =J86*K86 -> 687.5 | M86: =J86+L86 -> 3437.5
A87: Mid Premium | B87: Modular | C87: Wet / Exposed Area | D87: Base Storage, Wall Storage, Tall Storage, Wardrobe | E87: Carcass/shutter | F87: Core Material, Finish Material, Hinges | G87: Carcass Inner 1mm - BWP / Shutter - Gold / Rose Gold colour Aluminium Profile with Fluted Glass, Glossy Finish , Soft Close | H87: , Hettich Onsys, Advance , New Mika , Rotolam, Carcass -Century Sainik or Green Absolute / Shutter - CNR Aluminium Profile Shutters | J87: =J18+50 -> 2850 | K87: 0.25 | L87: =J87*K87 -> 712.5 | M87: =J87+L87 -> 3562.5
... A98: Mid Premium | B98: Modular | C98: Wet / Exposed Area | D98: Panel | E98: Wallpanel , pelmet , Base panel / Side panel , Jam Panel, Chimney Panel | F98: Finish Material, Core Material | G98: Glossy Finish , CARCASS - BWP | H98: Century Sainik or Green Absolute, New Mika , Advance , Rotolam | J98: =J29+50 -> 1050 | K98: 0.25 | L98: =J98*K98 -> 262.5 | M98: =J98+L98 -> 1312.5
D99: Panel | E99: Ceiling Panel | G99: Glossy Finish , CARCASS - BWP | J99: =J30+50 -> 1217 | K99: 0.25 | L99: =J99*K99 -> 304.25 | M99: =L99+J99 -> 1521.25
A100: Mid Premium | K100: 0.25 | L100: =J100*K100 -> 0 | M100: =J100+L100 -> 0
A101: Mid Premium | B101: Modular | C101: Dry / Inexposed area | D101: Base Storage, Wall Storage, Tall Storage, Wardrobe | E101: Carcass/shutter | F101: Core Material, Finish Material, Hinges | G101: Glossy Finish, Soft Close, Carcass - MR / Shutter - HDHMR | H101: Carcass - Century Sainik or Greenply Absolute / Shutter - Green Panel, Hettich Onsys , , New Mika , Advance , Rotolam | J101: =J32+50 -> 1550 | K101: 0.25 | L101: =J101*K101 -> 387.5 | M101: =J101+L101 -> 1937.5
D102: Base Storage - Inner 1mm, Wall Storage - inner 1mm, Tall Storage - Inner 1mm | E102: Carcass, Shutter | F102: Core Material, Finish Material, Hinges | G102: Glossy Finish, Soft Close, Carcass - MR / Shutter - HDHMR | H102: Carcass - Century Sainik or Green Absolute / Shutter - Green Panel, Hettich Onsys , , Advance , New Mika , Rotolam | I102: Supply and installation of Base storage - Inner 1mm unit with BWP Carcass, HDHMR Shutter, Smooth finish laminate and soft close hinges | J102: =J36+50 -> 1700 | K102: 0.25 | L102: =J102*K102 -> 425 | M102: =J102+L102 -> 2125
H103: Carcass - Century Sainik or Green Absolute / Shutter - Green Panel, Hettich Onsys , , Advance , New Mika , Rotolam | I103: Supply and installation of Wall storage - Inner 1mm unit with BWP Carcass, HDHMR Shutter, Smooth finish laminate and soft close hinges
H104: Carcass - Century Sainik or Green Absolute / Shutter - Green Panel, Hettich Onsys , , Advance , New Mika , Rotolam | I104: Supply and installation of Tall storage - Inner 1mm unit with BWP Carcass, HDHMR Shutter, Smooth finish laminate and soft close hinges
A105: Mid Premium | B105: Modular | C105: Dry / Inexposed area | D105: Base Storage, Wall Storage, Tall Storage, Wardrobe | E105: Carcass/shutter | F105: Core Material, Finish Material, Hinges | G105: Carcass - MR/ Shutter - Plywood Border with Clear / Tinted Glass , Glossy Finish , Soft Close | H105: Carcass - Century Sainik or Greenply Absolute / Shutter - Green Panel, Hettich Onsys , , New Mika , Advance , Rotolam | J105: =J39+50 -> 1955 | K105: 0.25 | L105: =J105*K105 -> 488.75 | M105: =J105+L105 -> 2443.75
A106: Mid Premium | B106: Modular | C106: Dry / Inexposed area | D106: Base Storage, Wall Storage, Tall Storage, Wardrobe | E106: Carcass/shutter | F106: Core Material, Finish Material, Hinges | G106: Carcass - MR / Shutter - Ply wood border with Fluted Glass , Glossy Finish , Soft Close | H106: Hettich Onsys , , Advance , New Mika , Rotolam, Carcass - Century Sainik or Green Absolute / Shutter - Green Panel with Glass | J106: =J40+50 -> 2075 | K106: 0.25 | L106: =J106*K106 -> 518.75 | M106: =J106+L106 -> 2593.75
A107: Mid Premium | B107: Modular | C107: Dry / Inexposed area | D107: Base Storage, Wall Storage, Tall Storage, Wardrobe | E107: Carcass/shutter | F107: Core Material, Finish Material, Hinges | G107: Carcass - MR / Shutter - Black / Silver colour Aluminium Profile with Clear or Tinted Glass , Glossy Finish , Soft Close | H107: Cracass - Century Sainik or Greenply Absolute / Shutter - Imported Aluminium Profile shutter, , Hettich Onsys, Advance , New Mika , Rotolam | J107: =J41+50 -> 2400 | K107: 0.25 | L107: =J107*K107 -> 600 | M107: =J107+L107 -> 3000
A108: Mid Premium | B108: Modular | C108: Dry / Inexposed area | D108: Base Storage, Wall Storage, Tall Storage, Wardrobe | E108: Carcass/shutter | F108: Core Material, Finish Material, Hinges | G108: Carcass - MR / Shutter - Black / Silver colour Aluminium Profile with Fluted Glass, Soft Close, Glossy Finish | H108: Cracass - Century Sainik or Greenply Absolute / Shutter - Imported Aluminium Profile shutter, , Hettich Onsys, Advance , New Mika , Rotolam | J108: =J42+50 -> 2500 | K108: 0.25 | L108: =J108*K108 -> 625 | M108: =J108+L108 -> 3125
A109: Mid Premium | B109: Modular | C109: Dry / Inexposed area | D109: Base Storage, Wall Storage, Tall Storage, Wardrobe | E109: Carcass/shutter | F109: Core Material, Finish Material, Hinges | G109: Carcass - MR / Shutter - Gold / Rose Gold Aluminium Profile with Clear Glass , Glossy Finish , Soft Close | H109: Cracass - Century Sainik or Greenply Absolute / Shutter - Imported Aluminium Profile shutter, , Hettich Onsys, Advance , New Mika , Rotolam | J109: =J43+50 -> 2500 | K109: 0.25 | L109: =J109*K109 -> 625 | M109: =J109+L109 -> 3125
A110: Mid Premium | B110: Modular | C110: Dry / Inexposed area | D110: Base Storage, Wall Storage, Tall Storage, Wardrobe | E110: Carcass/shutter | F110: Core Material, Finish Material, Hinges | G110: Carcass - MR / Shutter - Colour Aluminium profile with Fluted Glass , Glossy Finish , Soft Close | H110: Cracass - Century Sainik or Greenply Absolute / Shutter - Imported Aluminium Profile shutter, , Hettich Onsys, Advance , New Mika , Rotolam | J110: =J44+50 -> 2600 | K110: 0.25 | L110: =J110*K110 -> 650 | M110: =J110+L110 -> 3250
...

Sheet Premium
A1: Project Type | B1: Section | C1: Room Type | D1: Unit Type | E1: Panel type | F1: Category | G1: Material Type | H1: Brand | I1: Description | J1: Rate | K1: Hinges rate | L1: Basic Value | M1: Mark up | N1: Margin | O1: Selling Price
A2: SMOOTH FINISH
A3: Mid Premium | B3: Modular | C3: Wet / Exposed Area | D3: Base Storage, Wall Storage, Tall Storage, Wardrobe | E3: Carcass/shutter | F3: Core Material, Finish Material, Hinges | G3: Carcass - BWP / Shutter - HDHMR Boilo, Smooth Finish, Soft Close | H3: Carcass - Century Bond or Green OptimaG / Shutter - Action TESA, Hettich Veyosis or Hafele Eqv , , Greenlam , Century lam , Merino | I3: Supply and installation of Base storage unit with BWP Carcass, HDHMR Boilo Shutter, Smooth finish laminate and soft close hinges | J3: 1715 | L3: =J3+K3 -> 1715 | M3: 0.25 | N3: =L3*M3 -> 428.75 | O3: =L3+N3 -> 2143.75
I4: Supply and installation of Wall storage unit with BWP Carcass, HDHMR Boilo Shutter, Smooth finish laminate and soft close hinges
I5: Supply and installation of Tall storage unit with BWP Carcass, HDHMR Boilo Shutter, Smooth finish laminate and soft close hinges
I6: Supply and installation of Wardrobe with BWP Carcass, HDHMR Boilo Shutter, Smooth finish laminate and soft close hinges
A7: Mid Premium | B7: Modular | C7: Wet / Exposed Area | D7: Base Storage, Wall Storage, Tall Storage, Wardrobe | E7: Carcass/shutter | F7: Core Material, Finish Material, Hinges | G7: Carcass - BWP / Shutter - Plywood Border with Clear / Tinted Glass , Soft Close, Smooth Finish | H7: Hettich Veyosis or Hafele Eqv , , Greenlam , Century lam , Merino, Carcass / Shutter - Century Bond or Green OptimaG with Glass | J7: 2095 | L7: =J7+K7 -> 2095 | M7: 0.25 | N7: =L7*M7 -> 523.75 | O7: =L7+N7 -> 2618.75
A8: Mid Premium | B8: Modular | C8: Wet / Exposed Area | D8: Base Storage, Wall Storage, Tall Storage, Wardrobe | E8: Carcass/shutter | F8: Core Material, Finish Material, Hinges | G8: Carcass - BWP / Shutter - Plywood Border with Fluted Glass , Smooth Finish , Soft Close | H8: Hettich Veyosis or Hafele Eqv , , Greenlam , Century lam , Merino, Carcass / Shutter - Century Bond or Green OptimaG with Glass | J8: 2215 | L8: =J8+K8 -> 2215 | M8: 0.25 | N8: =L8*M8 -> 553.75 | O8: =L8+N8 -> 2768.75
A9: Mid Premium | B9: Modular | C9: Wet / Exposed Area | D9: Base Storage, Wall Storage, Tall Storage, Wardrobe | E9: Carcass/shutter | F9: Core Material, Finish Material, Hinges | G9: Carcass - BWP / Shutter - Black / Silver colour Aluminium Profile with Clear or Tinted Glass, Smooth Finish , Soft Close | H9: , Hettich Veyosis or Hafele Eqv, Greenlam , Century lam , Merino, Carcass -Century Bond or Green OptimaG / Shutter - CNR Aluminium Profile Shutters | J9: 2250 | L9: =J9+K9 -> 2250 | M9: 0.25 | N9: =L9*M9 -> 562.5 | O9: =L9+N9 -> 2812.5
A10: Mid Premium | B10: Modular | C10: Wet / Exposed Area | D10: Base Storage, Wall Storage, Tall Storage, Wardrobe | E10: Carcass/shutter | F10: Core Material, Finish Material, Hinges | G10: Carcass - BWP / Shutter - Black / Silver colour Aluminium Profile with Fluted Glass, Smooth Finish , Soft Close | H10: , Hettich Veyosis or Hafele Eqv, Greenlam , Century lam , Merino, Carcass -Century Bond or Green OptimaG / Shutter - CNR Aluminium Profile Shutters | J10: 2350 | L10: =J10+K10 -> 2350 | M10: 0.25 | N10: =L10*M10 -> 587.5 | O10: =L10+N10 -> 2937.5
A11: Mid Premium | B11: Modular | C11: Wet / Exposed Area | D11: Base Storage, Wall Storage, Tall Storage, Wardrobe | E11: Carcass/shutter | F11: Core Material, Finish Material, Hinges | G11: Carcass - BWP / Shutter - / Rose colour Aluminium Profile with Clear or Tinted Glass, Soft Close, Smooth Finish | H11: , Hettich Veyosis or Hafele Eqv, Greenlam , Century lam , Merino, Carcass -Century Bond or Green OptimaG / Shutter - CNR Aluminium Profile Shutters | J11: 2350 | L11: =J11+K11 -> 2350 | M11: 0.25 | N11: =L11*M11 -> 587.5 | O11: =L11+N11 -> 2937.5
A12: Mid Premium | B12: Modular | C12: Wet / Exposed Area | D12: Base Storage, Wall Storage, Tall Storage, Wardrobe | E12: Carcass/shutter | F12: Core Material, Finish Material, Hinges | G12: Carcass - BWP / Shutter - / Rose colour Aluminium Profile with Fluted Glass, Smooth Finish , Soft Close | H12: , Hettich Veyosis or Hafele Eqv, Greenlam , Century lam , Merino, Carcass -Century Bond or Green OptimaG / Shutter - CNR Aluminium Profile Shutters | J12: 2450 | L12: =J12+K12 -> 2450 | M12: 0.25 | N12: =L12*M12 -> 612.5 | O12: =L12+N12 -> 3062.5
A13: Mid Premium | B13: Modular | C13: Wet / Exposed Area | D13: Base Storage, Wall Storage, Tall Storage, Wardrobe | E13: Carcass/shutter | F13: Core Material, Finish Material, Hinges | G13: Carcass Inner 1mm- BWP / Shutter - Plywood Border with Clear / Tinted Glass , Smooth Finish , Soft Close | H13: Hettich Veyosis or Hafele Eqv , , Greenlam , Century lam , Merino, Carcass / Shutter - Century Bond or Green OptimaG with Glass | J13: 2345 | L13: =J13+K13 -> 2345 | M13: 0.25 | N13: =L13*M13 -> 586.25 | O13: =L13+N13 -> 2931.25
A14: Mid Premium | B14: Modular | C14: Wet / Exposed Area | D14: Base Storage, Wall Storage, Tall Storage, Wardrobe | E14: Carcass/shutter | F14: Core Material, Finish Material, Hinges | G14: Carcass inner 1mm - BWP / Shutter - Plywood Border with Fluted Glass , Smooth Finish , Soft Close | H14: Hettich Veyosis or Hafele Eqv , , Greenlam , Century lam , Merino, Carcass / Shutter - Century Bond or Green OptimaG with Glass | J14: 2465 | L14: =J14+K14 -> 2465 | M14: 0.25 | N14: =L14*M14 -> 616.25 | O14: =L14+N14 -> 3081.25
A15: Mid Premium | B15: Modular | C15: Wet / Exposed Area | D15: Base Storage, Wall Storage, Tall Storage, Wardrobe | E15: Carcass/shutter | F15: Core Material, Finish Material, Hinges | G15: Carcass Inner 1mm- BWP / Shutter - Black / Silver colour Aluminium Profile with Clear or Tinted Glass , Smooth Finish , Soft Close | H15: , Hettich Veyosis or Hafele Eqv, Greenlam , Century lam , Merino, Carcass -Century Bond or Green OptimaG / Shutter - CNR Aluminium Profile Shutters | J15: 2500 | L15: =J15+K15 -> 2500 | M15: 0.25 | N15: =L15*M15 -> 625 | O15: =L15+N15 -> 3125
A16: Mid Premium | B16: Modular | C16: Wet / Exposed Area | D16: Base Storage, Wall Storage, Tall Storage, Wardrobe | E16: Carcass/shutter | F16: Core Material, Finish Material, Hinges | G16: Carcass Inner 1mm - BWP / Shutter - Black / Silver colour Aluminium Profile with Fluted Glass, Smooth Finish , Soft Close | H16: , Hettich Veyosis or Hafele Eqv, Greenlam , Century lam , Merino, Carcass -Century Bond or Green OptimaG / Shutter - CNR Aluminium Profile Shutters | J16: 2600 | L16: =J16+K16 -> 2600 | M16: 0.25 | N16: =L16*M16 -> 650 | O16: =L16+N16 -> 3250
A17: Mid Premium | B17: Modular | C17: Wet / Exposed Area | D17: Base Storage, Wall Storage, Tall Storage, Wardrobe | E17: Carcass/shutter | F17: Core Material, Finish Material, Hinges | G17: Carcass Inner 1mm - BWP / Shutter - / Rose colour Aluminium Profile with Fluted Glass, Smooth Finish , Soft Close | H17: , Hettich Veyosis or Hafele Eqv, Greenlam , Century lam , Merino, Carcass -Century Bond or Green OptimaG / Shutter - CNR Aluminium Profile Shutters | J17: 2600 | L17: =J17+K17 -> 2600 | M17: 0.25 | N17: =L17*M17 -> 650 | O17: =L17+N17 -> 3250
A18: Mid Premium | B18: Modular | C18: Wet / Exposed Area | D18: Base Storage, Wall Storage, Tall Storage, Wardrobe | E18: Carcass/shutter | F18: Core Material, Finish Material, Hinges | G18: Carcass Inner 1mm- BWP / Shutter - / Rose colour Aluminium Profile with Clear or Tinted Glass, Smooth Finish , Soft Close | H18: , Hettich Veyosis or Hafele Eqv, Greenlam , Century lam , Merino, Carcass -Century Bond or Green OptimaG / Shutter - CNR Aluminium Profile Shutters | J18: 2700 | L18: =J18+K18 -> 2700 | M18: 0.25 | N18: =L18*M18 -> 675 | O18: =L18+N18 -> 3375
A19: Mid Premium | B19: Modular | C19: Wet / Exposed Area | D19: Curved Shape Base Storage unit | E19: Carcass/shutter | F19: Core Material, Finish Material, Hinges | G19: Carcass - BWP / Shutter - HDHMR Boilo, Smooth Finish , Soft Close | H19: Carcass - Century Bond or Green OptimaG / Shutter - Action TESA, Hettich Veyosis or Hafele Eqv , , Greenlam , Century lam , Merino | I19: Supply and installation of Curved Base storage unit with BWP Carcass, HDHMR Boilo Shutter, Smooth finish laminate and soft close hinges | J19: 2065 | L19: =J19+K19 -> 2065 | M19: 0.25 | N19: =L19*M19 -> 516.25 | O19: =L19+N19 -> 2581.25
A20: Mid Premium | B20: Modular | C20: Wet / Exposed Area | D20: Curved Shape Drawer Storage unit | E20: Carcass/shutter | F20: Core Material, Finish Material | G20: Carcass - BWP / Shutter - HDHMR Boilo, Smooth Finish | H20: Carcass - Century Bond or Green OptimaG / Shutter - Action TESA, Century lam , Merino , Greenlam | J20: 2065 | L20: =J20+K20 -> 2065 | M20: 0.25 | N20: =L20*M20 -> 516.25 | O20: =L20+N20 -> 2581.25
A21: Mid Premium | B21: Modular | C21: Wet / Exposed Area | D21: Tambour Storage | E21: Carcass | F21: Core Material, Finish Material | G21: CARCASS - BWP, Smooth Finish | H21: Carcass - Century Bond or Green OptimaG, Greenlam, Century lam , Merino | J21: 1465 | L21: =J21+K21 -> 1465 | M21: 0.25 | N21: =L21*M21 -> 366.25 | O21: =L21+N21 -> 1831.25
A22: Mid Premium | B22: Modular | C22: Wet / Exposed Area | D22: Open Unit - Inner 1mm | E22: Carcass | F22: Core Material, Finish Material | G22: CARCASS - BWP, Smooth Finish | H22: Carcass - Century Bond or Green OptimaG, Greenlam, Century lam , Merino | I22: Supply and installation of Open unit - Inner 1mm with BWP ply frame and Smooth finish laminate | J22: 1715 | L22: =J22+K22 -> 1715 | M22: 0.25 | N22: =L22*M22 -> 428.75 | O22: =L22+N22 -> 2143.75
A23: Mid Premium | B23: Modular | C23: Wet / Exposed Area | D23: Loft | E23: Frame and Shutter | F23: Core Material, Finish Material, Hinges | G23: Smooth Finish, Soft Close, Frame - BWP / Shutter - HDHMR Boilo | H23: Hettich Veyosis or Hafele Eqv , , Greenlam , Century lam , Merino, Frame- Century Bond or Green OptimaG / Shutter - Action TESA, | J23: 958 | L23: =J23+K23 -> 958 | M23: 0.25 | N23: =L23*M23 -> 239.5 | O23: =L23+N23 -> 1197.5
A24: Mid Premium | B24: Modular | C24: Wet / Exposed Area | D24: Ledge | E24: Ledge -25mm | F24: Finish Material, Core Material | G24: Smooth Finish , CARCASS - BWP | H24: Ledge - Century Bond or Green OptimaG, Greenlam , Century lam , Merino | I24: Supply and installation of Ledge with 25mm Ledge BWP and Smooth Finish Laminate | J24: 875 | L24: =J24+K24 -> 875 | M24: 0.25 | N24: =L24*M24 -> 218.75 | O24: =L24+N24 -> 1093.75
A25: Mid Premium | B25: Modular | C25: Wet / Exposed Area | D25: Ledge | E25: Ledge -36mm | F25: Finish Material, Core Material | G25: Smooth Finish , CARCASS - BWP | H25: Ledge - Century Bond or Green OptimaG, Greenlam , Century lam , Merino | I25: Supply and installation of Ledge with 36mm Ledge BWP and Smooth Finish Laminate | J25: 875 | L25: =J25+K25 -> 875 | M25: 0.25 | N25: =L25*M25 -> 218.75 | O25: =L25+N25 -> 1093.75
A26: Mid Premium | B26: Modular | C26: Wet / Exposed Area | D26: Ledge | E26: Ledge -50mm | F26: Finish Material, Core Material | G26: Smooth Finish , CARCASS - BWP | H26: Ledge - Century Bond or Green OptimaG, Greenlam , Century lam , Merino | I26: Supply and installation of Ledge with 50mm Ledge BWP and Smooth Finish Laminate | J26: 1025 | L26: =J26+K26 -> 1025 | M26: 0.25 | N26: =L26*M26 -> 256.25 | O26: =L26+N26 -> 1281.25
A27: Mid Premium | B27: Modular | C27: Wet / Exposed Area | D27: Partition | E27: Partition -75mm | F27: Finish Material, Core Material | G27: Smooth Finish , CARCASS - BWP | H27: Century Bond or Green OptimaG , Greenlam , Century lam , Merino | I27: Supply and installation of Ledge with 75mm Ledge BWP and Smooth Finish Laminate | J27: 1675 | L27: =J27+K27 -> 1675 | M27: 0.25 | N27: =L27*M27 -> 418.75 | O27: =L27+N27 -> 2093.75
A28: Mid Premium | B28: Modular | C28: Wet / Exposed Area | D28: Panel | E28: Curved Shape Panel | F28: Finish Material, Core Material | G28: Smooth Finish , CARCASS - BWP | H28: Century Bond or Green OptimaG, Century lam , Greenlam , Merino | I28: Supply and installation of Curved Wall Panel with BWP Ply Frame, Smooth Finish laminate | J28: 1008 | L28: =J28+K28 -> 1008 | M28: 0.25 | N28: =L28*M28 -> 252 | O28: =L28+N28 -> 1260
A29: Mid Premium | B29: Modular | C29: Wet / Exposed Area | D29: Panel | E29: Wallpanel , pelmet , Ceiling Panel , Base panel / Side panel | F29: Finish Material, Core Material | G29: Smooth Finish , CARCASS - BWP | H29: Century Bond or Green OptimaG, Century lam , Greenlam , Merino | I29: Supply and installation of Wall Panel with BWP Ply Frame, Smooth Finish laminate | J29: 1050 | L29: =J29+K29 -> 1050 | M29: 0.25 | N29: =L29*M29 -> 262.5 | O29: =L29+N29 -> 1312.5
I30: Supply and installation of Pelmet Panel with BWP Ply Frame, Smooth Finish laminate
I31: Supply and installation of Jam Panel with BWP Ply Frame, Smooth Finish laminate
I32: Supply and installation of Ceiling Panel with BWP Ply Frame, Smooth Finish laminate
I33: Supply and installation of Base Panel with BWP Ply Frame, Smooth Finish laminate
L34: =J34+K34 -> 0 | M34: 0.25 | N34: =L34*M34 -> 0 | O34: =L34+N34 -> 0
A35: GLOSSY FINISH | L35: =J35+K35 -> 0 | M35: 0.25 | N35: =L35*M35 -> 0 | O35: =L35+N35 -> 0
A36: Mid Premium | B36: Section | C36: Room Type | D36: Unit Type | E36: Panel type | F36: Category | G36: Material Type | H36: Brand | J36: Rate | L36: =J36+K36 -> #VALUE! | M36: 0.25 | N36: =L36*M36 -> #VALUE! | O36: =L36+N36 -> #VALUE!
A37: Mid Premium | B37: Modular | C37: Wet / Exposed Area | D37: Base Storage, Wall Storage, Tall Storage, Wardrobe | E37: Carcass/shutter | F37: Core Material, Finish Material, Hinges | G37: Carcass - BWP / Shutter - HDHMR Boilo, Glossy Finish, Soft Close | H37: Carcass - Century Bond or Green OptimaG / Shutter - Action TESA, Hettich Veyosis or Hafele Eqv , , Greenlam , Century lam , Merino | I37: Supply and installation of Base storage unit with BWP Carcass, HDHMR Boilo Shutter, Glossy finish laminate and soft close hinges | J37: =J3+50 -> 1765 | L37: =J37+K37 -> 1765 | M37: 0.25 | N37: =L37*M37 -> 441.25 | O37: =L37+N37 -> 2206.25
I38: Supply and installation of Wall storage unit with BWP Carcass, HDHMR Boilo Shutter, Glossy finish laminate and soft close hinges
I39: Supply and installation of Tall storage unit with BWP Carcass, HDHMR Boilo Shutter, Glossy finish laminate and soft close hinges
I40: Supply and installation of Wardrobe with BWP Carcass, HDHMR Boilo Shutter, Glossy finish laminate and soft close hinges
A41: Mid Premium | B41: Modular | C41: Wet / Exposed Area | D41: Base Storage, Wall Storage, Tall Storage, Wardrobe | E41: Carcass/shutter | F41: Core Material, Finish Material, Hinges | G41: Carcass - BWP / Shutter - Plywood Border with Clear / Tinted Glass , Soft Close, Glossy Finish | H41: Hettich Veyosis or Hafele Eqv , , Greenlam , Century lam , Merino, Carcass / Shutter - Century Bond or Green OptimaG with Glass | I41: Supply and installation of Base storage unit with BWP Carcass, Plywood Border with Clear/Tinted Glass Shutter, Glossy laminate and soft close hinges | J41: =J7+50 -> 2145 | L41: =J41+K41 -> 2145 | M41: 0.25 | N41: =L41*M41 -> 536.25 | O41: =L41+N41 -> 2681.25
I42: Supply and installation of Wall storage unit with BWP Carcass, Plywood Border with Clear/Tinted Glass Shutter, Glossy laminate and soft close hinges
I43: Supply and installation of Tall storage unit with BWP Carcass, Plywood Border with Clear/Tinted Glass Shutter, Glossy laminate and soft close hinges
I44: Supply and installation of Wardrobe with BWP Carcass, Plywood Border with Clear/Tinted Glass Shutter, Glossy laminate and soft close hinges
A45: Mid Premium | B45: Modular | C45: Wet / Exposed Area | D45: Base Storage, Wall Storage, Tall Storage, Wardrobe | E45: Carcass/shutter | F45: Core Material, Finish Material, Hinges | G45: Carcass - BWP / Shutter - Plywood Border with Fluted Glass , Glossy Finish , Soft Close | H45: Hettich Veyosis or Hafele Eqv , , Greenlam , Century lam , Merino, Carcass / Shutter - Century Bond or Green OptimaG with Glass | I45: Supply and installation of Base storage unit with BWP Carcass, Plywood Border with Fluted Glass Shutter, Glossy laminate and soft close hinges | J45: =J8+50 -> 2265 | L45: =J45+K45 -> 2265 | M45: 0.25 | N45: =L45*M45 -> 566.25 | O45: =L45+N45 -> 2831.25
I46: Supply and installation of Wall storage unit with BWP Carcass, Plywood Border with Fluted Glass Shutter, Glossy laminate and soft close hinges
I47: Supply and installation of Tall storage unit with BWP Carcass, Plywood Border with Fluted Glass Shutter, Glossy laminate and soft close hinges
I48: Supply and installation of Wardrobe with BWP Carcass, Plywood Border with Fluted Glass Shutter, Glossy laminate and soft close hinges
A49: Mid Premium | B49: Modular | C49: Wet / Exposed Area | D49: Base Storage, Wall Storage, Tall Storage, Wardrobe | E49: Carcass/shutter | F49: Core Material, Finish Material, Hinges | G49: Carcass - BWP / Shutter - Black / Silver colour Aluminium Profile with Clear or Tinted Glass, Glossy Finish , Soft Close | H49: , Hettich Veyosis or Hafele Eqv, Greenlam , Century lam , Merino, Carcass -Century Bond or Green OptimaG / Shutter - CNR Aluminium Profile Shutters | J49: =J9+50 -> 2300 | L49: =J49+K49 -> 2300 | M49: 0.25 | N49: =L49*M49 -> 575 | O49: =L49+N49 -> 2875
A50: Mid Premium | B50: Modular | C50: Wet / Exposed Area | D50: Base Storage, Wall Storage, Tall Storage, Wardrobe | E50: Carcass/shutter | F50: Core Material, Finish Material, Hinges | G50: Carcass - BWP / Shutter - Black / Silver colour Aluminium Profile with Fluted Glass, Glossy Finish , Soft Close | H50: , Hettich Veyosis or Hafele Eqv, Greenlam , Century lam , Merino, Carcass -Century Bond or Green OptimaG / Shutter - CNR Aluminium Profile Shutters | J50: =J10+50 -> 2400 | L50: =J50+K50 -> 2400 | M50: 0.25 | N50: =L50*M50 -> 600 | O50: =L50+N50 -> 3000
A51: Mid Premium | B51: Modular | C51: Wet / Exposed Area | D51: Base Storage, Wall Storage, Tall Storage, Wardrobe | E51: Carcass/shutter | F51: Core Material, Finish Material, Hinges | G51: Carcass - BWP / Shutter - / Rose colour Aluminium Profile with Clear or Tinted Glass, Soft Close, Glossy Finish | H51: , Hettich Veyosis or Hafele Eqv, Greenlam , Century lam , Merino, Carcass -Century Bond or Green OptimaG / Shutter - CNR Aluminium Profile Shutters | J51: =J11+50 -> 2400 | L51: =J51+K51 -> 2400 | M51: 0.25 | N51: =L51*M51 -> 600 | O51: =L51+N51 -> 3000
A52: Mid Premium | B52: Modular | C52: Wet / Exposed Area | D52: Base Storage, Wall Storage, Tall Storage, Wardrobe | E52: Carcass/shutter | F52: Core Material, Finish Material, Hinges | G52: Carcass - BWP / Shutter - / Rose colour Aluminium Profile with Fluted Glass, Glossy Finish , Soft Close | H52: , Hettich Veyosis or Hafele Eqv, Greenlam , Century lam , Merino, Carcass -Century Bond or Green OptimaG / Shutter - CNR Aluminium Profile Shutters | J52: =J12+50 -> 2500 | L52: =J52+K52 -> 2500 | M52: 0.25 | N52: =L52*M52 -> 625 | O52: =L52+N52 -> 3125
A53: Mid Premium | B53: Modular | C53: Wet / Exposed Area | D53: Base Storage, Wall Storage, Tall Storage, Wardrobe | E53: Carcass/shutter | F53: Core Material, Finish Material, Hinges | G53: Carcass Inner 1mm- BWP / Shutter - Plywood Border with Clear / Tinted Glass , Glossy Finish , Soft Close | H53: Hettich Veyosis or Hafele Eqv , , Greenlam , Century lam , Merino, Carcass / Shutter - Century Bond or Green OptimaG with Glass | J53: =J13+50 -> 2395 | L53: =J53+K53 -> 2395 | M53: 0.25 | N53: =L53*M53 -> 598.75 | O53: =L53+N53 -> 2993.75
A54: Mid Premium | B54: Modular | C54: Wet / Exposed Area | D54: Base Storage, Wall Storage, Tall Storage, Wardrobe | E54: Carcass/shutter | F54: Core Material, Finish Material, Hinges | G54: Carcass inner 1mm - BWP / Shutter - Plywood Border with Fluted Glass , Glossy Finish , Soft Close | H54: Hettich Veyosis or Hafele Eqv , , Greenlam , Century lam , Merino, Carcass / Shutter - Century Bond or Green OptimaG with Glass | J54: =J14+50 -> 2515 | L54: =J54+K54 -> 2515 | M54: 0.25 | N54: =L54*M54 -> 628.75 | O54: =L54+N54 -> 3143.75
A55: Mid Premium | B55: Modular | C55: Wet / Exposed Area | D55: Base Storage, Wall Storage, Tall Storage, Wardrobe | E55: Carcass/shutter | F55: Core Material, Finish Material, Hinges | G55: Carcass Inner 1mm- BWP / Shutter - Black / Silver colour Aluminium Profile with Clear or Tinted Glass , Glossy Finish , Soft Close | H55: , Hettich Veyosis or Hafele Eqv, Greenlam , Century lam , Merino, Carcass -Century Bond or Green OptimaG / Shutter - CNR Aluminium Profile Shutters | I55: Supply and installation of Base storage - Inner 1mm unit with BWP Carcass, Black/Silver Aluminium Profile with Clear/Tinted Glass Shutter, Glossy laminate and soft close hinges | J55: =J15+50 -> 2550 | L55: =J55+K55 -> 2550 | M55: 0.25 | N55: =L55*M55 -> 637.5 | O55: =L55+N55 -> 3187.5
I56: Supply and installation of Wall storage - Inner 1mm unit with BWP Carcass, Black/Silver Aluminium Profile with Clear/Tinted Glass Shutter, Glossy laminate and soft close hinges
I57: Supply and installation of Tall storage - Inner 1mm unit with BWP Carcass, Black/Silver Aluminium Profile with Clear/Tinted Glass Shutter, Glossy laminate and soft close hinges
I58: Supply and installation of Wardrobe - Inner 1mm unit with BWP Carcass, Black/Silver Aluminium Profile with Clear/Tinted Glass Shutter, Glossy laminate and soft close hinges
A59: Mid Premium | B59: Modular | C59: Wet / Exposed Area | D59: Base Storage, Wall Storage, Tall Storage, Wardrobe | E59: Carcass/shutter | F59: Core Material, Finish Material, Hinges | G59: Carcass Inner 1mm - BWP / Shutter - Black / Silver colour Aluminium Profile with Fluted Glass, Glossy Finish , Soft Close | H59: , Hettich Veyosis or Hafele Eqv, Greenlam , Century lam , Merino, Carcass -Century Bond or Green OptimaG / Shutter - CNR Aluminium Profile Shutters | J59: =J16+50 -> 2650 | L59: =J59+K59 -> 2650 | M59: 0.25 | N59: =L59*M59 -> 662.5 | O59: =L59+N59 -> 3312.5
A60: Mid Premium | B60: Modular | C60: Wet / Exposed Area | D60: Base Storage, Wall Storage, Tall Storage, Wardrobe | E60: Carcass/shutter | F60: Core Material, Finish Material, Hinges | G60: Carcass Inner 1mm - BWP / Shutter - / Rose colour Aluminium Profile with Fluted Glass, Glossy Finish , Soft Close | H60: , Hettich Veyosis or Hafele Eqv, Greenlam , Century lam , Merino, Carcass -Century Bond or Green OptimaG / Shutter - CNR Aluminium Profile Shutters | J60: =J17+50 -> 2650 | L60: =J60+K60 -> 2650 | M60: 0.25 | N60: =L60*M60 -> 662.5 | O60: =L60+N60 -> 3312.5
A61: Mid Premium | B61: Modular | C61: Wet / Exposed Area | D61: Base Storage, Wall Storage, Tall Storage, Wardrobe | E61: Carcass/shutter | F61: Core Material, Finish Material, Hinges | G61: Carcass Inner 1mm- BWP / Shutter - / Rose colour Aluminium Profile with Clear or Tinted Glass, Glossy Finish , Soft Close | H61: , Hettich Veyosis or Hafele Eqv, Greenlam , Century lam , Merino, Carcass -Century Bond or Green OptimaG / Shutter - CNR Aluminium Profile Shutters | J61: =J18+50 -> 2750 | L61: =J61+K61 -> 2750 | M61: 0.25 | N61: =L61*M61 -> 687.5 | O61: =L61+N61 -> 3437.5
A62: Mid Premium | B62: Modular | C62: Wet / Exposed Area | D62: Curved Shape Base Storage unit | E62: Carcass/shutter | F62: Core Material, Finish Material, Hinges | G62: Carcass - BWP / Shutter - HDHMR Boilo, Glossy Finish , Soft Close | H62: Carcass - Century Bond or Green OptimaG / Shutter - Action TESA, Hettich Veyosis or Hafele Eqv , , Greenlam , Century lam , Merino | I62: Supply and installation of Curved Base storage unit with BWP Carcass, HDHMR Boilo Shutter, Glossy finish laminate and soft close hinges | J62: =J19+50 -> 2115 | L62: =J62+K62 -> 2115 | M62: 0.25 | N62: =L62*M62 -> 528.75 | O62: =L62+N62 -> 2643.75
C63: Wet / Exposed Area | D63: Curved Shape Wall Storage unit | E63: Carcass/shutter | F63: Core Material, Finish Material, Hinges | G63: Carcass - BWP / Shutter - HDHMR Boilo, Glossy Finish , Soft Close | H63: Carcass - Century Bond or Green OptimaG / Shutter - Action TESA, Hettich Veyosis or Hafele Eqv , , Greenlam , Century lam , Merino | I63: Supply and installation of Curved Wall storage unit with BWP Carcass, HDHMR Boilo Shutter, Glossy finish laminate and soft close hinges
A64: Mid Premium | B64: Modular | C64: Wet / Exposed Area | D64: Curved Shape Drawer Storage unit | E64: Carcass/shutter | F64: Core Material, Finish Material | G64: Carcass - BWP / Shutter - HDHMR Boilo, Glossy Finish | H64: Carcass - Century Bond or Green OptimaG / Shutter - Action TESA, Century lam , Merino , Greenlam | J64: =J20+50 -> 2115 | L64: =J64+K64 -> 2115 | M64: 0.25 | N64: =L64*M64 -> 528.75 | O64: =L64+N64 -> 2643.75
A65: Mid Premium | B65: Modular | C65: Wet / Exposed Area | D65: Tambour Storage | E65: Carcass | F65: Core Material, Finish Material | G65: CARCASS - BWP, Glossy Finish | H65: Carcass - Century Bond or Green OptimaG, Greenlam, Century lam , Merino | J65: =J21+50 -> 1515 | L65: =J65+K65 -> 1515 | M65: 0.25 | N65: =L65*M65 -> 378.75 | O65: =L65+N65 -> 1893.75
A66: Mid Premium | B66: Modular | C66: Wet / Exposed Area | D66: Open Unit - Inner 1mm | E66: Carcass | F66: Core Material, Finish Material | G66: CARCASS - BWP, Glossy Finish | H66: Carcass - Century Bond or Green OptimaG, Greenlam, Century lam , Merino | J66: =J22+50 -> 1765 | L66: =J66+K66 -> 1765 | M66: 0.25 | N66: =L66*M66 -> 441.25 | O66: =L66+N66 -> 2206.25
A67: Mid Premium | B67: Modular | C67: Wet / Exposed Area | D67: Loft | E67: Frame and Shutter | F67: Core Material, Finish Material, Hinges | G67: Glossy Finish, Soft Close, Frame - BWP / Shutter - HDHMR Boilo | H67: Hettich Veyosis or Hafele Eqv , , Greenlam , Century lam , Merino, Frame- Century Bond or Green OptimaG / Shutter - Action TESA, | I67: Supply and installation of Loft Frame and Shutter unit with BWP Frame, HDHMR Boilo Shutter, Glossy finish laminate and Soft Close hinges | J67: =J23+50 -> 1008 | L67: =J67+K67 -> 1008 | M67: 0.25 | N67: =L67*M67 -> 252 | O67: =L67+N67 -> 1260
A68: Mid Premium | B68: Modular | C68: Wet / Exposed Area | D68: Ledge | E68: Ledge -25mm | F68: Finish Material, Core Material | G68: Glossy Finish , CARCASS - BWP | H68: Ledge - Century Bond or Green OptimaG, Greenlam , Century lam , Merino | I68: Supply and installation of Ledge with 25mm Ledge BWP and Glossy Finish Laminate | J68: =J24+50 -> 925 | L68: =J68+K68 -> 925 | M68: 0.25 | N68: =L68*M68 -> 231.25 | O68: =L68+N68 -> 1156.25
A69: Mid Premium | B69: Modular | C69: Wet / Exposed Area | D69: Ledge | E69: Ledge -36mm | F69: Finish Material, Core Material | G69: Glossy Finish , CARCASS - BWP | H69: Ledge - Century Bond or Green OptimaG, Greenlam , Century lam , Merino | I69: Supply and installation of Ledge with 36mm Ledge BWP and Glossy Finish Laminate | J69: =J25+50 -> 925 | L69: =J69+K69 -> 925 | M69: 0.25 | N69: =L69*M69 -> 231.25 | O69: =L69+N69 -> 1156.25
A70: Mid Premium | B70: Modular | C70: Wet / Exposed Area | D70: Ledge | E70: Ledge -50mm | F70: Finish Material, Core Material | G70: Glossy Finish , CARCASS - BWP | H70: Ledge - Century Bond or Green OptimaG, Greenlam , Century lam , Merino | I70: Supply and installation of Ledge with 50mm Ledge BWP and Glossy Finish Laminate | J70: =J26+50 -> 1075 | L70: =J70+K70 -> 1075 | M70: 0.25 | N70: =L70*M70 -> 268.75 | O70: =L70+N70 -> 1343.75
A71: Mid Premium | B71: Modular | C71: Wet / Exposed Area | D71: Partition | E71: Partition -75mm | F71: Finish Material, Core Material | G71: Glossy Finish , CARCASS - BWP | H71: Century Bond or Green OptimaG , Greenlam , Century lam , Merino | I71: Supply and installation of Partition with 75mm Ledge BWP and Glossy Finish Laminate | J71: =J27+50 -> 1725 | L71: =J71+K71 -> 1725 | M71: 0.25 | N71: =L71*M71 -> 431.25 | O71: =L71+N71 -> 2156.25
A72: Mid Premium | B72: Modular | C72: Wet / Exposed Area | D72: Panel | E72: Curved Shape Panel | F72: Finish Material, Core Material | G72: Glossy Finish , CARCASS - BWP | H72: Century Bond or Green OptimaG, Century lam , Greenlam , Merino | I72: Supply and installation of Curved Wall Panel with BWP Ply Frame, Glossy Finish laminate | J72: =J28+50 -> 1058 | L72: =J72+K72 -> 1058 | M72: 0.25 | N72: =L72*M72 -> 264.5 | O72: =L72+N72 -> 1322.5
A73: Mid Premium | B73: Modular | C73: Wet / Exposed Area | D73: Panel | E73: Wallpanel , pelmet , Ceiling Panel , Base panel / Side panel | F73: Finish Material, Core Material | G73: Glossy Finish , CARCASS - BWP | H73: Century Bond or Green OptimaG, Century lam , Greenlam , Merino | I73: Supply and installation of Wall Panel with BWP Ply Frame, Glossy Finish laminate | J73: =J29+50 -> 1100 | L73: =J73+K73 -> 1100 | M73: 0.25 | N73: =L73*M73 -> 275 | O73: =L73+N73 -> 1375
I74: Supply and installation of Pelmet Panel with BWP Ply Frame, Glossy Finish laminate
I75: Supply and installation of Jam Panel with BWP Ply Frame, Glossy Finish laminate
I76: Supply and installation of Ceiling Panel with BWP Ply Frame, Glossy Finish laminate
I77: Supply and installation of Base Panel with BWP Ply Frame, Glossy Finish laminate
A78: MR+ FINISH | L78: =J78+K78 -> 0 | M78: 0.25 | N78: =L78*M78 -> 0 | O78: =L78+N78 -> 0
A79: Mid Premium | B79: Section | C79: Room Type | D79: Unit Type | E79: Panel type | F79: Category | G79: Material Type | H79: Brand | J79: Rate | L79: =J79+K79 -> #VALUE! | M79: 0.25 | N79: =L79*M79 -> #VALUE! | O79: =L79+N79 -> #VALUE!
A80: Mid Premium | B80: Modular | C80: Wet / Exposed Area | D80: Base Storage, Wall Storage, Tall Storage, Wardrobe | E80: Carcass/shutter | F80: Core Material, Finish Material, Hinges | G80: Carcass - BWP / Shutter - HDHMR Boilo, MR+ Finish, Soft Close | H80: Carcass - Century Bond or Green OptimaG / Shutter - Action TESA, Hettich Veyosis or Hafele Eqv , , Greenlam , Century lam , Merino | I80: Supply and installation of Base storage unit with BWP Carcass, HDHMR Boilo Shutter, MR+ finish laminate and soft close hinges | J80: =J37+50 -> 1815 | L80: =J80+K80 -> 1815 | M80: 0.25 | N80: =L80*M80 -> 453.75 | O80: =L80+N80 -> 2268.75
I81: Supply and installation of Wall storage unit with BWP Carcass, HDHMR Boilo Shutter, MR+ finish laminate and soft close hinges
I82: Supply and installation of Tall storage unit with BWP Carcass, HDHMR Boilo Shutter, MR+ finish laminate and soft close hinges
I83: Supply and installation of Wardrobe with BWP Carcass, HDHMR Boilo Shutter, MR+ finish laminate and soft close hinges
A84: Mid Premium | B84: Modular | C84: Wet / Exposed Area | D84: Base Storage, Wall Storage, Tall Storage, Wardrobe | E84: Carcass/shutter | F84: Core Material, Finish Material, Hinges | G84: Carcass - BWP / Shutter - Plywood Border with Clear / Tinted Glass , Soft Close, MR+ Finish | H84: Hettich Veyosis or Hafele Eqv , , Greenlam , Century lam , Merino, Carcass / Shutter - Century Bond or Green OptimaG with Glass | J84: =J41+50 -> 2195 | L84: =J84+K84 -> 2195 | M84: 0.25 | N84: =L84*M84 -> 548.75 | O84: =L84+N84 -> 2743.75
A85: Mid Premium | B85: Modular | C85: Wet / Exposed Area | D85: Base Storage, Wall Storage, Tall Storage, Wardrobe | E85: Carcass/shutter | F85: Core Material, Finish Material, Hinges | G85: Carcass - BWP / Shutter - Plywood Border with Fluted Glass , MR+ Finish , Soft Close | H85: Hettich Veyosis or Hafele Eqv , , Greenlam , Century lam , Merino, Carcass / Shutter - Century Bond or Green OptimaG with Glass | J85: =J45+50 -> 2315 | L85: =J85+K85 -> 2315 | M85: 0.25 | N85: =L85*M85 -> 578.75 | O85: =L85+N85 -> 2893.75
A86: Mid Premium | B86: Modular | C86: Wet / Exposed Area | D86: Base Storage, Wall Storage, Tall Storage, Wardrobe | E86: Carcass/shutter | F86: Core Material, Finish Material, Hinges | G86: Carcass - BWP / Shutter - Black / Silver colour Aluminium Profile with Clear or Tinted Glass, MR+ Finish , Soft Close | H86: , Hettich Veyosis or Hafele Eqv, Greenlam , Century lam , Merino, Carcass -Century Bond or Green OptimaG / Shutter - CNR Aluminium Profile Shutters | J86: =J49+50 -> 2350 | L86: =J86+K86 -> 2350 | M86: 0.25 | N86: =L86*M86 -> 587.5 | O86: =L86+N86 -> 2937.5
A87: Mid Premium | B87: Modular | C87: Wet / Exposed Area | D87: Base Storage, Wall Storage, Tall Storage, Wardrobe | E87: Carcass/shutter | F87: Core Material, Finish Material, Hinges | G87: Carcass - BWP / Shutter - Black / Silver colour Aluminium Profile with Fluted Glass, MR+ Finish , Soft Close | H87: , Hettich Veyosis or Hafele Eqv, Greenlam , Century lam , Merino, Carcass -Century Bond or Green OptimaG / Shutter - CNR Aluminium Profile Shutters | I87: Supply and installation of Base storage unit with BWP Carcass, Black/Silver Aluminium Profile with Clear/Tinted Glass Shutter, MR+ laminate and soft close hinges | J87: =J50+50 -> 2450 | L87: =J87+K87 -> 2450 | M87: 0.25 | N87: =L87*M87 -> 612.5 | O87: =L87+N87 -> 3062.5
I88: Supply and installation of Wall storage unit with BWP Carcass, Black/Silver Aluminium Profile with Clear/Tinted Glass Shutter, MR+ laminate and soft close hinges
I89: Supply and installation of Tall storage unit with BWP Carcass, Black/Silver Aluminium Profile with Clear/Tinted Glass Shutter, MR+ laminate and soft close hinges
I90: Supply and installation of Wardrobe with BWP Carcass, Black/Silver Aluminium Profile with Clear/Tinted Glass Shutter, MR+ laminate and soft close hinges
A91: Mid Premium | B91: Modular | C91: Wet / Exposed Area | D91: Base Storage, Wall Storage, Tall Storage, Wardrobe | E91: Carcass/shutter | F91: Core Material, Finish Material, Hinges | G91: Carcass - BWP / Shutter - / Rose colour Aluminium Profile with Clear or Tinted Glass, Soft Close, MR+ Finish | H91: , Hettich Veyosis or Hafele Eqv, Greenlam , Century lam , Merino, Carcass -Century Bond or Green OptimaG / Shutter - CNR Aluminium Profile Shutters | J91: =J51+50 -> 2450 | L91: =J91+K91 -> 2450 | M91: 0.25 | N91: =L91*M91 -> 612.5 | O91: =L91+N91 -> 3062.5
A92: Mid Premium | B92: Modular | C92: Wet / Exposed Area | D92: Base Storage, Wall Storage, Tall Storage, Wardrobe | E92: Carcass/shutter | F92: Core Material, Finish Material, Hinges | G92: Carcass - BWP / Shutter - / Rose colour Aluminium Profile with Fluted Glass, MR+ Finish , Soft Close | H92: , Hettich Veyosis or Hafele Eqv, Greenlam , Century lam , Merino, Carcass -Century Bond or Green OptimaG / Shutter - CNR Aluminium Profile Shutters | J92: =J52+50 -> 2550 | L92: =J92+K92 -> 2550 | M92: 0.25 | N92: =L92*M92 -> 637.5 | O92: =L92+N92 -> 3187.5
A93: Mid Premium | B93: Modular | C93: Wet / Exposed Area | D93: Base Storage, Wall Storage, Tall Storage, Wardrobe | E93: Carcass/shutter | F93: Core Material, Finish Material, Hinges | G93: Carcass Inner 1mm- BWP / Shutter - Plywood Border with Clear / Tinted Glass , MR+ Finish , Soft Close | H93: Hettich Veyosis or Hafele Eqv , , Greenlam , Century lam , Merino, Carcass / Shutter - Century Bond or Green OptimaG with Glass | J93: =J53+50 -> 2445 | L93: =J93+K93 -> 2445 | M93: 0.25 | N93: =L93*M93 -> 611.25 | O93: =L93+N93 -> 3056.25
A94: Mid Premium | B94: Modular | C94: Wet / Exposed Area | D94: Base Storage, Wall Storage, Tall Storage, Wardrobe | E94: Carcass/shutter | F94: Core Material, Finish Material, Hinges | G94: Carcass inner 1mm - BWP / Shutter - Plywood Border with Fluted Glass , MR+ Finish , Soft Close | H94: Hettich Veyosis or Hafele Eqv , , Greenlam , Century lam , Merino, Carcass / Shutter - Century Bond or Green OptimaG with Glass | J94: =J54+50 -> 2565 | L94: =J94+K94 -> 2565 | M94: 0.25 | N94: =L94*M94 -> 641.25 | O94: =L94+N94 -> 3206.25
A95: Mid Premium | B95: Modular | C95: Wet / Exposed Area | D95: Base Storage, Wall Storage, Tall Storage, Wardrobe | E95: Carcass/shutter | F95: Core Material, Finish Material, Hinges | G95: Carcass Inner 1mm- BWP / Shutter - Black / Silver colour Aluminium Profile with Clear or Tinted Glass , MR+ Finish , Soft Close | H95: , Hettich Veyosis or Hafele Eqv, Greenlam , Century lam , Merino, Carcass -Century Bond or Green OptimaG / Shutter - CNR Aluminium Profile Shutters | J95: =J55+50 -> 2600 | L95: =J95+K95 -> 2600 | M95: 0.25 | N95: =L95*M95 -> 650 | O95: =L95+N95 -> 3250
A96: Mid Premium | B96: Modular | C96: Wet / Exposed Area | D96: Base Storage, Wall Storage, Tall Storage, Wardrobe | E96: Carcass/shutter | F96: Core Material, Finish Material, Hinges | G96: Carcass Inner 1mm - BWP / Shutter - Black / Silver colour Aluminium Profile with Fluted Glass, MR+ Finish , Soft Close | H96: , Hettich Veyosis or Hafele Eqv, Greenlam , Century lam , Merino, Carcass -Century Bond or Green OptimaG / Shutter - CNR Aluminium Profile Shutters | J96: =J59+50 -> 2700 | L96: =J96+K96 -> 2700 | M96: 0.25 | N96: =L96*M96 -> 675 | O96: =L96+N96 -> 3375
A97: Mid Premium | B97: Modular | C97: Wet / Exposed Area | D97: Base Storage, Wall Storage, Tall Storage, Wardrobe | E97: Carcass/shutter | F97: Core Material, Finish Material, Hinges | G97: Carcass Inner 1mm - BWP / Shutter - / Rose colour Aluminium Profile with Fluted Glass, MR+ Finish , Soft Close | H97: , Hettich Veyosis or Hafele Eqv, Greenlam , Century lam , Merino, Carcass -Century Bond or Green OptimaG / Shutter - CNR Aluminium Profile Shutters | J97: =J60+50 -> 2700 | L97: =J97+K97 -> 2700 | M97: 0.25 | N97: =L97*M97 -> 675 | O97: =L97+N97 -> 3375
A98: Mid Premium | B98: Modular | C98: Wet / Exposed Area | D98: Base Storage, Wall Storage, Tall Storage, Wardrobe | E98: Carcass/shutter | F98: Core Material, Finish Material, Hinges | G98: Carcass Inner 1mm- BWP / Shutter - / Rose colour Aluminium Profile with Clear or Tinted Glass, MR+ Finish , Soft Close | H98: , Hettich Veyosis or Hafele Eqv, Greenlam , Century lam , Merino, Carcass -Century Bond or Green OptimaG / Shutter - CNR Aluminium Profile Shutters | J98: =J61+50 -> 2800 | L98: =J98+K98 -> 2800 | M98: 0.25 | N98: =L98*M98 -> 700 | O98: =L98+N98 -> 3500
A99: Mid Premium | B99: Modular | C99: Wet / Exposed Area | D99: Tambour Storage | E99: Carcass | F99: Core Material, Finish Material | G99: CARCASS - BWP, MR+ Finish | H99: Carcass - Century Bond or Green OptimaG, Greenlam, Century lam , Merino | J99: =J65+50 -> 1565 | L99: =J99+K99 -> 1565 | M99: 0.25 | N99: =L99*M99 -> 391.25 | O99: =L99+N99 -> 1956.25
A100: Mid Premium | B100: Modular | C100: Wet / Exposed Area | D100: Open Unit - Inner 1mm | E100: Carcass | F100: Core Material, Finish Material | G100: CARCASS - BWP, MR+ Finish | H100: Carcass - Century Bond or Green OptimaG, Greenlam, Century lam , Merino | I100: Supply and installation of Open Unit - 1mm with BWP Carcass, MR+ laminate | J100: =J66+50 -> 1815 | L100: =J100+K100 -> 1815 | M100: 0.25 | N100: =L100*M100 -> 453.75 | O100: =L100+N100 -> 2268.75
...

Sheet Luxury
A1: Project Type | B1: Section | C1: Room Type | D1: Unit Type | E1: Panel type | F1: Category | G1: Material Type | H1: Brand | J1: Rate | K1: Hinges Blum | L1: Basic Value | M1: Mark up | N1: Margin | O1: Selling Price
A2: SMOOTH FINISH
A3: Mid Premium | B3: Modular | C3: Wet / Exposed Area | D3: Base Storage, Wall Storage, Tall Storage, Wardrobe | E3: Carcass/shutter | F3: Core Material, Finish Material, Hinges | G3: Carcass - BWP / Shutter - HDHMR Boilo, Smooth Finish, Soft Close | H3: Carcass - Century ClubPrime or Green Gold / Shutter - Action TESA, Blum , , Royal Crown , Royal Touche , | I3: Supply and installation of Base storage unit with BWP Carcass, HDHMR Boilo Shutter, Smooth Finish laminate and soft close hinges | J3: 1790 | L3: =J3+K3 -> 1790 | M3: 0.25 | N3: =L3*M3 -> 447.5 | O3: =L3+N3 -> 2237.5
I4: Supply and installation of Wall storage unit with BWP Carcass, HDHMR Boilo Shutter, Smooth finish laminate and soft close hinges
I5: Supply and installation of Tall storage unit with BWP Carcass, HDHMR Boilo Shutter, Smooth finish laminate and soft close hinges
I6: Supply and installation of Wardrobe with BWP Carcass, HDHMR Boilo Shutter, Smooth finish laminate and soft close hinges
A7: Mid Premium | B7: Modular | C7: Wet / Exposed Area | D7: Base Storage, Wall Storage, Tall Storage, Wardrobe | E7: Carcass/shutter | F7: Core Material, Finish Material, Hinges | G7: Carcass - BWP / Shutter - Plywood Border with Clear / Tinted Glass , Soft Close, Smooth Finish | H7: Blum , , Royal Crown , Royal Touche , , Carcass / Shutter - Century ClubPrime or Green Gold with Glass | J7: 2170 | L7: =J7+K7 -> 2170 | M7: 0.25 | N7: =L7*M7 -> 542.5 | O7: =L7+N7 -> 2712.5
A8: Mid Premium | B8: Modular | C8: Wet / Exposed Area | D8: Base Storage, Wall Storage, Tall Storage, Wardrobe | E8: Carcass/shutter | F8: Core Material, Finish Material, Hinges | G8: Carcass - BWP / Shutter - Plywood Border with Fluted Glass , Smooth Finish , Soft Close | H8: Blum , , Royal Crown , Royal Touche , , Carcass / Shutter - Century ClubPrime or Green Gold with Glass | J8: 2290 | L8: =J8+K8 -> 2290 | M8: 0.25 | N8: =L8*M8 -> 572.5 | O8: =L8+N8 -> 2862.5
A9: Mid Premium | B9: Modular | C9: Wet / Exposed Area | D9: Base Storage, Wall Storage, Tall Storage, Wardrobe | E9: Carcass/shutter | F9: Core Material, Finish Material, Hinges | G9: Carcass - BWP / Shutter - Black / Silver colour Aluminium Profile with Clear or Tinted Glass, Smooth Finish , Soft Close | H9: , Blum, Royal Crown , Royal Touche , , Carcass -Century ClubPrime or Green Gold / Shutter - CNR Aluminium Profile Shutters | J9: 2325 | L9: =J9+K9 -> 2325 | M9: 0.25 | N9: =L9*M9 -> 581.25 | O9: =L9+N9 -> 2906.25
A10: Mid Premium | B10: Modular | C10: Wet / Exposed Area | D10: Base Storage, Wall Storage, Tall Storage, Wardrobe | E10: Carcass/shutter | F10: Core Material, Finish Material, Hinges | G10: Carcass - BWP / Shutter - Black / Silver colour Aluminium Profile with Fluted Glass, Smooth Finish , Soft Close | H10: , Blum, Royal Crown , Royal Touche , , Carcass -Century ClubPrime or Green Gold / Shutter - CNR Aluminium Profile Shutters | J10: 2425 | L10: =J10+K10 -> 2425 | M10: 0.25 | N10: =L10*M10 -> 606.25 | O10: =L10+N10 -> 3031.25
A11: Mid Premium | B11: Modular | C11: Wet / Exposed Area | D11: Base Storage, Wall Storage, Tall Storage, Wardrobe | E11: Carcass/shutter | F11: Core Material, Finish Material, Hinges | G11: Carcass - BWP / Shutter - / Rose colour Aluminium Profile with Clear or Tinted Glass, Soft Close, Smooth Finish | H11: , Blum, Royal Crown , Royal Touche , , Carcass -Century ClubPrime or Green Gold / Shutter - CNR Aluminium Profile Shutters | J11: 2425 | L11: =J11+K11 -> 2425 | M11: 0.25 | N11: =L11*M11 -> 606.25 | O11: =L11+N11 -> 3031.25
A12: Mid Premium | B12: Modular | C12: Wet / Exposed Area | D12: Base Storage, Wall Storage, Tall Storage, Wardrobe | E12: Carcass/shutter | F12: Core Material, Finish Material, Hinges | G12: Carcass - BWP / Shutter - / Rose colour Aluminium Profile with Fluted Glass, Smooth Finish , Soft Close | H12: , Blum, Royal Crown , Royal Touche , , Carcass -Century ClubPrime or Green Gold / Shutter - CNR Aluminium Profile Shutters | J12: 2525 | L12: =J12+K12 -> 2525 | M12: 0.25 | N12: =L12*M12 -> 631.25 | O12: =L12+N12 -> 3156.25
A13: Mid Premium | B13: Modular | C13: Wet / Exposed Area | D13: Base Storage, Wall Storage, Tall Storage, Wardrobe | E13: Carcass/shutter | F13: Core Material, Finish Material, Hinges | G13: Carcass Inner 1mm- BWP / Shutter - Plywood Border with Clear / Tinted Glass , Smooth Finish , Soft Close | H13: Blum , , Royal Crown , Royal Touche , , Carcass / Shutter - Century ClubPrime or Green Gold with Glass | J13: 2420 | L13: =J13+K13 -> 2420 | M13: 0.25 | N13: =L13*M13 -> 605 | O13: =L13+N13 -> 3025
A14: Mid Premium | B14: Modular | C14: Wet / Exposed Area | D14: Base Storage, Wall Storage, Tall Storage, Wardrobe | E14: Carcass/shutter | F14: Core Material, Finish Material, Hinges | G14: Carcass inner 1mm - BWP / Shutter - Plywood Border with Fluted Glass , Smooth Finish , Soft Close | H14: Blum , , Royal Crown , Royal Touche , , Carcass / Shutter - Century ClubPrime or Green Gold with Glass | J14: 2540 | L14: =J14+K14 -> 2540 | M14: 0.25 | N14: =L14*M14 -> 635 | O14: =L14+N14 -> 3175
A15: Mid Premium | B15: Modular | C15: Wet / Exposed Area | D15: Base Storage, Wall Storage, Tall Storage, Wardrobe | E15: Carcass/shutter | F15: Core Material, Finish Material, Hinges | G15: Carcass Inner 1mm- BWP / Shutter - Black / Silver colour Aluminium Profile with Clear or Tinted Glass , Smooth Finish , Soft Close | H15: , Blum, Royal Crown , Royal Touche , , Carcass -Century ClubPrime or Green Gold / Shutter - CNR Aluminium Profile Shutters | J15: 2575 | L15: =J15+K15 -> 2575 | M15: 0.25 | N15: =L15*M15 -> 643.75 | O15: =L15+N15 -> 3218.75
A16: Mid Premium | B16: Modular | C16: Wet / Exposed Area | D16: Base Storage, Wall Storage, Tall Storage, Wardrobe | E16: Carcass/shutter | F16: Core Material, Finish Material, Hinges | G16: Carcass Inner 1mm - BWP / Shutter - Black / Silver colour Aluminium Profile with Fluted Glass, Smooth Finish , Soft Close | H16: , Blum, Royal Crown , Royal Touche , , Carcass -Century ClubPrime or Green Gold / Shutter - CNR Aluminium Profile Shutters | J16: 2675 | L16: =J16+K16 -> 2675 | M16: 0.25 | N16: =L16*M16 -> 668.75 | O16: =L16+N16 -> 3343.75
A17: Mid Premium | B17: Modular | C17: Wet / Exposed Area | D17: Base Storage, Wall Storage, Tall Storage, Wardrobe | E17: Carcass/shutter | F17: Core Material, Finish Material, Hinges | G17: Carcass Inner 1mm - BWP / Shutter - / Rose colour Aluminium Profile with Fluted Glass, Smooth Finish , Soft Close | H17: , Blum, Royal Crown , Royal Touche , , Carcass -Century ClubPrime or Green Gold / Shutter - CNR Aluminium Profile Shutters | I17: Supply and installation of Base storage - Inner 1mm unit with BWP Carcass, Black/Silver Aluminium Profile with Clear/Tinted Glass Shutter, Smooth laminate and soft close hinges | J17: 2675 | L17: =J17+K17 -> 2675 | M17: 0.25 | N17: =L17*M17 -> 668.75 | O17: =L17+N17 -> 3343.75
I18: Supply and installation of Wall storage - Inner 1mm unit with BWP Carcass, Black/Silver Aluminium Profile with Clear/Tinted Glass Shutter, Smooth laminate and soft close hinges
I19: Supply and installation of Tall storage - Inner 1mm unit with BWP Carcass, Black/Silver Aluminium Profile with Clear/Tinted Glass Shutter, Smooth laminate and soft close hinges
I20: Supply and installation of Wardrobe - Inner 1mm unit with BWP Carcass, Black/Silver Aluminium Profile with Clear/Tinted Glass Shutter, Smooth laminate and soft close hinges
A21: Mid Premium | B21: Modular | C21: Wet / Exposed Area | D21: Base Storage, Wall Storage, Tall Storage, Wardrobe | E21: Carcass/shutter | F21: Core Material, Finish Material, Hinges | G21: Carcass Inner 1mm- BWP / Shutter - / Rose colour Aluminium Profile with Clear or Tinted Glass, Smooth Finish , Soft Close | H21: , Blum, Royal Crown , Royal Touche , , Carcass -Century ClubPrime or Green Gold / Shutter - CNR Aluminium Profile Shutters | J21: 2775 | L21: =J21+K21 -> 2775 | M21: 0.25 | N21: =L21*M21 -> 693.75 | O21: =L21+N21 -> 3468.75
A22: Mid Premium | B22: Modular | C22: Wet / Exposed Area | D22: Curved Shape Base Storage unit | E22: Carcass/shutter | F22: Core Material, Finish Material, Hinges | G22: Carcass - BWP / Shutter - HDHMR Boilo, Smooth Finish , Soft Close | H22: Carcass - Century ClubPrime or Green Gold / Shutter - Action TESA, Blum , , Royal Crown , Royal Touche , | J22: 2140 | L22: =J22+K22 -> 2140 | M22: 0.25 | N22: =L22*M22 -> 535 | O22: =L22+N22 -> 2675
A23: Mid Premium | B23: Modular | C23: Wet / Exposed Area | D23: Curved Shape Drawer Storage unit | E23: Carcass/shutter | F23: Core Material, Finish Material | G23: Carcass - BWP / Shutter - HDHMR Boilo, Smooth Finish | H23: Carcass - Century ClubPrime or Green Gold / Shutter - Action TESA, Royal Touche , , Royal Crown | J23: 2140 | L23: =J23+K23 -> 2140 | M23: 0.25 | N23: =L23*M23 -> 535 | O23: =L23+N23 -> 2675
A24: Mid Premium | B24: Modular | C24: Wet / Exposed Area | D24: Tambour Storage | E24: Carcass | F24: Core Material, Finish Material | G24: CARCASS - BWP, Smooth Finish | H24: Carcass - Century ClubPrime or Green Gold , Royal Crown, Royal Touche , | J24: 1540 | L24: =J24+K24 -> 1540 | M24: 0.25 | N24: =L24*M24 -> 385 | O24: =L24+N24 -> 1925
A25: Mid Premium | B25: Modular | C25: Wet / Exposed Area | D25: Open Unit - Inner 1mm | E25: Carcass | F25: Core Material, Finish Material | G25: CARCASS - BWP, Smooth Finish | H25: Carcass - Century ClubPrime or Green Gold , Royal Crown, Royal Touche , | I25: Supply and installation of Open unit - Inner 1mm with BWP ply frame and Smooth finish laminate | J25: 1790 | L25: =J25+K25 -> 1790 | M25: 0.25 | N25: =L25*M25 -> 447.5 | O25: =L25+N25 -> 2237.5
A26: Mid Premium | B26: Modular | C26: Wet / Exposed Area | D26: Loft | E26: Frame and Shutter | F26: Core Material, Finish Material, Hinges | G26: Smooth Finish, Soft Close, Frame - BWP / Shutter - HDHMR Boilo | H26: Blum , , Royal Crown , Royal Touche , , Frame- Century ClubPrime or Green Gold / Shutter - Action TESA, | I26: Supply and installation of Loft Frame and Shutter unit with BWP Frame, HDHMR Boilo Shutter, Smooth laminate and Soft Close hinges | J26: 1033 | L26: =J26+K26 -> 1033 | M26: 0.25 | N26: =L26*M26 -> 258.25 | O26: =L26+N26 -> 1291.25
A27: Mid Premium | B27: Modular | C27: Wet / Exposed Area | D27: Ledge | E27: Ledge -25mm | F27: Finish Material, Core Material | G27: Smooth Finish , CARCASS - BWP | H27: Ledge - Century ClubPrime or Green Gold , Royal Crown , Royal Touche , | I27: Supply and installation of Ledge with 25mm Ledge BWP and Smooth Laminate | J27: 950 | L27: =J27+K27 -> 950 | M27: 0.25 | N27: =L27*M27 -> 237.5 | O27: =L27+N27 -> 1187.5
A28: Mid Premium | B28: Modular | C28: Wet / Exposed Area | D28: Ledge | E28: Ledge -36mm | F28: Finish Material, Core Material | G28: Smooth Finish , CARCASS - BWP | H28: Ledge - Century ClubPrime or Green Gold , Royal Crown , Royal Touche , | I28: Supply and installation of Ledge with 36mm Ledge BWP and Smooth Laminate | J28: 950 | L28: =J28+K28 -> 950 | M28: 0.25 | N28: =L28*M28 -> 237.5 | O28: =L28+N28 -> 1187.5
A29: Mid Premium | B29: Modular | C29: Wet / Exposed Area | D29: Ledge | E29: Ledge -50mm | F29: Finish Material, Core Material | G29: Smooth Finish , CARCASS - BWP | H29: Ledge - Century ClubPrime or Green Gold , Royal Crown , Royal Touche , | I29: Supply and installation of Ledge with 50mm Ledge BWP and Smooth Laminate | J29: 1100 | L29: =J29+K29 -> 1100 | M29: 0.25 | N29: =L29*M29 -> 275 | O29: =L29+N29 -> 1375
A30: Mid Premium | B30: Modular | C30: Wet / Exposed Area | D30: Partition | E30: Partition -75mm | F30: Finish Material, Core Material | G30: Smooth Finish , CARCASS - BWP | H30: Century ClubPrime or Green Gold , Royal Crown , Royal Touche , | I30: Supply and installation of Partition - 75mm with BWP Ply Frame, Smooth laminate | J30: 1750 | L30: =J30+K30 -> 1750 | M30: 0.25 | N30: =L30*M30 -> 437.5 | O30: =L30+N30 -> 2187.5
A31: Mid Premium | B31: Modular | C31: Wet / Exposed Area | D31: Panel | E31: Curved Shape Panel | F31: Finish Material, Core Material | G31: Smooth Finish , CARCASS - BWP | H31: Century ClubPrime or Green Gold , Royal Touche , Royal Crown , | J31: 1083 | L31: =J31+K31 -> 1083 | M31: 0.25 | N31: =L31*M31 -> 270.75 | O31: =L31+N31 -> 1353.75
A32: Mid Premium | B32: Modular | C32: Wet / Exposed Area | D32: Panel | E32: Wallpanel , pelmet , Ceiling Panel , Base panel / Side panel | F32: Finish Material, Core Material | G32: Smooth Finish , CARCASS - BWP | H32: Century ClubPrime or Green Gold , Royal Touche , Royal Crown , | I32: Supply and installation of Wall Panel with BWP Ply Frame, Smooth Finish laminate | J32: 1125 | L32: =J32+K32 -> 1125 | M32: 0.25 | N32: =L32*M32 -> 281.25 | O32: =L32+N32 -> 1406.25
I33: Supply and installation of Pelmet Panel with BWP Ply Frame, Smooth Finish laminate
I34: Supply and installation of Jam Panel with BWP Ply Frame, Smooth Finish laminate
I35: Supply and installation of Ceiling Panel with BWP Ply Frame, Smooth Finish laminate
I36: Supply and installation of Base Panel with BWP Ply Frame, Smooth Finish laminate
L37: =J37+K37 -> 0 | M37: 0.25 | N37: =L37*M37 -> 0 | O37: =L37+N37 -> 0
A38: GLOSSY FINISH | L38: =J38+K38 -> 0 | M38: 0.25 | N38: =L38*M38 -> 0 | O38: =L38+N38 -> 0
A39: Mid Premium | B39: Section | C39: Room Type | D39: Unit Type | E39: Panel type | F39: Category | G39: Material Type | H39: Brand | J39: Rate | L39: =J39+K39 -> #VALUE! | M39: 0.25 | N39: =L39*M39 -> #VALUE! | O39: =L39+N39 -> #VALUE!
A40: Mid Premium | B40: Modular | C40: Wet / Exposed Area | D40: Base Storage, Wall Storage, Tall Storage, Wardrobe | E40: Carcass/shutter | F40: Core Material, Finish Material, Hinges | G40: Carcass - BWP / Shutter - HDHMR Boilo, Glossy Finish, Soft Close | H40: Carcass - Century ClubPrime or Green Gold / Shutter - Action TESA, Blum , , Royal Crown , Royal Touche , | J40: 1840 | L40: =J40+K40 -> 1840 | M40: 0.25 | N40: =L40*M40 -> 460 | O40: =L40+N40 -> 2300
A41: Mid Premium | B41: Modular | C41: Wet / Exposed Area | D41: Base Storage, Wall Storage, Tall Storage, Wardrobe | E41: Carcass/shutter | F41: Core Material, Finish Material, Hinges | G41: Carcass - BWP / Shutter - Plywood Border with Clear / Tinted Glass , Soft Close, Glossy Finish | H41: Blum , , Royal Crown , Royal Touche , , Carcass / Shutter - Century ClubPrime or Green Gold with Glass | J41: 2220 | L41: =J41+K41 -> 2220 | M41: 0.25 | N41: =L41*M41 -> 555 | O41: =L41+N41 -> 2775
A42: Mid Premium | B42: Modular | C42: Wet / Exposed Area | D42: Base Storage, Wall Storage, Tall Storage, Wardrobe | E42: Carcass/shutter | F42: Core Material, Finish Material, Hinges | G42: Carcass - BWP / Shutter - Plywood Border with Fluted Glass , Glossy Finish , Soft Close | H42: Blum , , Royal Crown , Royal Touche , , Carcass / Shutter - Century ClubPrime or Green Gold with Glass | J42: 2340 | L42: =J42+K42 -> 2340 | M42: 0.25 | N42: =L42*M42 -> 585 | O42: =L42+N42 -> 2925
A43: Mid Premium | B43: Modular | C43: Wet / Exposed Area | D43: Base Storage, Wall Storage, Tall Storage, Wardrobe | E43: Carcass/shutter | F43: Core Material, Finish Material, Hinges | G43: Carcass - BWP / Shutter - Black / Silver colour Aluminium Profile with Clear or Tinted Glass, Glossy Finish , Soft Close | H43: , Blum, Royal Crown , Royal Touche , , Carcass -Century ClubPrime or Green Gold / Shutter - CNR Aluminium Profile Shutters | J43: 2375 | L43: =J43+K43 -> 2375 | M43: 0.25 | N43: =L43*M43 -> 593.75 | O43: =L43+N43 -> 2968.75
A44: Mid Premium | B44: Modular | C44: Wet / Exposed Area | D44: Base Storage, Wall Storage, Tall Storage, Wardrobe | E44: Carcass/shutter | F44: Core Material, Finish Material, Hinges | G44: Carcass - BWP / Shutter - Black / Silver colour Aluminium Profile with Fluted Glass, Glossy Finish , Soft Close | H44: , Blum, Royal Crown , Royal Touche , , Carcass -Century ClubPrime or Green Gold / Shutter - CNR Aluminium Profile Shutters | J44: 2475 | L44: =J44+K44 -> 2475 | M44: 0.25 | N44: =L44*M44 -> 618.75 | O44: =L44+N44 -> 3093.75
A45: Mid Premium | B45: Modular | C45: Wet / Exposed Area | D45: Base Storage, Wall Storage, Tall Storage, Wardrobe | E45: Carcass/shutter | F45: Core Material, Finish Material, Hinges | G45: Carcass - BWP / Shutter - / Rose colour Aluminium Profile with Clear or Tinted Glass, Soft Close, Glossy Finish | H45: , Blum, Royal Crown , Royal Touche , , Carcass -Century ClubPrime or Green Gold / Shutter - CNR Aluminium Profile Shutters | J45: 2475 | L45: =J45+K45 -> 2475 | M45: 0.25 | N45: =L45*M45 -> 618.75 | O45: =L45+N45 -> 3093.75
A46: Mid Premium | B46: Modular | C46: Wet / Exposed Area | D46: Base Storage, Wall Storage, Tall Storage, Wardrobe | E46: Carcass/shutter | F46: Core Material, Finish Material, Hinges | G46: Carcass - BWP / Shutter - / Rose colour Aluminium Profile with Fluted Glass, Glossy Finish , Soft Close | H46: , Blum, Royal Crown , Royal Touche , , Carcass -Century ClubPrime or Green Gold / Shutter - CNR Aluminium Profile Shutters | J46: 2575 | L46: =J46+K46 -> 2575 | M46: 0.25 | N46: =L46*M46 -> 643.75 | O46: =L46+N46 -> 3218.75
A47: Mid Premium | B47: Modular | C47: Wet / Exposed Area | D47: Base Storage, Wall Storage, Tall Storage, Wardrobe | E47: Carcass/shutter | F47: Core Material, Finish Material, Hinges | G47: Carcass Inner 1mm- BWP / Shutter - Plywood Border with Clear / Tinted Glass , Glossy Finish , Soft Close | H47: Blum , , Royal Crown , Royal Touche , , Carcass / Shutter - Century ClubPrime or Green Gold with Glass | J47: 2470 | L47: =J47+K47 -> 2470 | M47: 0.25 | N47: =L47*M47 -> 617.5 | O47: =L47+N47 -> 3087.5
A48: Mid Premium | B48: Modular | C48: Wet / Exposed Area | D48: Base Storage, Wall Storage, Tall Storage, Wardrobe | E48: Carcass/shutter | F48: Core Material, Finish Material, Hinges | G48: Carcass inner 1mm - BWP / Shutter - Plywood Border with Fluted Glass , Glossy Finish , Soft Close | H48: Blum , , Royal Crown , Royal Touche , , Carcass / Shutter - Century ClubPrime or Green Gold with Glass | J48: 2590 | L48: =J48+K48 -> 2590 | M48: 0.25 | N48: =L48*M48 -> 647.5 | O48: =L48+N48 -> 3237.5
A49: Mid Premium | B49: Modular | C49: Wet / Exposed Area | D49: Base Storage, Wall Storage, Tall Storage, Wardrobe | E49: Carcass/shutter | F49: Core Material, Finish Material, Hinges | G49: Carcass Inner 1mm- BWP / Shutter - Black / Silver colour Aluminium Profile with Clear or Tinted Glass , Glossy Finish , Soft Close | H49: , Blum, Royal Crown , Royal Touche , , Carcass -Century ClubPrime or Green Gold / Shutter - CNR Aluminium Profile Shutters | J49: 2625 | L49: =J49+K49 -> 2625 | M49: 0.25 | N49: =L49*M49 -> 656.25 | O49: =L49+N49 -> 3281.25
A50: Mid Premium | B50: Modular | C50: Wet / Exposed Area | D50: Base Storage, Wall Storage, Tall Storage, Wardrobe | E50: Carcass/shutter | F50: Core Material, Finish Material, Hinges | G50: Carcass Inner 1mm - BWP / Shutter - Black / Silver colour Aluminium Profile with Fluted Glass, Glossy Finish , Soft Close | H50: , Blum, Royal Crown , Royal Touche , , Carcass -Century ClubPrime or Green Gold / Shutter - CNR Aluminium Profile Shutters | J50: 2725 | L50: =J50+K50 -> 2725 | M50: 0.25 | N50: =L50*M50 -> 681.25 | O50: =L50+N50 -> 3406.25
A51: Mid Premium | B51: Modular | C51: Wet / Exposed Area | D51: Base Storage, Wall Storage, Tall Storage, Wardrobe | E51: Carcass/shutter | F51: Core Material, Finish Material, Hinges | G51: Carcass Inner 1mm - BWP / Shutter - / Rose colour Aluminium Profile with Fluted Glass, Glossy Finish , Soft Close | H51: , Blum, Royal Crown , Royal Touche , , Carcass -Century ClubPrime or Green Gold / Shutter - CNR Aluminium Profile Shutters | J51: 2725 | L51: =J51+K51 -> 2725 | M51: 0.25 | N51: =L51*M51 -> 681.25 | O51: =L51+N51 -> 3406.25
... A56: Mid Premium | B56: Modular | C56: Wet / Exposed Area | D56: Open Unit - Inner 1mm | E56: Carcass | F56: Core Material, Finish Material | G56: CARCASS - BWP, Glossy Finish | H56: Carcass - Century ClubPrime or Green Gold , Royal Crown, Royal Touche , | J56: 1840 | L56: =J56+K56 -> 1840 | M56: 0.25 | N56: =L56*M56 -> 460 | O56: =L56+N56 -> 2300
A57: Mid Premium | B57: Modular | C57: Wet / Exposed Area | D57: Loft | E57: Frame and Shutter | F57: Core Material, Finish Material, Hinges | G57: Glossy Finish, Soft Close, Frame - BWP / Shutter - HDHMR Boilo | H57: Blum , , Royal Crown , Royal Touche , , Frame- Century ClubPrime or Green Gold / Shutter - Action TESA, | I57: Supply and installation of Loft Frame and Shutter unit with BWP Frame, HDHMR Boilo Shutter, Glossy finish laminate and Soft Close hinges | J57: 1083 | L57: =J57+K57 -> 1083 | M57: 0.25 | N57: =L57*M57 -> 270.75 | O57: =L57+N57 -> 1353.75
A58: Mid Premium | B58: Modular | C58: Wet / Exposed Area | D58: Ledge | E58: Ledge -25mm | F58: Finish Material, Core Material | G58: Glossy Finish , CARCASS - BWP | H58: Ledge - Century ClubPrime or Green Gold , Royal Crown , Royal Touche , | I58: Supply and installation of Ledge with 25mm Ledge BWP and Glossy Laminate | J58: 1000 | L58: =J58+K58 -> 1000 | M58: 0.25 | N58: =L58*M58 -> 250 | O58: =L58+N58 -> 1250
A59: Mid Premium | B59: Modular | C59: Wet / Exposed Area | D59: Ledge | E59: Ledge -36mm | F59: Finish Material, Core Material | G59: Glossy Finish , CARCASS - BWP | H59: Ledge - Century ClubPrime or Green Gold , Royal Crown , Royal Touche , | I59: Supply and installation of Ledge with 36mm Ledge BWP and Glossy Laminate | J59: 1000 | L59: =J59+K59 -> 1000 | M59: 0.25 | N59: =L59*M59 -> 250 | O59: =L59+N59 -> 1250
A60: Mid Premium | B60: Modular | C60: Wet / Exposed Area | D60: Ledge | E60: Ledge -50mm | F60: Finish Material, Core Material | G60: Glossy Finish , CARCASS - BWP | H60: Ledge - Century ClubPrime or Green Gold , Royal Crown , Royal Touche , | I60: Supply and installation of Ledge with 50mm Ledge BWP and Glossy Laminate | J60: 1150 | L60: =J60+K60 -> 1150 | M60: 0.25 | N60: =L60*M60 -> 287.5 | O60: =L60+N60 -> 1437.5
A61: Mid Premium | B61: Modular | C61: Wet / Exposed Area | D61: Partition | E61: Partition -75mm | F61: Finish Material, Core Material | G61: Glossy Finish , CARCASS - BWP | H61: Century ClubPrime or Green Gold , Royal Crown , Royal Touche , | I61: Supply and installation of Partition - 75mm with BWP Ply Frame, Glossy laminate | J61: 1800 | L61: =J61+K61 -> 1800 | M61: 0.25 | N61: =L61*M61 -> 450 | O61: =L61+N61 -> 2250
A62: Mid Premium | B62: Modular | C62: Wet / Exposed Area | D62: Panel | E62: Curved Shape Panel | F62: Finish Material, Core Material | G62: Glossy Finish , CARCASS - BWP | H62: Century ClubPrime or Green Gold , Royal Touche , Royal Crown , | J62: 1133 | L62: =J62+K62 -> 1133 | M62: 0.25 | N62: =L62*M62 -> 283.25 | O62: =L62+N62 -> 1416.25
A63: Mid Premium | B63: Modular | C63: Wet / Exposed Area | D63: Panel | E63: Wallpanel , pelmet , Ceiling Panel , Base panel / Side panel | F63: Finish Material, Core Material | G63: Glossy Finish , CARCASS - BWP | H63: Century ClubPrime or Green Gold , Royal Touche , Royal Crown , | I63: Supply and installation of Wall Panel with BWP Ply Frame, Glossy Finish laminate | J63: 1175 | L63: =J63+K63 -> 1175 | M63: 0.25 | N63: =L63*M63 -> 293.75 | O63: =L63+N63 -> 1468.75
I64: Supply and installation of Pelmet Panel with BWP Ply Frame, Glossy Finish laminate
I65: Supply and installation of Jam Panel with BWP Ply Frame, Glossy Finish laminate
I66: Supply and installation of Ceiling Panel with BWP Ply Frame, Glossy Finish laminate
I67: Supply and installation of Base Panel with BWP Ply Frame, Glossy Finish laminate
A68: MR+ FINISH
A69: Mid Premium | B69: Section | C69: Room Type | D69: Unit Type | E69: Panel type | F69: Category | G69: Material Type | H69: Brand
A70: Mid Premium | B70: Modular | C70: Wet / Exposed Area | D70: Base Storage, Wall Storage, Tall Storage, Wardrobe | E70: Carcass/shutter | F70: Core Material, Finish Material, Hinges | G70: Carcass - BWP / Shutter - HDHMR Boilo, MR+ Finish, Soft Close | H70: Carcass - Century ClubPrime or Green Gold / Shutter - Action TESA, Blum , , Royal Crown , Royal Touche , | I70: Supply and installation of Base storage unit with BWP Carcass, HDHMR Boilo Shutter, MR+ finish laminate and soft close hinges | J70: 1890 | L70: =J70+K70 -> 1890 | M70: 0.25 | N70: =L70*M70 -> 472.5 | O70: =L70+N70 -> 2362.5
I71: Supply and installation of Wall storage unit with BWP Carcass, HDHMR Boilo Shutter, MR+ finish laminate and soft close hinges
I72: Supply and installation of Tall storage unit with BWP Carcass, HDHMR Boilo Shutter, MR+ finish laminate and soft close hinges
I73: Supply and installation of Wardrobe with BWP Carcass, HDHMR Boilo Shutter, MR+ finish laminate and soft close hinges
A74: Mid Premium | B74: Modular | C74: Wet / Exposed Area | D74: Base Storage, Wall Storage, Tall Storage, Wardrobe | E74: Carcass/shutter | F74: Core Material, Finish Material, Hinges | G74: Carcass - BWP / Shutter - Plywood Border with Clear / Tinted Glass , Soft Close, MR+ Finish | H74: Blum , , Royal Crown , Royal Touche , , Carcass / Shutter - Century ClubPrime or Green Gold with Glass | J74: 2270 | L74: =J74+K74 -> 2270 | M74: 0.25 | N74: =L74*M74 -> 567.5 | O74: =L74+N74 -> 2837.5
A75: Mid Premium | B75: Modular | C75: Wet / Exposed Area | D75: Base Storage, Wall Storage, Tall Storage, Wardrobe | E75: Carcass/shutter | F75: Core Material, Finish Material, Hinges | G75: Carcass - BWP / Shutter - Plywood Border with Fluted Glass , MR+ Finish , Soft Close | H75: Blum , , Royal Crown , Royal Touche , , Carcass / Shutter - Century ClubPrime or Green Gold with Glass | J75: 2390 | L75: =J75+K75 -> 2390 | M75: 0.25 | N75: =L75*M75 -> 597.5 | O75: =L75+N75 -> 2987.5
A76: Mid Premium | B76: Modular | C76: Wet / Exposed Area | D76: Base Storage, Wall Storage, Tall Storage, Wardrobe | E76: Carcass/shutter | F76: Core Material, Finish Material, Hinges | G76: Carcass - BWP / Shutter - Black / Silver colour Aluminium Profile with Clear or Tinted Glass, MR+ Finish , Soft Close | H76: , Blum, Royal Crown , Royal Touche , , Carcass -Century ClubPrime or Green Gold / Shutter - CNR Aluminium Profile Shutters | I76: Supply and installation of Base storage unit with BWP Carcass, Black/Silver Aluminium Profile with Clear/Tinted Glass Shutter, MR+ laminate and soft close hinges | J76: 2425 | L76: =J76+K76 -> 2425 | M76: 0.25 | N76: =L76*M76 -> 606.25 | O76: =L76+N76 -> 3031.25
I77: Supply and installation of Wall storage unit with BWP Carcass, Black/Silver Aluminium Profile with Clear/Tinted Glass Shutter, MR+ laminate and soft close hinges
I78: Supply and installation of Tall storage unit with BWP Carcass, Black/Silver Aluminium Profile with Clear/Tinted Glass Shutter, MR+ laminate and soft close hinges
I79: Supply and installation of Wardrobe with BWP Carcass, Black/Silver Aluminium Profile with Clear/Tinted Glass Shutter, MR+ laminate and soft close hinges
A80: Mid Premium | B80: Modular | C80: Wet / Exposed Area | D80: Base Storage, Wall Storage, Tall Storage, Wardrobe | E80: Carcass/shutter | F80: Core Material, Finish Material, Hinges | G80: Carcass - BWP / Shutter - Black / Silver colour Aluminium Profile with Fluted Glass, MR+ Finish , Soft Close | H80: , Blum, Royal Crown , Royal Touche , , Carcass -Century ClubPrime or Green Gold / Shutter - CNR Aluminium Profile Shutters | J80: 2525 | L80: =J80+K80 -> 2525 | M80: 0.25 | N80: =L80*M80 -> 631.25 | O80: =L80+N80 -> 3156.25
A81: Mid Premium | B81: Modular | C81: Wet / Exposed Area | D81: Base Storage, Wall Storage, Tall Storage, Wardrobe | E81: Carcass/shutter | F81: Core Material, Finish Material, Hinges | G81: Carcass - BWP / Shutter - / Rose colour Aluminium Profile with Clear or Tinted Glass, Soft Close, MR+ Finish | H81: , Blum, Royal Crown , Royal Touche , , Carcass -Century ClubPrime or Green Gold / Shutter - CNR Aluminium Profile Shutters | J81: 2525 | L81: =J81+K81 -> 2525 | M81: 0.25 | N81: =L81*M81 -> 631.25 | O81: =L81+N81 -> 3156.25
A82: Mid Premium | B82: Modular | C82: Wet / Exposed Area | D82: Base Storage, Wall Storage, Tall Storage, Wardrobe | E82: Carcass/shutter | F82: Core Material, Finish Material, Hinges | G82: Carcass - BWP / Shutter - / Rose colour Aluminium Profile with Fluted Glass, MR+ Finish , Soft Close | H82: , Blum, Royal Crown , Royal Touche , , Carcass -Century ClubPrime or Green Gold / Shutter - CNR Aluminium Profile Shutters | J82: 2625 | L82: =J82+K82 -> 2625 | M82: 0.25 | N82: =L82*M82 -> 656.25 | O82: =L82+N82 -> 3281.25
A83: Mid Premium | B83: Modular | C83: Wet / Exposed Area | D83: Base Storage, Wall Storage, Tall Storage, Wardrobe | E83: Carcass/shutter | F83: Core Material, Finish Material, Hinges | G83: Carcass Inner 1mm- BWP / Shutter - Plywood Border with Clear / Tinted Glass , MR+ Finish , Soft Close | H83: Blum , , Royal Crown , Royal Touche , , Carcass / Shutter - Century ClubPrime or Green Gold with Glass | J83: 2520 | L83: =J83+K83 -> 2520 | M83: 0.25 | N83: =L83*M83 -> 630 | O83: =L83+N83 -> 3150
A84: Mid Premium | B84: Modular | C84: Wet / Exposed Area | D84: Base Storage, Wall Storage, Tall Storage, Wardrobe | E84: Carcass/shutter | F84: Core Material, Finish Material, Hinges | G84: Carcass inner 1mm - BWP / Shutter - Plywood Border with Fluted Glass , MR+ Finish , Soft Close | H84: Blum , , Royal Crown , Royal Touche , , Carcass / Shutter - Century ClubPrime or Green Gold with Glass | J84: 2640 | L84: =J84+K84 -> 2640 | M84: 0.25 | N84: =L84*M84 -> 660 | O84: =L84+N84 -> 3300
A85: Mid Premium | B85: Modular | C85: Wet / Exposed Area | D85: Base Storage, Wall Storage, Tall Storage, Wardrobe | E85: Carcass/shutter | F85: Core Material, Finish Material, Hinges | G85: Carcass Inner 1mm- BWP / Shutter - Black / Silver colour Aluminium Profile with Clear or Tinted Glass , MR+ Finish , Soft Close | H85: , Blum, Royal Crown , Royal Touche , , Carcass -Century ClubPrime or Green Gold / Shutter - CNR Aluminium Profile Shutters | J85: 2675 | L85: =J85+K85 -> 2675 | M85: 0.25 | N85: =L85*M85 -> 668.75 | O85: =L85+N85 -> 3343.75
A86: Mid Premium | B86: Modular | C86: Wet / Exposed Area | D86: Base Storage, Wall Storage, Tall Storage, Wardrobe | E86: Carcass/shutter | F86: Core Material, Finish Material, Hinges | G86: Carcass Inner 1mm - BWP / Shutter - Black / Silver colour Aluminium Profile with Fluted Glass, MR+ Finish , Soft Close | H86: , Blum, Royal Crown , Royal Touche , , Carcass -Century ClubPrime or Green Gold / Shutter - CNR Aluminium Profile Shutters | J86: 2775 | L86: =J86+K86 -> 2775 | M86: 0.25 | N86: =L86*M86 -> 693.75 | O86: =L86+N86 -> 3468.75
A87: Mid Premium | B87: Modular | C87: Wet / Exposed Area | D87: Base Storage, Wall Storage, Tall Storage, Wardrobe | E87: Carcass/shutter | F87: Core Material, Finish Material, Hinges | G87: Carcass Inner 1mm - BWP / Shutter - / Rose colour Aluminium Profile with Fluted Glass, MR+ Finish , Soft Close | H87: , Blum, Royal Crown , Royal Touche , , Carcass -Century ClubPrime or Green Gold / Shutter - CNR Aluminium Profile Shutters | J87: 2775 | L87: =J87+K87 -> 2775 | M87: 0.25 | N87: =L87*M87 -> 693.75 | O87: =L87+N87 -> 3468.75
A88: Mid Premium | B88: Modular | C88: Wet / Exposed Area | D88: Base Storage, Wall Storage, Tall Storage, Wardrobe | E88: Carcass/shutter | F88: Core Material, Finish Material, Hinges | G88: Carcass Inner 1mm- BWP / Shutter - / Rose colour Aluminium Profile with Clear or Tinted Glass, MR+ Finish , Soft Close | H88: , Blum, Royal Crown , Royal Touche , , Carcass -Century ClubPrime or Green Gold / Shutter - CNR Aluminium Profile Shutters | J88: 2875 | L88: =J88+K88 -> 2875 | M88: 0.25 | N88: =L88*M88 -> 718.75 | O88: =L88+N88 -> 3593.75
A89: Mid Premium | B89: Modular | C89: Wet / Exposed Area | D89: Tambour Storage | E89: Carcass | F89: Core Material, Finish Material | G89: CARCASS - BWP, MR+ Finish | H89: Carcass - Century ClubPrime or Green Gold , Royal Crown, Royal Touche , | J89: 1640 | L89: =J89+K89 -> 1640 | M89: 0.25 | N89: =L89*M89 -> 410 | O89: =L89+N89 -> 2050
A90: Mid Premium | B90: Modular | C90: Wet / Exposed Area | D90: Open Unit - Inner 1mm | E90: Carcass | F90: Core Material, Finish Material | G90: CARCASS - BWP, MR+ Finish | H90: Carcass - Century ClubPrime or Green Gold , Royal Crown, Royal Touche , | J90: 1890 | L90: =J90+K90 -> 1890 | M90: 0.25 | N90: =L90*M90 -> 472.5 | O90: =L90+N90 -> 2362.5
A91: Mid Premium | B91: Modular | C91: Wet / Exposed Area | D91: Loft | E91: Frame and Shutter | F91: Core Material, Finish Material, Hinges | G91: MR+ Finish, Soft Close, Frame - BWP / Shutter - HDHMR Boilo | H91: Blum , , Royal Crown , Royal Touche , , Frame- Century ClubPrime or Green Gold / Shutter - Action TESA, | I91: Supply and installation of Loft Frame and Shutter unit with BWP Frame, HDHMR Boilo Shutter, MR+ laminate and Soft Close hinges | J91: 1133 | L91: =J91+K91 -> 1133 | M91: 0.25 | N91: =L91*M91 -> 283.25 | O91: =L91+N91 -> 1416.25
A92: Mid Premium | B92: Modular | C92: Wet / Exposed Area | D92: Ledge | E92: Ledge -25mm | F92: Finish Material, Core Material | G92: MR+ Finish , CARCASS - BWP | H92: Ledge - Century ClubPrime or Green Gold , Royal Crown , Royal Touche , | I92: Supply and installation of Ledge with 25mm Ledge BWP and MR+ Laminate | J92: 1050 | L92: =J92+K92 -> 1050 | M92: 0.25 | N92: =L92*M92 -> 262.5 | O92: =L92+N92 -> 1312.5
A93: Mid Premium | B93: Modular | C93: Wet / Exposed Area | D93: Ledge | E93: Ledge -36mm | F93: Finish Material, Core Material | G93: MR+ Finish , CARCASS - BWP | H93: Ledge - Century ClubPrime or Green Gold , Royal Crown , Royal Touche , | I93: Supply and installation of Ledge with 36mm Ledge BWP and MR+ Laminate | J93: 1050 | L93: =J93+K93 -> 1050 | M93: 0.25 | N93: =L93*M93 -> 262.5 | O93: =L93+N93 -> 1312.5
A94: Mid Premium | B94: Modular | C94: Wet / Exposed Area | D94: Ledge | E94: Ledge -50mm | F94: Finish Material, Core Material | G94: MR+ Finish , CARCASS - BWP | H94: Ledge - Century ClubPrime or Green Gold , Royal Crown , Royal Touche , | I94: Supply and installation of Ledge with 50mm Ledge BWP and MR+ Laminate | J94: 1200 | L94: =J94+K94 -> 1200 | M94: 0.25 | N94: =L94*M94 -> 300 | O94: =L94+N94 -> 1500
A95: Mid Premium | B95: Modular | C95: Wet / Exposed Area | D95: Partition | E95: Partition -75mm | F95: Finish Material, Core Material | G95: MR+ Finish , CARCASS - BWP | H95: Century ClubPrime or Green Gold , Royal Crown , Royal Touche , | I95: Supply and installation of Partition - 75mm with BWP Ply Frame, MR+ laminate | J95: 1850 | L95: =J95+K95 -> 1850 | M95: 0.25 | N95: =L95*M95 -> 462.5 | O95: =L95+N95 -> 2312.5
A96: Mid Premium | B96: Modular | C96: Wet / Exposed Area | D96: Panel | E96: Wallpanel , pelmet , Ceiling Panel , Base panel / Side panel | F96: Finish Material, Core Material | G96: MR+ Finish , CARCASS - BWP | H96: Century ClubPrime or Green Gold , Royal Touche , Royal Crown , | I96: Supply and installation of Wall Panel with BWP Ply Frame, MR+ laminate | J96: 1225 | L96: =J96+K96 -> 1225 | M96: 0.25 | N96: =L96*M96 -> 306.25 | O96: =L96+N96 -> 1531.25
I97: Supply and installation of Pelmet Panel with BWP Ply Frame, MR+ laminate
I98: Supply and installation of Jam Panel with BWP Ply Frame, MR+ laminate
I99: Supply and installation of Ceiling Panel with BWP Ply Frame, MR+ laminate
I100: Supply and installation of Base Panel with BWP Ply Frame, MR+ laminate
A101: Designer lam FINISH | L101: =J101+K101 -> 0 | M101: 0.25 | N101: =L101*M101 -> 0 | O101: =L101+N101 -> 0
A102: Mid Premium | B102: Section | C102: Room Type | D102: Unit Type | E102: Panel type | F102: Category | G102: Material Type | H102: Brand | J102: Rate | L102: =J102+K102 -> #VALUE! | M102: 0.25 | N102: =L102*M102 -> #VALUE! | O102: =L102+N102 -> #VALUE!
A103: Mid Premium | B103: Modular | C103: Wet / Exposed Area | D103: Base Storage, Wall Storage, Tall Storage, Wardrobe | E103: Carcass/shutter | F103: Core Material, Finish Material, Hinges | G103: Carcass - BWP / Shutter - HDHMR Boilo, Designer lam Finish, Soft Close | H103: Carcass - Century ClubPrime or Green Gold / Shutter - Action TESA, Blum , , Royal Crown , Royal Touche , | I103: Supply and installation of Base storage unit with BWP Carcass, HDHMR Boilo Shutter, Designer laminate and soft close hinges | J103: 1940 | L103: =J103+K103 -> 1940 | M103: 0.25 | N103: =L103*M103 -> 485 | O103: =L103+N103 -> 2425
I104: Supply and installation of Wall storage unit with BWP Carcass, HDHMR Boilo Shutter, Designer finish laminate and soft close hinges
...

Sheet GQ 1
A2: No | B2: Description | C2: Length (Ft) | D2: Height | E2: Qty (sqft) | F2: Unit | G2: Length (mm) | H2: Height | I2: Unit | J2: Rate | K2: Quantity | L2: Amount
B4: Modular Work
B5: Living room
B6: =Economy!I46 -> Supply and installation of Base storage unit with MR Premium Carcass, HDF Shutter, Smooth finish laminate and soft close hinges | C6: 4 | D6: 1.5 | E6: =C6*D6 -> 6 | F6: Sft | G6: =C6*300 -> 1200 | H6: =D6*300 -> 450 | I6: mm | J6: =Economy!M46 -> 1718.75 | K6: 1 | L6: =K6*J6*E6 -> 10312.5
B7: =Economy!I57 -> Supply and installation of Base storage unit with MR Premium Carcass, Aluminium profile shutter with Tinted glass, Smooth finish laminate and soft close hinges | C7: 2 | D7: 1.5 | E7: =C7*D7 -> 3 | F7: Sft | G7: =C7*300 -> 600 | H7: =D7*300 -> 450 | I7: mm | J7: =Economy!M57 -> 2656.25 | K7: 1 | L7: =K7*J7*E7 -> 7968.75 | M7: Accessories to be added
B8: =Economy!I58 -> Supply and installation of Wall storage unit with MR Premium Carcass, Aluminium profile shutter with Tinted glass, Smooth finish laminate and soft close hinges | C8: 1.5 | D8: 5 | E8: =C8*D8 -> 7.5 | F8: Sft | G8: =C8*300 -> 450 | H8: =D8*300 -> 1500 | I8: mm | J8: =Economy!M57 -> 2656.25 | K8: 1 | L8: =K8*J8*E8 -> 19921.875
B9: =Economy!I81 -> Supply and installation of Wall Panel with MR Premium Carcass, Smooth finish laminate | C9: 6 | D9: 4.25 | E9: =C9*D9 -> 25.5 | F9: Sft | G9: =C9*300 -> 1800 | H9: =D9*300 -> 1275 | I9: mm | J9: =Economy!M81 -> 968.75 | K9: 1 | L9: =K9*J9*E9 -> 24703.125
B10: =Economy!I46 -> Supply and installation of Base storage unit with MR Premium Carcass, HDF Shutter, Smooth finish laminate and soft close hinges | C10: 3.5 | D10: 2.5 | E10: =C10*D10 -> 8.75 | F10: Sft | G10: =C10*300 -> 1050 | H10: =D10*300 -> 750 | I10: mm | J10: =Economy!M46 -> 1718.75 | K10: 1 | L10: =K10*J10*E10 -> 15039.062
B11: =Economy!I58 -> Supply and installation of Wall storage unit with MR Premium Carcass, Aluminium profile shutter with Tinted glass, Smooth finish laminate and soft close hinges | C11: 3.5 | D11: 2 | E11: =C11*D11 -> 7 | F11: Sft | G11: =C11*300 -> 1050 | H11: =D11*300 -> 600 | I11: mm | J11: =Economy!M57 -> 2656.25 | K11: 1 | L11: =K11*J11*E11 -> 18593.75
B12: =Economy!I83 -> Supply and installation of Jam Panel with MR Premium Carcass, Smooth finish laminate | C12: 65.25 | D12: 1 | E12: =C12*D12 -> 65.25 | F12: Sft | G12: =C12*300 -> 19575 | H12: =D12*300 -> 300 | I12: mm | J12: =Economy!M81 -> 968.75 | K12: 1 | L12: =K12*J12*E12 -> 63210.938 | M12: Jam panel to be added
B13: =Economy!I82 -> Supply and installation of Pelmet Panel with MR Premium Carcass, Smooth finish laminate | C13: 4 | D13: 1.5 | E13: =C13*D13 -> 6 | F13: Sft | G13: =C13*300 -> 1200 | H13: =D13*300 -> 450 | I13: mm | J13: =Economy!M81 -> 968.75 | K13: 1 | L13: =K13*J13*E13 -> 5812.5
B14: Pooja unit
B15: =Economy!I55 -> Supply and installation of Base storage unit with MR Premium Carcass, Plywood Border with Fluted Glass Shutter, Smooth finish laminate and soft close hinges | C15: 3 | D15: 4 | E15: =C15*D15 -> 12 | F15: Sft | G15: =C15*300 -> 900 | H15: =D15*300 -> 1200 | I15: mm | J15: =Economy!M55 -> 2375 | K15: 1 | L15: =K15*J15*E15 -> 28500
B16: =Economy!I46 -> Supply and installation of Base storage unit with MR Premium Carcass, HDF Shutter, Smooth finish laminate and soft close hinges | C16: 3 | D16: 3 | E16: =C16*D16 -> 9 | F16: Sft | G16: =C16*300 -> 900 | H16: =D16*300 -> 900 | I16: mm | J16: =Economy!M46 -> 1718.75 | K16: 1 | L16: =K16*J16*E16 -> 15468.75
B17: Kitchen
B18: =Economy!I3 -> Supply and installation of Base storage unit with BWP Carcass, HDF Shutter, Smooth finish laminate and soft close hinges | C18: 16.5 | D18: 2.75 | E18: =C18*D18 -> 45.375 | F18: Sft | G18: =C18*300 -> 4950 | H18: =D18*300 -> 825 | I18: mm | J18: =Economy!M3 -> 1843.75 | K18: 1 | L18: =K18*J18*E18 -> 83660.156 | M18: Mesh shutter
B19: =Economy!I4 -> Supply and installation of Wall storage unit with BWP Carcass, HDF Shutter, Smooth finish laminate and soft close hinges | C19: 13.5 | D19: 2.25 | E19: =C19*D19 -> 30.375 | F19: Sft | G19: =C19*300 -> 4050 | H19: =D19*300 -> 675 | I19: mm | J19: =Economy!M3 -> 1843.75 | K19: 1 | L19: =K19*J19*E19 -> 56003.906
B20: =Economy!I34 -> Supply and installation of Open unit - Inner 1mm with BWP Carcass and Smooth finish laminate | C20: 5.25 | D20: 1 | E20: =C20*D20 -> 5.25 | F20: Sft | G20: =C20*300 -> 1575 | H20: =D20*300 -> 300 | I20: mm | J20: =Economy!M34 -> 1843.75 | K20: 1 | L20: =K20*J20*E20 -> 9679.6875
B21: =Economy!I41 -> Supply and installation of Chimney Panel with BWP Carcass and Smooth finish laminate | C21: 3.25 | D21: 1 | E21: =C21*D21 -> 3.25 | F21: Sft | G21: =C21*300 -> 975 | H21: =D21*300 -> 300 | I21: mm | J21: =Economy!M41 -> 1093.75 | K21: 1 | L21: =K21*J21*E21 -> 3554.6875 | M21: Chimeny panel
B22: =Economy!I33 -> Supply and installation of Open unit - Inner 0.8mm with BWP Carcass and Smooth finish laminate | C22: 2 | D22: 4.25 | E22: =C22*D22 -> 8.5 | F22: Sft | G22: =C22*300 -> 600 | H22: =D22*300 -> 1275 | I22: mm | J22: =Economy!M33 -> 1562.5 | K22: 1 | L22: =K22*J22*E22 -> 13281.25 | M22: Tambour unit to be chnaged as open unit inner 0.8 and outer 1mm
B23: =Economy!I75 -> Supply and installation of Loft Frame and Shutter unit with MR Premium Frame, HDF Shutter, Smooth finish laminate and Soft Close hinges | C23: 18.5 | D23: 2.5 | E23: =C23*D23 -> 46.25 | F23: Sft | G23: =C23*300 -> 5550 | H23: =D23*300 -> 750 | I23: mm | J23: =Economy!M75 -> 965 | K23: 1 | L23: =K23*J23*E23 -> 44631.25
B24: =Economy!I81 -> Supply and installation of Wall Panel with MR Premium Carcass, Smooth finish laminate | C24: 16.5 | D24: 2 | E24: =C24*D24 -> 33 | F24: Sft | G24: =C24*300 -> 4950 | H24: =D24*300 -> 600 | I24: mm | J24: =Economy!M81 -> 968.75 | K24: 1 | L24: =K24*J24*E24 -> 31968.75
B25: Master Bedroom
B26: =Economy!I49 -> Supply and installation of Wardrobe with MR Premium Carcass, HDF Shutter, Smooth finish laminate and soft close hinges | C26: 6.5 | D26: 7 | E26: =C26*D26 -> 45.5 | F26: Sft | G26: =C26*300 -> 1950 | H26: =D26*300 -> 2100 | I26: mm | J26: =Economy!M46 -> 1718.75 | K26: 1 | L26: =K26*J26*E26 -> 78203.125
B27: =Economy!I48 -> Supply and installation of Tall storage unit with MR Premium Carcass, HDF Shutter, Smooth finish laminate and soft close hinges | C27: 2 | D27: 7 | E27: 15 | F27: Sft | G27: =C27*300 -> 600 | H27: =D27*300 -> 2100 | I27: mm | J27: =Economy!M46 -> 1718.75 | K27: 1 | L27: =K27*J27*E27 -> 25781.25
B28: =Economy!I75 -> Supply and installation of Loft Frame and Shutter unit with MR Premium Frame, HDF Shutter, Smooth finish laminate and Soft Close hinges | C28: 9.5 | D28: 2.5 | E28: =C28*D28 -> 23.75 | F28: Sft | G28: =C28*300 -> 2850 | H28: =D28*300 -> 750 | I28: mm | J28: =Economy!M75 -> 965 | K28: 1 | L28: =K28*J28*E28 -> 22918.75
B29: =Economy!I76 -> Supply and installation of Ledge with 25mm Ledge MR Premium and Smooth finish laminate | C29: 10.75 | D29: 1 | E29: =C29*D29 -> 10.75 | F29: Sft | G29: =C29*300 -> 3225 | H29: =D29*300 -> 300 | I29: mm | J29: =Economy!M76 -> 822.5 | K29: 1 | L29: =K29*J29*E29 -> 8841.875
B30: =Economy!I76 -> Supply and installation of Ledge with 25mm Ledge MR Premium and Smooth finish laminate | C30: 5 | D30: 1.5 | E30: =C30*D30 -> 7.5 | F30: Sft | G30: =C30*300 -> 1500 | H30: =D30*300 -> 450 | I30: mm | J30: =Economy!M76 -> 822.5 | K30: 1 | L30: =K30*J30*E30 -> 6168.75
B31: =Economy!I50 -> Supply and installation of Drawer Storage with MR Premium Carcass, HDF Shutter, Smooth finish laminate and soft close hinges | C31: 1.5 | D31: 1.5 | E31: =C31*D31 -> 2.25 | F31: Sft | G31: =C31*300 -> 450 | H31: =D31*300 -> 450 | I31: mm | J31: =Economy!M46 -> 1718.75 | K31: 1 | L31: =K31*J31*E31 -> 3867.1875 | M31: Drawer to be added
B32: =Economy!I47 -> Supply and installation of Wall storage unit with MR Premium Carcass, HDF Shutter, Smooth finish laminate and soft close hinges | C32: 2 | D32: 5 | E32: =C32*D32 -> 10 | F32: Sft | G32: =C32*300 -> 600 | H32: =D32*300 -> 1500 | I32: mm | J32: =Economy!M46 -> 1718.75 | K32: 1 | L32: =K32*J32*E32 -> 17187.5 | M32: Mirror to be added
B33: =Economy!I47 -> Supply and installation of Wall storage unit with MR Premium Carcass, HDF Shutter, Smooth finish laminate and soft close hinges | C33: 1.75 | D33: 1.5 | E33: =C33*D33 -> 2.625 | F33: Sft | G33: =C33*300 -> 525 | H33: =D33*300 -> 450 | I33: mm | J33: =Economy!M46 -> 1718.75 | K33: 1 | L33: =K33*J33*E33 -> 4511.7188 | M33: Drawer to be added
B34: =Economy!I82 -> Supply and installation of Pelmet Panel with MR Premium Carcass, Smooth finish laminate | C34: 4 | D34: 1.5 | E34: =C34*D34 -> 6 | F34: Sft | G34: =C34*300 -> 1200 | H34: =D34*300 -> 450 | I34: mm | J34: =Economy!M81 -> 968.75 | K34: 1 | L34: =K34*J34*E34 -> 5812.5
B35: Mother's bedroom
B36: =Economy!I49 -> Supply and installation of Wardrobe with MR Premium Carcass, HDF Shutter, Smooth finish laminate and soft close hinges | C36: 5.75 | D36: 8 | E36: =C36*D36 -> 46 | F36: Sft | G36: =C36*300 -> 1725 | H36: =D36*300 -> 2400 | I36: mm | J36: =Economy!M46 -> 1718.75 | K36: 1 | L36: =K36*J36*E36 -> 79062.5
B37: =Economy!I46 -> Supply and installation of Base storage unit with MR Premium Carcass, HDF Shutter, Smooth finish laminate and soft close hinges | C37: 5.5 | D37: 2 | E37: =C37*D37 -> 11 | F37: Sft | G37: =C37*300 -> 1650 | H37: =D37*300 -> 600 | I37: mm | J37: =Economy!M46 -> 1718.75 | K37: 1 | L37: =K37*J37*E37 -> 18906.25
B38: =Economy!I75 -> Supply and installation of Loft Frame and Shutter unit with MR Premium Frame, HDF Shutter, Smooth finish laminate and Soft Close hinges | C38: 11.25 | D38: 1.5 | E38: =C38*D38 -> 16.875 | F38: Sft | G38: =C38*300 -> 3375 | H38: =D38*300 -> 450 | I38: mm | J38: =Economy!M75 -> 965 | K38: 1 | L38: =K38*J38*E38 -> 16284.375
B39: =Economy!I85 -> Supply and installation of Base Panel with MR Premium Carcass, Smooth finish laminate | C39: 7.5 | D39: 2 | E39: =C39*D39 -> 15 | F39: Sft | G39: =C39*300 -> 2250 | H39: =D39*300 -> 600 | I39: mm | J39: =Economy!M81 -> 968.75 | K39: 1 | L39: =K39*J39*E39 -> 14531.25
B40: =Economy!I76 -> Supply and installation of Ledge with 25mm Ledge MR Premium and Smooth finish laminate | C40: 3 | D40: 1 | E40: =C40*D40 -> 3 | F40: Sft | G40: =C40*300 -> 900 | H40: =D40*300 -> 300 | I40: mm | J40: =Economy!M76 -> 822.5 | K40: 1 | L40: =K40*J40*E40 -> 2467.5
B41: =Economy!I80 -> Supply and installation of Chamfered Wall Panel with MR Premium Carcass, Smooth finish laminate | C41: 2 | D41: 3.5 | E41: =C41*D41 -> 7 | F41: Sft | G41: =C41*300 -> 600 | H41: =D41*300 -> 1050 | I41: mm | J41: =Economy!M46 -> 1718.75 | K41: 1 | L41: =K41*J41*E41 -> 12031.25 | M41: Mirror Costing to be added
B42: =Economy!I50 -> Supply and installation of Drawer Storage with MR Premium Carcass, HDF Shutter, Smooth finish laminate and soft close hinges | C42: 2 | D42: 1.5 | E42: 7.1 | F42: Sft | G42: 1425 | H42: 450 | I42: mm | J42: =Economy!M46 -> 1718.75 | K42: 1 | L42: =K42*J42*E42 -> 12203.125
B43: =Economy!I82 -> Supply and installation of Pelmet Panel with MR Premium Carcass, Smooth finish laminate | C43: 4 | D43: 1.5 | E43: =C43*D43 -> 6 | F43: Sft | G43: =C43*300 -> 1200 | H43: =D43*300 -> 450 | I43: mm | J43: =Economy!M81 -> 968.75 | K43: 1 | L43: =K43*J43*E43 -> 5812.5
B44: Son's Bedroom
B45: =Economy!I49 -> Supply and installation of Wardrobe with MR Premium Carcass, HDF Shutter, Smooth finish laminate and soft close hinges | C45: 6.5 | D45: 7 | E45: =C45*D45 -> 45.5 | F45: Sft | G45: =C45*300 -> 1950 | H45: =D45*300 -> 2100 | I45: mm | J45: =Economy!M46 -> 1718.75 | K45: 1 | L45: =K45*J45*E45 -> 78203.125
B46: =Economy!I76 -> Supply and installation of Ledge with 25mm Ledge MR Premium and Smooth finish laminate | C46: 10.25 | D46: 2.25 | E46: =C46*D46 -> 23.0625 | F46: Sft | G46: =C46*300 -> 3075 | H46: =D46*300 -> 675 | I46: mm | J46: =Economy!M75 -> 965 | K46: 1 | L46: =K46*J46*E46 -> 22255.312
B47: =Economy!I85 -> Supply and installation of Base Panel with MR Premium Carcass, Smooth finish laminate | C47: 3 | D47: 2 | E47: =C47*D47 -> 6 | F47: Sft | G47: =C47*300 -> 900 | H47: =D47*300 -> 600 | I47: mm | J47: =Economy!M81 -> 968.75 | K47: 1 | L47: =K47*J47*E47 -> 5812.5
B48: =Economy!I48 -> Supply and installation of Tall storage unit with MR Premium Carcass, HDF Shutter, Smooth finish laminate and soft close hinges | C48: 2.25 | D48: 5 | E48: 15 | F48: Sft | G48: =C48*300 -> 675 | H48: =D48*300 -> 1500 | I48: mm | J48: =Economy!M46 -> 1718.75 | K48: 1 | L48: =K48*J48*E48 -> 25781.25 | M48: CNC Costing to be added
B49: =Economy!I50 -> Supply and installation of Drawer Storage with MR Premium Carcass, HDF Shutter, Smooth finish laminate and soft close hinges | C49: 2.25 | D49: 1.5 | E49: 7.1 | F49: Sft | G49: =C49*300 -> 675 | H49: 450 | I49: mm | J49: =Economy!M46 -> 1718.75 | K49: 1 | L49: =K49*J49*E49 -> 12203.125
B50: =Economy!I76 -> Supply and installation of Ledge with 25mm Ledge MR Premium and Smooth finish laminate | C50: 6 | D50: 2 | E50: =C50*D50 -> 12 | F50: Sft | G50: =C50*300 -> 1800 | H50: =D50*300 -> 600 | I50: mm | J50: =Economy!M76 -> 822.5 | K50: 1 | L50: =K50*J50*E50 -> 9870
B51: =Economy!I52 -> Supply and installation of Wall storage - Inner 1mm unit with MR Premium Carcass, HDF Shutter, Smooth finish laminate and soft close hinges | C51: 1.75 | D51: 4.5 | E51: =C51*D51 -> 7.875 | F51: Sft | G51: =C51*300 -> 525 | H51: =D51*300 -> 1350 | I51: mm | J51: =Economy!M46 -> 1718.75 | K51: 1 | L51: =K51*J51*E51 -> 13535.156
B52: =Economy!I51 -> Supply and installation of Base storage - Inner 1mm unit with MR Premium Carcass, HDF Shutter, Smooth finish laminate and soft close hinges | C52: 1.75 | D52: 2 | E52: =C52*D52 -> 3.5 | F52: Sft | G52: =C52*300 -> 525 | H52: =D52*300 -> 600 | I52: mm | J52: =Economy!M51 -> 1906.25 | K52: 1 | L52: =K52*J52*E52 -> 6671.875
B53: =Economy!I76 -> Supply and installation of Ledge with 25mm Ledge MR Premium and Smooth finish laminate | C53: 4 | D53: 1 | E53: =C53*D53 -> 4 | F53: Sft | G53: =C53*300 -> 1200 | H53: =D53*300 -> 300 | I53: mm | J53: =Economy!M76 -> 822.5 | K53: 1 | L53: =K53*J53*E53 -> 3290
B54: =Economy!I82 -> Supply and installation of Pelmet Panel with MR Premium Carcass, Smooth finish laminate | C54: 4 | D54: 1.5 | E54: =C54*D54 -> 6 | F54: Sft | G54: =C54*300 -> 1200 | H54: =D54*300 -> 450 | I54: mm | J54: =Economy!M81 -> 968.75 | K54: 1 | L54: =K54*J54*E54 -> 5812.5
B55: Balcony
B56: =Economy!I5 -> Supply and installation of Tall storage unit with BWP Carcass, HDF Shutter, Smooth finish laminate and soft close hinges | C56: 2 | D56: 6 | E56: =C56*D56 -> 12 | F56: Sft | G56: =C56*300 -> 600 | H56: =D56*300 -> 1800 | I56: mm | J56: =Economy!M3 -> 1843.75 | K56: 1 | L56: =K56*J56*E56 -> 22125
B57: Vanity units
B58: =Economy!I4 -> Supply and installation of Wall storage unit with BWP Carcass, HDF Shutter, Smooth finish laminate and soft close hinges | C58: 2 | D58: 2 | E58: =C58*D58 -> 4 | F58: Sft | G58: =C58*300 -> 600 | H58: =D58*300 -> 600 | I58: mm | J58: =Economy!M3 -> 1843.75 | K58: 1 | L58: =K58*J58*E58*K58 -> 7375
B59: =Economy!I4 -> Supply and installation of Wall storage unit with BWP Carcass, HDF Shutter, Smooth finish laminate and soft close hinges | C59: 2 | D59: 2 | E59: =C59*D59 -> 4 | F59: Sft | G59: =C59*300 -> 600 | H59: =D59*300 -> 600 | I59: mm | J59: =Economy!M3 -> 1843.75 | K59: 1 | L59: =K59*J59*E59*K59 -> 7375
B60: =Economy!I4 -> Supply and installation of Wall storage unit with BWP Carcass, HDF Shutter, Smooth finish laminate and soft close hinges | C60: 2 | D60: 2 | E60: =C60*D60 -> 4 | F60: Sft | G60: =C60*300 -> 600 | H60: =D60*300 -> 600 | I60: mm | J60: =Economy!M3 -> 1843.75 | K60: 1 | L60: =K60*J60*E60*K60 -> 7375
B61: TRANSPORTATION,LOADING & UNLOADING
B62: SUB TOTAL | L62: =SUM(L5:L60) -> 1014587.2
B63: Markup | L63: 0.05
B64: TOTAL | L64: =(L62*L63)+L62 -> 1065316.5
B65: GST 18% | L65: =L64*18% -> 191756.98
B66: GRAND TOTAL | L66: =L64+L65 -> 1257073.5

Sheet Copy of GQ 1
A2: No | B2: Description | C2: Length (Ft) | D2: Height | E2: Qty (sqft) | F2: Unit | G2: Length (mm) | H2: Height | I2: Unit | J2: Rate | K2: Quantity | L2: Amount
B4: Jodular Work
B5: Living room
B6: =Economy!I46 -> Supply and installation of Base storage unit with MR Premium Carcass, HDF Shutter, Smooth finish laminate and soft close hinges | C6: 4 | D6: 1.5 | E6: =C6*D6 -> 6 | F6: Sft | G6: =C6*300 -> 1200 | H6: =D6*300 -> 450 | I6: mm | J6: =Economy!J46 -> 1375 | K6: 1 | L6: =K6*J6*E6 -> 8250
B7: =Economy!I57 -> Supply and installation of Base storage unit with MR Premium Carcass, Aluminium profile shutter with Tinted glass, Smooth finish laminate and soft close hinges | C7: 2 | D7: 1.5 | E7: =C7*D7 -> 3 | F7: Sft | G7: =C7*300 -> 600 | H7: =D7*300 -> 450 | I7: mm | J7: =Economy!J57 -> 2125 | K7: 1 | L7: =K7*J7*E7 -> 6375 | M7: Accessories to be added
B8: =Economy!I58 -> Supply and installation of Wall storage unit with MR Premium Carcass, Aluminium profile shutter with Tinted glass, Smooth finish laminate and soft close hinges | C8: 1.5 | D8: 5 | E8: =C8*D8 -> 7.5 | F8: Sft | G8: =C8*300 -> 450 | H8: =D8*300 -> 1500 | I8: mm | J8: =Economy!J57 -> 2125 | K8: 1 | L8: =K8*J8*E8 -> 15937.5
B9: =Economy!I81 -> Supply and installation of Wall Panel with MR Premium Carcass, Smooth finish laminate | C9: 6 | D9: 4.25 | E9: =C9*D9 -> 25.5 | F9: Sft | G9: =C9*300 -> 1800 | H9: =D9*300 -> 1275 | I9: mm | J9: =Economy!J81 -> 775 | K9: 1 | L9: =K9*J9*E9 -> 19762.5
B10: =Economy!I46 -> Supply and installation of Base storage unit with MR Premium Carcass, HDF Shutter, Smooth finish laminate and soft close hinges | C10: 3.5 | D10: 2.5 | E10: =C10*D10 -> 8.75 | F10: Sft | G10: =C10*300 -> 1050 | H10: =D10*300 -> 750 | I10: mm | J10: =Economy!J46 -> 1375 | K10: 1 | L10: =K10*J10*E10 -> 12031.25
B11: =Economy!I58 -> Supply and installation of Wall storage unit with MR Premium Carcass, Aluminium profile shutter with Tinted glass, Smooth finish laminate and soft close hinges | C11: 3.5 | D11: 2 | E11: =C11*D11 -> 7 | F11: Sft | G11: =C11*300 -> 1050 | H11: =D11*300 -> 600 | I11: mm | J11: =Economy!J57 -> 2125 | K11: 1 | L11: =K11*J11*E11 -> 14875
B12: =Economy!I83 -> Supply and installation of Jam Panel with MR Premium Carcass, Smooth finish laminate | C12: 65.25 | D12: 1 | E12: =C12*D12 -> 65.25 | F12: Sft | G12: =C12*300 -> 19575 | H12: =D12*300 -> 300 | I12: mm | J12: =Economy!J81 -> 775 | K12: 1 | L12: =K12*J12*E12 -> 50568.75 | M12: Jam panel to be added
B13: =Economy!I82 -> Supply and installation of Pelmet Panel with MR Premium Carcass, Smooth finish laminate | C13: 4 | D13: 1.5 | E13: =C13*D13 -> 6 | F13: Sft | G13: =C13*300 -> 1200 | H13: =D13*300 -> 450 | I13: mm | J13: =Economy!J81 -> 775 | K13: 1 | L13: =K13*J13*E13 -> 4650
B14: Pooja unit
B15: =Economy!I55 -> Supply and installation of Base storage unit with MR Premium Carcass, Plywood Border with Fluted Glass Shutter, Smooth finish laminate and soft close hinges | C15: 3 | D15: 4 | E15: =C15*D15 -> 12 | F15: Sft | G15: =C15*300 -> 900 | H15: =D15*300 -> 1200 | I15: mm | J15: =Economy!J55 -> 1900 | K15: 1 | L15: =K15*J15*E15 -> 22800
B16: =Economy!I46 -> Supply and installation of Base storage unit with MR Premium Carcass, HDF Shutter, Smooth finish laminate and soft close hinges | C16: 3 | D16: 3 | E16: =C16*D16 -> 9 | F16: Sft | G16: =C16*300 -> 900 | H16: =D16*300 -> 900 | I16: mm | J16: =Economy!J46 -> 1375 | K16: 1 | L16: =K16*J16*E16 -> 12375
B17: Kitchen
B18: =Economy!I3 -> Supply and installation of Base storage unit with BWP Carcass, HDF Shutter, Smooth finish laminate and soft close hinges | C18: 16.5 | D18: 2.75 | E18: =C18*D18 -> 45.375 | F18: Sft | G18: =C18*300 -> 4950 | H18: =D18*300 -> 825 | I18: mm | J18: =Economy!J3 -> 1475 | K18: 1 | L18: =K18*J18*E18 -> 66928.125 | M18: Jesh shutter
B19: =Economy!I4 -> Supply and installation of Wall storage unit with BWP Carcass, HDF Shutter, Smooth finish laminate and soft close hinges | C19: 13.5 | D19: 2.25 | E19: =C19*D19 -> 30.375 | F19: Sft | G19: =C19*300 -> 4050 | H19: =D19*300 -> 675 | I19: mm | J19: =Economy!J3 -> 1475 | K19: 1 | L19: =K19*J19*E19 -> 44803.125
B20: =Economy!I34 -> Supply and installation of Open unit - Inner 1mm with BWP Carcass and Smooth finish laminate | C20: 5.25 | D20: 1 | E20: =C20*D20 -> 5.25 | F20: Sft | G20: =C20*300 -> 1575 | H20: =D20*300 -> 300 | I20: mm | J20: =Economy!J34 -> 1475 | K20: 1 | L20: =K20*J20*E20 -> 7743.75
B21: =Economy!I41 -> Supply and installation of Chimney Panel with BWP Carcass and Smooth finish laminate | C21: 3.25 | D21: 1 | E21: =C21*D21 -> 3.25 | F21: Sft | G21: =C21*300 -> 975 | H21: =D21*300 -> 300 | I21: mm | J21: =Economy!J41 -> 875 | K21: 1 | L21: =K21*J21*E21 -> 2843.75 | M21: Chimeny panel
B22: =Economy!I33 -> Supply and installation of Open unit - Inner 0.8mm with BWP Carcass and Smooth finish laminate | C22: 2 | D22: 4.25 | E22: =C22*D22 -> 8.5 | F22: Sft | G22: =C22*300 -> 600 | H22: =D22*300 -> 1275 | I22: mm | J22: =Economy!J33 -> 1250 | K22: 1 | L22: =K22*J22*E22 -> 10625 | M22: Tambour unit to be chnaged as open unit inner 0.8 and outer 1mm
B23: =Economy!I75 -> Supply and installation of Loft Frame and Shutter unit with MR Premium Frame, HDF Shutter, Smooth finish laminate and Soft Close hinges | C23: 18.5 | D23: 2.5 | E23: =C23*D23 -> 46.25 | F23: Sft | G23: =C23*300 -> 5550 | H23: =D23*300 -> 750 | I23: mm | J23: =Economy!J75 -> 772 | K23: 1 | L23: =K23*J23*E23 -> 35705
B24: =Economy!I81 -> Supply and installation of Wall Panel with MR Premium Carcass, Smooth finish laminate | C24: 16.5 | D24: 2 | E24: =C24*D24 -> 33 | F24: Sft | G24: =C24*300 -> 4950 | H24: =D24*300 -> 600 | I24: mm | J24: =Economy!J81 -> 775 | K24: 1 | L24: =K24*J24*E24 -> 25575
B25: Jaster Bedroom
B26: =Economy!I49 -> Supply and installation of Wardrobe with MR Premium Carcass, HDF Shutter, Smooth finish laminate and soft close hinges | C26: 6.5 | D26: 7 | E26: =C26*D26 -> 45.5 | F26: Sft | G26: =C26*300 -> 1950 | H26: =D26*300 -> 2100 | I26: mm | J26: =Economy!J46 -> 1375 | K26: 1 | L26: =K26*J26*E26 -> 62562.5
B27: =Economy!I48 -> Supply and installation of Tall storage unit with MR Premium Carcass, HDF Shutter, Smooth finish laminate and soft close hinges | C27: 2 | D27: 7 | E27: 15 | F27: Sft | G27: =C27*300 -> 600 | H27: =D27*300 -> 2100 | I27: mm | J27: =Economy!J46 -> 1375 | K27: 1 | L27: =K27*J27*E27 -> 20625
B28: =Economy!I75 -> Supply and installation of Loft Frame and Shutter unit with MR Premium Frame, HDF Shutter, Smooth finish laminate and Soft Close hinges | C28: 9.5 | D28: 2.5 | E28: =C28*D28 -> 23.75 | F28: Sft | G28: =C28*300 -> 2850 | H28: =D28*300 -> 750 | I28: mm | J28: =Economy!J75 -> 772 | K28: 1 | L28: =K28*J28*E28 -> 18335
B29: =Economy!I76 -> Supply and installation of Ledge with 25mm Ledge MR Premium and Smooth finish laminate | C29: 10.75 | D29: 1 | E29: =C29*D29 -> 10.75 | F29: Sft | G29: =C29*300 -> 3225 | H29: =D29*300 -> 300 | I29: mm | J29: =Economy!J76 -> 658 | K29: 1 | L29: =K29*J29*E29 -> 7073.5
B30: =Economy!I76 -> Supply and installation of Ledge with 25mm Ledge MR Premium and Smooth finish laminate | C30: 5 | D30: 1.5 | E30: =C30*D30 -> 7.5 | F30: Sft | G30: =C30*300 -> 1500 | H30: =D30*300 -> 450 | I30: mm | J30: =Economy!J76 -> 658 | K30: 1 | L30: =K30*J30*E30 -> 4935
B31: =Economy!I50 -> Supply and installation of Drawer Storage with MR Premium Carcass, HDF Shutter, Smooth finish laminate and soft close hinges | C31: 1.5 | D31: 1.5 | E31: =C31*D31 -> 2.25 | F31: Sft | G31: =C31*300 -> 450 | H31: =D31*300 -> 450 | I31: mm | J31: =Economy!J46 -> 1375 | K31: 1 | L31: =K31*J31*E31 -> 3093.75 | M31: Drawer to be added
B32: =Economy!I47 -> Supply and installation of Wall storage unit with MR Premium Carcass, HDF Shutter, Smooth finish laminate and soft close hinges | C32: 2 | D32: 5 | E32: =C32*D32 -> 10 | F32: Sft | G32: =C32*300 -> 600 | H32: =D32*300 -> 1500 | I32: mm | J32: =Economy!J46 -> 1375 | K32: 1 | L32: =K32*J32*E32 -> 13750 | M32: Jirror to be added
B33: =Economy!I47 -> Supply and installation of Wall storage unit with MR Premium Carcass, HDF Shutter, Smooth finish laminate and soft close hinges | C33: 1.75 | D33: 1.5 | E33: =C33*D33 -> 2.625 | F33: Sft | G33: =C33*300 -> 525 | H33: =D33*300 -> 450 | I33: mm | J33: =Economy!J46 -> 1375 | K33: 1 | L33: =K33*J33*E33 -> 3609.375 | M33: Drawer to be added
B34: =Economy!I82 -> Supply and installation of Pelmet Panel with MR Premium Carcass, Smooth finish laminate | C34: 4 | D34: 1.5 | E34: =C34*D34 -> 6 | F34: Sft | G34: =C34*300 -> 1200 | H34: =D34*300 -> 450 | I34: mm | J34: =Economy!J81 -> 775 | K34: 1 | L34: =K34*J34*E34 -> 4650
B35: Jother's bedroom
B36: =Economy!I49 -> Supply and installation of Wardrobe with MR Premium Carcass, HDF Shutter, Smooth finish laminate and soft close hinges | C36: 5.75 | D36: 8 | E36: =C36*D36 -> 46 | F36: Sft | G36: =C36*300 -> 1725 | H36: =D36*300 -> 2400 | I36: mm | J36: =Economy!J46 -> 1375 | K36: 1 | L36: =K36*J36*E36 -> 63250
B37: =Economy!I46 -> Supply and installation of Base storage unit with MR Premium Carcass, HDF Shutter, Smooth finish laminate and soft close hinges | C37: 5.5 | D37: 2 | E37: =C37*D37 -> 11 | F37: Sft | G37: =C37*300 -> 1650 | H37: =D37*300 -> 600 | I37: mm | J37: =Economy!J46 -> 1375 | K37: 1 | L37: =K37*J37*E37 -> 15125
B38: =Economy!I75 -> Supply and installation of Loft Frame and Shutter unit with MR Premium Frame, HDF Shutter, Smooth finish laminate and Soft Close hinges | C38: 11.25 | D38: 1.5 | E38: =C38*D38 -> 16.875 | F38: Sft | G38: =C38*300 -> 3375 | H38: =D38*300 -> 450 | I38: mm | J38: =Economy!J75 -> 772 | K38: 1 | L38: =K38*J38*E38 -> 13027.5
B39: =Economy!I85 -> Supply and installation of Base Panel with MR Premium Carcass, Smooth finish laminate | C39: 7.5 | D39: 2 | E39: =C39*D39 -> 15 | F39: Sft | G39: =C39*300 -> 2250 | H39: =D39*300 -> 600 | I39: mm | J39: =Economy!J81 -> 775 | K39: 1 | L39: =K39*J39*E39 -> 11625
B40: =Economy!I76 -> Supply and installation of Ledge with 25mm Ledge MR Premium and Smooth finish laminate | C40: 3 | D40: 1 | E40: =C40*D40 -> 3 | F40: Sft | G40: =C40*300 -> 900 | H40: =D40*300 -> 300 | I40: mm | J40: =Economy!J76 -> 658 | K40: 1 | L40: =K40*J40*E40 -> 1974
B41: =Economy!I80 -> Supply and installation of Chamfered Wall Panel with MR Premium Carcass, Smooth finish laminate | C41: 2 | D41: 3.5 | E41: =C41*D41 -> 7 | F41: Sft | G41: =C41*300 -> 600 | H41: =D41*300 -> 1050 | I41: mm | J41: =Economy!J46 -> 1375 | K41: 1 | L41: =K41*J41*E41 -> 9625 | M41: Jirror Costing to be added
B42: =Economy!I50 -> Supply and installation of Drawer Storage with MR Premium Carcass, HDF Shutter, Smooth finish laminate and soft close hinges | C42: 2 | D42: 1.5 | E42: 7.1 | F42: Sft | G42: 1425 | H42: 450 | I42: mm | J42: =Economy!J46 -> 1375 | K42: 1 | L42: =K42*J42*E42 -> 9762.5
B43: =Economy!I82 -> Supply and installation of Pelmet Panel with MR Premium Carcass, Smooth finish laminate | C43: 4 | D43: 1.5 | E43: =C43*D43 -> 6 | F43: Sft | G43: =C43*300 -> 1200 | H43: =D43*300 -> 450 | I43: mm | J43: =Economy!J81 -> 775 | K43: 1 | L43: =K43*J43*E43 -> 4650
B44: Son's Bedroom
B45: =Economy!I49 -> Supply and installation of Wardrobe with MR Premium Carcass, HDF Shutter, Smooth finish laminate and soft close hinges | C45: 6.5 | D45: 7 | E45: =C45*D45 -> 45.5 | F45: Sft | G45: =C45*300 -> 1950 | H45: =D45*300 -> 2100 | I45: mm | J45: =Economy!J46 -> 1375 | K45: 1 | L45: =K45*J45*E45 -> 62562.5
B46: =Economy!I76 -> Supply and installation of Ledge with 25mm Ledge MR Premium and Smooth finish laminate | C46: 10.25 | D46: 2.25 | E46: =C46*D46 -> 23.0625 | F46: Sft | G46: =C46*300 -> 3075 | H46: =D46*300 -> 675 | I46: mm | J46: =Economy!J75 -> 772 | K46: 1 | L46: =K46*J46*E46 -> 17804.25
B47: =Economy!I85 -> Supply and installation of Base Panel with MR Premium Carcass, Smooth finish laminate | C47: 3 | D47: 2 | E47: =C47*D47 -> 6 | F47: Sft | G47: =C47*300 -> 900 | H47: =D47*300 -> 600 | I47: mm | J47: =Economy!J81 -> 775 | K47: 1 | L47: =K47*J47*E47 -> 4650
B48: =Economy!I48 -> Supply and installation of Tall storage unit with MR Premium Carcass, HDF Shutter, Smooth finish laminate and soft close hinges | C48: 2.25 | D48: 5 | E48: 15 | F48: Sft | G48: =C48*300 -> 675 | H48: =D48*300 -> 1500 | I48: mm | J48: =Economy!J46 -> 1375 | K48: 1 | L48: =K48*J48*E48 -> 20625 | M48: CNC Costing to be added
B49: =Economy!I50 -> Supply and installation of Drawer Storage with MR Premium Carcass, HDF Shutter, Smooth finish laminate and soft close hinges | C49: 2.25 | D49: 1.5 | E49: 7.1 | F49: Sft | G49: =C49*300 -> 675 | H49: 450 | I49: mm | J49: =Economy!J46 -> 1375 | K49: 1 | L49: =K49*J49*E49 -> 9762.5
B50: =Economy!I76 -> Supply and installation of Ledge with 25mm Ledge MR Premium and Smooth finish laminate | C50: 6 | D50: 2 | E50: =C50*D50 -> 12 | F50: Sft | G50: =C50*300 -> 1800 | H50: =D50*300 -> 600 | I50: mm | J50: =Economy!J76 -> 658 | K50: 1 | L50: =K50*J50*E50 -> 7896
B51: =Economy!I52 -> Supply and installation of Wall storage - Inner 1mm unit with MR Premium Carcass, HDF Shutter, Smooth finish laminate and soft close hinges | C51: 1.75 | D51: 4.5 | E51: =C51*D51 -> 7.875 | F51: Sft | G51: =C51*300 -> 525 | H51: =D51*300 -> 1350 | I51: mm | J51: =Economy!J46 -> 1375 | K51: 1 | L51: =K51*J51*E51 -> 10828.125
B52: =Economy!I51 -> Supply and installation of Base storage - Inner 1mm unit with MR Premium Carcass, HDF Shutter, Smooth finish laminate and soft close hinges | C52: 1.75 | D52: 2 | E52: =C52*D52 -> 3.5 | F52: Sft | G52: =C52*300 -> 525 | H52: =D52*300 -> 600 | I52: mm | J52: =Economy!J51 -> 1525 | K52: 1 | L52: =K52*J52*E52 -> 5337.5
B53: =Economy!I76 -> Supply and installation of Ledge with 25mm Ledge MR Premium and Smooth finish laminate | C53: 4 | D53: 1 | E53: =C53*D53 -> 4 | F53: Sft | G53: =C53*300 -> 1200 | H53: =D53*300 -> 300 | I53: mm | J53: =Economy!J76 -> 658 | K53: 1 | L53: =K53*J53*E53 -> 2632
B54: =Economy!I82 -> Supply and installation of Pelmet Panel with MR Premium Carcass, Smooth finish laminate | C54: 4 | D54: 1.5 | E54: =C54*D54 -> 6 | F54: Sft | G54: =C54*300 -> 1200 | H54: =D54*300 -> 450 | I54: mm | J54: =Economy!J81 -> 775 | K54: 1 | L54: =K54*J54*E54 -> 4650
B55: Balcony
B56: =Economy!I5 -> Supply and installation of Tall storage unit with BWP Carcass, HDF Shutter, Smooth finish laminate and soft close hinges | C56: 2 | D56: 6 | E56: =C56*D56 -> 12 | F56: Sft | G56: =C56*300 -> 600 | H56: =D56*300 -> 1800 | I56: mm | J56: =Economy!J3 -> 1475 | K56: 1 | L56: =K56*J56*E56 -> 17700
B57: Vanity units
B58: =Economy!I4 -> Supply and installation of Wall storage unit with BWP Carcass, HDF Shutter, Smooth finish laminate and soft close hinges | C58: 2 | D58: 2 | E58: =C58*D58 -> 4 | F58: Sft | G58: =C58*300 -> 600 | H58: =D58*300 -> 600 | I58: mm | J58: =Economy!J3 -> 1475 | K58: 1 | L58: =K58*J58*E58*K58 -> 5900
B59: =Economy!I4 -> Supply and installation of Wall storage unit with BWP Carcass, HDF Shutter, Smooth finish laminate and soft close hinges | C59: 2 | D59: 2 | E59: =C59*D59 -> 4 | F59: Sft | G59: =C59*300 -> 600 | H59: =D59*300 -> 600 | I59: mm | J59: =Economy!J3 -> 1475 | K59: 1 | L59: =K59*J59*E59*K59 -> 5900
B60: =Economy!I4 -> Supply and installation of Wall storage unit with BWP Carcass, HDF Shutter, Smooth finish laminate and soft close hinges | C60: 2 | D60: 2 | E60: =C60*D60 -> 4 | F60: Sft | G60: =C60*300 -> 600 | H60: =D60*300 -> 600 | I60: mm | J60: =Economy!J3 -> 1475 | K60: 1 | L60: =K60*J60*E60*K60 -> 5900
B61: TRANSPORTATION,LOADING & UNLOADING | N61: =L62*0.4 -> 324667.9
B62: SUB TOTAL | L62: =SUM(L5:L60) -> 811669.75
B63: Jarkup | L63: 0.05
B64: TOTAL | L64: =(L62*L63)+L62 -> 852253.24
B65: GST 18% | L65: =L64*18% -> 153405.58
B66: GRAND TOTAL | L66: =L62+L65 -> 965075.33

Sheet Finemake Price
A1: Quotation - Interiors:
A2: Material Specification
B3: Cabinets (Carcass) | E3: Kitchen - Century/Greenply BWP 710 Grade (15 Years Warranty), Rest Century/Greenply MR Grade Plywood (15 Years Warranty) | U3: Kitchen - Century/Greenply BWP 710 Grade (15 Years Warranty), Rest Century/Greenply MR Grade Plywood (15 Years Warranty)
B4: Cabinet Panel Thickness | E4: 18 mm(16mm+1mm+1mm) 8mm
B5: Cabinet Back Panel Thickness
B6: Base material for shutters | E6: (Plywood) Kitchen - Century/Greenply BWP 710 Grade (10 Years Warranty), Rest Century/Greenply MR Grade Plywood (10 Years Warranty) (HDHMR) - Action tesa
B7: Shutter Thickness | E7: 18 mm(16mm+1mm+1mm)
B8: Laminate Thickness (Inside & Outside)
B9: Edge Banding | E9: Rehau / Equivalent Make
B10: Laminate Finish | E10: As Mentioned in Description
B11: Colour Options | E11: Merino / Greenlam/ Centurylam/ NewMika
B12: Hinges and Drawer Slides | E12: Hettich Soft close Hinges & Quadro Channels for Kitchen & for Wardrobe/ loft
B13: Handles | E13: 4" or 6" handles for Floor Cabinets Shutters,4" or 6" handles for loft/Wall Cabinets and 8 " handles for Wardrobe . And kitchen - basic rate Rs. 120
A15: No | B15: Description | C15: Length | D15: Height | E15: Qty (sqft) | F15: Unit | G15: Length | H15: Height | I15: Unit | J15: Rate | K15: Quantity | L15: Amount
B17: Modular Work
B18: Living room
B19: =Economy!I46 -> Supply and installation of Base storage unit with MR Premium Carcass, HDF Shutter, Smooth finish laminate and soft close hinges | C19: 4 | D19: 1.5 | E19: =C19*D19 -> 6 | F19: Sft | G19: =C19*300 -> 1200 | H19: =D19*300 -> 450 | I19: mm | J19: =875 -> 875 | K19: 1 | L19: =K19*J19*E19 -> 5250 | M19: =E19*150 -> 900
B20: =Economy!I57 -> Supply and installation of Base storage unit with MR Premium Carcass, Aluminium profile shutter with Tinted glass, Smooth finish laminate and soft close hinges | C20: 2 | D20: 1.5 | E20: =C20*D20 -> 3 | F20: Sft | G20: =C20*300 -> 600 | H20: =D20*300 -> 450 | I20: mm | K20: 1 | L20: =K20*J20*E20 -> 0 | M20: =E20*150 -> 450
B21: =Economy!I58 -> Supply and installation of Wall storage unit with MR Premium Carcass, Aluminium profile shutter with Tinted glass, Smooth finish laminate and soft close hinges | C21: 1.5 | D21: 5 | E21: =C21*D21 -> 7.5 | F21: Sft | G21: =C21*300 -> 450 | H21: =D21*300 -> 1500 | I21: mm | K21: 1 | L21: =K21*J21*E21 -> 0 | M21: =E21*150 -> 1125
B22: =Economy!I81 -> Supply and installation of Wall Panel with MR Premium Carcass, Smooth finish laminate | C22: 6 | D22: 4.25 | E22: =C22*D22 -> 25.5 | F22: Sft | G22: =C22*300 -> 1800 | H22: =D22*300 -> 1275 | I22: mm | J22: =75 -> 75 | K22: 1 | L22: =K22*J22*E22 -> 1912.5 | M22: =E22*150 -> 3825
B23: =Economy!I46 -> Supply and installation of Base storage unit with MR Premium Carcass, HDF Shutter, Smooth finish laminate and soft close hinges | C23: 3.5 | D23: 2.5 | E23: =C23*D23 -> 8.75 | F23: Sft | G23: =C23*300 -> 1050 | H23: =D23*300 -> 750 | I23: mm | J23: 875 | K23: 1 | L23: =K23*J23*E23 -> 7656.25 | M23: =E23*150 -> 1312.5
B24: =Economy!I58 -> Supply and installation of Wall storage unit with MR Premium Carcass, Aluminium profile shutter with Tinted glass, Smooth finish laminate and soft close hinges | C24: 3.5 | D24: 2 | E24: =C24*D24 -> 7 | F24: Sft | G24: =C24*300 -> 1050 | H24: =D24*300 -> 600 | I24: mm | K24: 1 | L24: =K24*J24*E24 -> 0 | M24: =E24*150 -> 1050
B25: =Economy!I83 -> Supply and installation of Jam Panel with MR Premium Carcass, Smooth finish laminate | C25: 65.25 | D25: 1 | E25: =C25*D25 -> 65.25 | F25: Sft | G25: =C25*300 -> 19575 | H25: =D25*300 -> 300 | I25: mm | J25: 150 | K25: 1 | L25: =K25*J25*E25 -> 9787.5 | M25: =E25*150 -> 9787.5
B26: =Economy!I82 -> Supply and installation of Pelmet Panel with MR Premium Carcass, Smooth finish laminate | C26: 4 | D26: 1.5 | E26: =C26*D26 -> 6 | F26: Sft | G26: =C26*300 -> 1200 | H26: =D26*300 -> 450 | I26: mm | J26: 150 | K26: 1 | L26: =K26*J26*E26 -> 900 | M26: =E26*150 -> 900
B27: Pooja unit | M27: =E27*150 -> 0
B28: =Economy!I55 -> Supply and installation of Base storage unit with MR Premium Carcass, Plywood Border with Fluted Glass Shutter, Smooth finish laminate and soft close hinges | C28: 3 | D28: 4 | E28: =C28*D28 -> 12 | F28: Sft | G28: =C28*300 -> 900 | H28: =D28*300 -> 1200 | I28: mm | K28: 1 | L28: =K28*J28*E28 -> 0 | M28: =E28*150 -> 1800
B29: =Economy!I46 -> Supply and installation of Base storage unit with MR Premium Carcass, HDF Shutter, Smooth finish laminate and soft close hinges | C29: 3 | D29: 3 | E29: =C29*D29 -> 9 | F29: Sft | G29: =C29*300 -> 900 | H29: =D29*300 -> 900 | I29: mm | J29: 875 | K29: 1 | L29: =K29*J29*E29 -> 7875 | M29: =E29*150 -> 1350
B30: Kitchen | M30: =E30*150 -> 0
B31: =Economy!I3 -> Supply and installation of Base storage unit with BWP Carcass, HDF Shutter, Smooth finish laminate and soft close hinges | C31: 16.5 | D31: 2.75 | E31: =C31*D31 -> 45.375 | F31: Sft | G31: =C31*300 -> 4950 | H31: =D31*300 -> 825 | I31: mm | J31: 1050 | K31: 1 | L31: =K31*J31*E31 -> 47643.75 | M31: =E31*150 -> 6806.25
B32: =Economy!I4 -> Supply and installation of Wall storage unit with BWP Carcass, HDF Shutter, Smooth finish laminate and soft close hinges | C32: 13.5 | D32: 2.25 | E32: =C32*D32 -> 30.375 | F32: Sft | G32: =C32*300 -> 4050 | H32: =D32*300 -> 675 | I32: mm | J32: 1050 | K32: 1 | L32: =K32*J32*E32 -> 31893.75 | M32: =E32*150 -> 4556.25
B33: =Economy!I34 -> Supply and installation of Open unit - Inner 1mm with BWP Carcass and Smooth finish laminate | C33: 5.25 | D33: 1 | E33: =C33*D33 -> 5.25 | F33: Sft | G33: =C33*300 -> 1575 | H33: =D33*300 -> 300 | I33: mm | J33: 1050 | K33: 1 | L33: =K33*J33*E33 -> 5512.5 | M33: =E33*150 -> 787.5
B34: =Economy!I41 -> Supply and installation of Chimney Panel with BWP Carcass and Smooth finish laminate | C34: 3.25 | D34: 1 | E34: =C34*D34 -> 3.25 | F34: Sft | G34: =C34*300 -> 975 | H34: =D34*300 -> 300 | I34: mm | J34: 75 | K34: 1 | L34: =K34*J34*E34 -> 243.75 | M34: =E34*150 -> 487.5
B35: =Economy!I33 -> Supply and installation of Open unit - Inner 0.8mm with BWP Carcass and Smooth finish laminate | C35: 2 | D35: 4.25 | E35: =C35*D35 -> 8.5 | F35: Sft | G35: =C35*300 -> 600 | H35: =D35*300 -> 1275 | I35: mm | J35: 1050 | K35: 1 | L35: =K35*J35*E35 -> 8925 | M35: =E35*150 -> 1275
B36: =Economy!I75 -> Supply and installation of Loft Frame and Shutter unit with MR Premium Frame, HDF Shutter, Smooth finish laminate and Soft Close hinges | C36: 18.5 | D36: 2.5 | E36: =C36*D36 -> 46.25 | F36: Sft | G36: =C36*300 -> 5550 | H36: =D36*300 -> 750 | I36: mm | J36: 600 | K36: 1 | L36: =K36*J36*E36 -> 27750 | M36: =E36*150 -> 6937.5
B37: =Economy!I81 -> Supply and installation of Wall Panel with MR Premium Carcass, Smooth finish laminate | C37: 16.5 | D37: 2 | E37: =C37*D37 -> 33 | F37: Sft | G37: =C37*300 -> 4950 | H37: =D37*300 -> 600 | I37: mm | J37: 75 | K37: 1 | L37: =K37*J37*E37 -> 2475 | M37: =E37*150 -> 4950
B38: Master Bedroom | M38: =E38*150 -> 0
B39: =Economy!I49 -> Supply and installation of Wardrobe with MR Premium Carcass, HDF Shutter, Smooth finish laminate and soft close hinges | C39: 6.5 | D39: 7 | E39: =C39*D39 -> 45.5 | F39: Sft | G39: =C39*300 -> 1950 | H39: =D39*300 -> 2100 | I39: mm | J39: 875 | K39: 1 | L39: =K39*J39*E39 -> 39812.5 | M39: =E39*150 -> 6825
B40: =Economy!I48 -> Supply and installation of Tall storage unit with MR Premium Carcass, HDF Shutter, Smooth finish laminate and soft close hinges | C40: 2 | D40: 7 | E40: 15 | F40: Sft | G40: =C40*300 -> 600 | H40: =D40*300 -> 2100 | I40: mm | J40: 875 | K40: 1 | L40: =K40*J40*E40 -> 13125 | M40: =E40*150 -> 2250
B41: =Economy!I75 -> Supply and installation of Loft Frame and Shutter unit with MR Premium Frame, HDF Shutter, Smooth finish laminate and Soft Close hinges | C41: 9.5 | D41: 2.5 | E41: =C41*D41 -> 23.75 | F41: Sft | G41: =C41*300 -> 2850 | H41: =D41*300 -> 750 | I41: mm | J41: 600 | K41: 1 | L41: =K41*J41*E41 -> 14250 | M41: =E41*150 -> 3562.5
B42: =Economy!I76 -> Supply and installation of Ledge with 25mm Ledge MR Premium and Smooth finish laminate | C42: 10.75 | D42: 1 | E42: =C42*D42 -> 10.75 | F42: Sft | G42: =C42*300 -> 3225 | H42: =D42*300 -> 300 | I42: mm | J42: 495 | K42: 1 | L42: =K42*J42*E42 -> 5321.25 | M42: =E42*150 -> 1612.5
B43: =Economy!I76 -> Supply and installation of Ledge with 25mm Ledge MR Premium and Smooth finish laminate | C43: 5 | D43: 1.5 | E43: =C43*D43 -> 7.5 | F43: Sft | G43: =C43*300 -> 1500 | H43: =D43*300 -> 450 | I43: mm | J43: 495 | K43: 1 | L43: =K43*J43*E43 -> 3712.5 | M43: =E43*150 -> 1125
B44: =Economy!I50 -> Supply and installation of Drawer Storage with MR Premium Carcass, HDF Shutter, Smooth finish laminate and soft close hinges | C44: 1.5 | D44: 1.5 | E44: =C44*D44 -> 2.25 | F44: Sft | G44: =C44*300 -> 450 | H44: =D44*300 -> 450 | I44: mm | J44: 875 | K44: 1 | L44: =K44*J44*E44 -> 1968.75 | M44: =E44*150 -> 337.5
B45: =Economy!I47 -> Supply and installation of Wall storage unit with MR Premium Carcass, HDF Shutter, Smooth finish laminate and soft close hinges | C45: 2 | D45: 5 | E45: =C45*D45 -> 10 | F45: Sft | G45: =C45*300 -> 600 | H45: =D45*300 -> 1500 | I45: mm | J45: 875 | K45: 1 | L45: =K45*J45*E45 -> 8750 | M45: =E45*150 -> 1500
B46: =Economy!I47 -> Supply and installation of Wall storage unit with MR Premium Carcass, HDF Shutter, Smooth finish laminate and soft close hinges | C46: 1.75 | D46: 1.5 | E46: =C46*D46 -> 2.625 | F46: Sft | G46: =C46*300 -> 525 | H46: =D46*300 -> 450 | I46: mm | J46: 875 | K46: 1 | L46: =K46*J46*E46 -> 2296.875 | M46: =E46*150 -> 393.75
B47: =Economy!I82 -> Supply and installation of Pelmet Panel with MR Premium Carcass, Smooth finish laminate | C47: 4 | D47: 1.5 | E47: =C47*D47 -> 6 | F47: Sft | G47: =C47*300 -> 1200 | H47: =D47*300 -> 450 | I47: mm | J47: 150 | K47: 1 | L47: =K47*J47*E47 -> 900 | M47: =E47*150 -> 900
B48: Mother's bedroom | M48: =E48*150 -> 0
B49: =Economy!I49 -> Supply and installation of Wardrobe with MR Premium Carcass, HDF Shutter, Smooth finish laminate and soft close hinges | C49: 5.75 | D49: 8 | E49: =C49*D49 -> 46 | F49: Sft | G49: =C49*300 -> 1725 | H49: =D49*300 -> 2400 | I49: mm | J49: 875 | K49: 1 | L49: =K49*J49*E49 -> 40250 | M49: =E49*150 -> 6900
B50: =Economy!I46 -> Supply and installation of Base storage unit with MR Premium Carcass, HDF Shutter, Smooth finish laminate and soft close hinges | C50: 5.5 | D50: 2 | E50: =C50*D50 -> 11 | F50: Sft | G50: =C50*300 -> 1650 | H50: =D50*300 -> 600 | I50: mm | J50: 875 | K50: 1 | L50: =K50*J50*E50 -> 9625 | M50: =E50*150 -> 1650
B51: =Economy!I75 -> Supply and installation of Loft Frame and Shutter unit with MR Premium Frame, HDF Shutter, Smooth finish laminate and Soft Close hinges | C51: 11.25 | D51: 1.5 | E51: =C51*D51 -> 16.875 | F51: Sft | G51: =C51*300 -> 3375 | H51: =D51*300 -> 450 | I51: mm | J51: 600 | K51: 1 | L51: =K51*J51*E51 -> 10125 | M51: =E51*150 -> 2531.25
B52: =Economy!I85 -> Supply and installation of Base Panel with MR Premium Carcass, Smooth finish laminate | C52: 7.5 | D52: 2 | E52: =C52*D52 -> 15 | F52: Sft | G52: =C52*300 -> 2250 | H52: =D52*300 -> 600 | I52: mm | J52: 75 | K52: 1 | L52: =K52*J52*E52 -> 1125 | M52: =E52*150 -> 2250
B53: =Economy!I76 -> Supply and installation of Ledge with 25mm Ledge MR Premium and Smooth finish laminate | C53: 3 | D53: 1 | E53: =C53*D53 -> 3 | F53: Sft | G53: =C53*300 -> 900 | H53: =D53*300 -> 300 | I53: mm | J53: 495 | K53: 1 | L53: =K53*J53*E53 -> 1485 | M53: =E53*150 -> 450
B54: =Economy!I80 -> Supply and installation of Chamfered Wall Panel with MR Premium Carcass, Smooth finish laminate | C54: 2 | D54: 3.5 | E54: =C54*D54 -> 7 | F54: Sft | G54: =C54*300 -> 600 | H54: =D54*300 -> 1050 | I54: mm | J54: 150 | K54: 1 | L54: =K54*J54*E54 -> 1050 | M54: =E54*150 -> 1050
B55: =Economy!I50 -> Supply and installation of Drawer Storage with MR Premium Carcass, HDF Shutter, Smooth finish laminate and soft close hinges | C55: 2 | D55: 1.5 | E55: 7.1 | F55: Sft | G55: 1425 | H55: 450 | I55: mm | J55: 875 | K55: 1 | L55: =K55*J55*E55 -> 6212.5 | M55: =E55*150 -> 1065
B56: =Economy!I82 -> Supply and installation of Pelmet Panel with MR Premium Carcass, Smooth finish laminate | C56: 4 | D56: 1.5 | E56: =C56*D56 -> 6 | F56: Sft | G56: =C56*300 -> 1200 | H56: =D56*300 -> 450 | I56: mm | J56: 150 | K56: 1 | L56: =K56*J56*E56 -> 900 | M56: =E56*150 -> 900
B57: Son's Bedroom | M57: =E57*150 -> 0
B58: =Economy!I49 -> Supply and installation of Wardrobe with MR Premium Carcass, HDF Shutter, Smooth finish laminate and soft close hinges | C58: 6.5 | D58: 7 | E58: =C58*D58 -> 45.5 | F58: Sft | G58: =C58*300 -> 1950 | H58: =D58*300 -> 2100 | I58: mm | J58: 875 | K58: 1 | L58: =K58*J58*E58 -> 39812.5 | M58: =E58*150 -> 6825
B59: =Economy!I76 -> Supply and installation of Ledge with 25mm Ledge MR Premium and Smooth finish laminate | C59: 10.25 | D59: 2.25 | E59: =C59*D59 -> 23.0625 | F59: Sft | G59: =C59*300 -> 3075 | H59: =D59*300 -> 675 | I59: mm | J59: 495 | K59: 1 | L59: =K59*J59*E59 -> 11415.938 | M59: =E59*150 -> 3459.375
B60: =Economy!I85 -> Supply and installation of Base Panel with MR Premium Carcass, Smooth finish laminate | C60: 3 | D60: 2 | E60: =C60*D60 -> 6 | F60: Sft | G60: =C60*300 -> 900 | H60: =D60*300 -> 600 | I60: mm | J60: 75 | K60: 1 | L60: =K60*J60*E60 -> 450 | M60: =E60*150 -> 900
